Workbook

Sheet Brand
A1: Brand Code | B1: Brand Name | C1: Country | D1: INSERT INTO medical_supply_brand (name, country, code) VALUES ('3M', 'United States', '3M');
A2: BRAND-001 | B2: 3M™ | C2: Mỹ | D2: ="INSERT INTO medical_supply_brand (name, country, code) VALUES ('"&SUBSTITUTE(B2,"'","''")&"', '"&SUBSTITUTE(C2,"'","''")&"', '"&SUBSTITUTE(A2,"'","''")&"');" -> INSERT INTO medical_supply_brand (name, country, code) VALUES ('3M™', 'Mỹ', 'BRAND-001');
A3: BRAND-002 | B3: Abbott | C3: Mỹ | D3: ="INSERT INTO medical_supply_brand (name, country, code) VALUES ('"&SUBSTITUTE(B3,"'","''")&"', '"&SUBSTITUTE(C3,"'","''")&"', '"&SUBSTITUTE(A3,"'","''")&"');" -> INSERT INTO medical_supply_brand (name, country, code) VALUES ('Abbott', 'Mỹ', 'BRAND-002');
A4: BRAND-003 | B4: Acon | C4: Mỹ | D4: ="INSERT INTO medical_supply_brand (name, country, code) VALUES ('"&SUBSTITUTE(B4,"'","''")&"', '"&SUBSTITUTE(C4,"'","''")&"', '"&SUBSTITUTE(A4,"'","''")&"');" -> INSERT INTO medical_supply_brand (name, country, code) VALUES ('Acon', 'Mỹ', 'BRAND-003');
A5: BRAND-004 | B5: Aveflor | C5: Cộng hòa Séc | D5: ="INSERT INTO medical_supply_brand (name, country, code) VALUES ('"&SUBSTITUTE(B5,"'","''")&"', '"&SUBSTITUTE(C5,"'","''")&"', '"&SUBSTITUTE(A5,"'","''")&"');" -> INSERT INTO medical_supply_brand (name, country, code) VALUES ('Aveflor', 'Cộng hòa Séc', 'BRAND-004');
A6: BRAND-005 | B6: Bicakcilar | C6: Thổ Nhĩ Kỳ | D6: ="INSERT INTO medical_supply_brand (name, country, code) VALUES ('"&SUBSTITUTE(B6,"'","''")&"', '"&SUBSTITUTE(C6,"'","''")&"', '"&SUBSTITUTE(A6,"'","''")&"');" -> INSERT INTO medical_supply_brand (name, country, code) VALUES ('Bicakcilar', 'Thổ Nhĩ Kỳ', 'BRAND-005');
A7: BRAND-006 | B7: Biotek | C7: Trung Quốc | D7: ="INSERT INTO medical_supply_brand (name, country, code) VALUES ('"&SUBSTITUTE(B7,"'","''")&"', '"&SUBSTITUTE(C7,"'","''")&"', '"&SUBSTITUTE(A7,"'","''")&"');" -> INSERT INTO medical_supply_brand (name, country, code) VALUES ('Biotek', 'Trung Quốc', 'BRAND-006');
A8: BRAND-007 | B8: Bornsun | C8: Trung Quốc | D8: ="INSERT INTO medical_supply_brand (name, country, code) VALUES ('"&SUBSTITUTE(B8,"'","''")&"', '"&SUBSTITUTE(C8,"'","''")&"', '"&SUBSTITUTE(A8,"'","''")&"');" -> INSERT INTO medical_supply_brand (name, country, code) VALUES ('Bornsun', 'Trung Quốc', 'BRAND-007');
A9: BRAND-008 | B9: CODY | C9: Hàn Quốc | D9: ="INSERT INTO medical_supply_brand (name, country, code) VALUES ('"&SUBSTITUTE(B9,"'","''")&"', '"&SUBSTITUTE(C9,"'","''")&"', '"&SUBSTITUTE(A9,"'","''")&"');" -> INSERT INTO medical_supply_brand (name, country, code) VALUES ('CODY', 'Hàn Quốc', 'BRAND-008');
A10: BRAND-009 | B10: CODY Health | C10: Đài Loan | D10: ="INSERT INTO medical_supply_brand (name, country, code) VALUES ('"&SUBSTITUTE(B10,"'","''")&"', '"&SUBSTITUTE(C10,"'","''")&"', '"&SUBSTITUTE(A10,"'","''")&"');" -> INSERT INTO medical_supply_brand (name, country, code) VALUES ('CODY Health', 'Đài Loan', 'BRAND-009');
A11: BRAND-010 | B11: Coloplast | C11: Đan Mạch | D11: ="INSERT INTO medical_supply_brand (name, country, code) VALUES ('"&SUBSTITUTE(B11,"'","''")&"', '"&SUBSTITUTE(C11,"'","''")&"', '"&SUBSTITUTE(A11,"'","''")&"');" -> INSERT INTO medical_supply_brand (name, country, code) VALUES ('Coloplast', 'Đan Mạch', 'BRAND-010');
A12: BRAND-011 | B12: ConvaTec | C12: Cộng hòa Dominica | D12: ="INSERT INTO medical_supply_brand (name, country, code) VALUES ('"&SUBSTITUTE(B12,"'","''")&"', '"&SUBSTITUTE(C12,"'","''")&"', '"&SUBSTITUTE(A12,"'","''")&"');" -> INSERT INTO medical_supply_brand (name, country, code) VALUES ('ConvaTec', 'Cộng hòa Dominica', 'BRAND-011');
A13: BRAND-012 | B13: Covidien | C13: Mỹ | D13: ="INSERT INTO medical_supply_brand (name, country, code) VALUES ('"&SUBSTITUTE(B13,"'","''")&"', '"&SUBSTITUTE(C13,"'","''")&"', '"&SUBSTITUTE(A13,"'","''")&"');" -> INSERT INTO medical_supply_brand (name, country, code) VALUES ('Covidien', 'Mỹ', 'BRAND-012');
... A31: BRAND-030 | B31: Jumper | C31: Trung Quốc | D31: ="INSERT INTO medical_supply_brand (name, country, code) VALUES ('"&SUBSTITUTE(B31,"'","''")&"', '"&SUBSTITUTE(C31,"'","''")&"', '"&SUBSTITUTE(A31,"'","''")&"');" -> INSERT INTO medical_supply_brand (name, country, code) VALUES ('Jumper', 'Trung Quốc', 'BRAND-030');
A32: BRAND-031 | B32: Khác | D32: ="INSERT INTO medical_supply_brand (name, country, code) VALUES ('"&SUBSTITUTE(B32,"'","''")&"', '"&SUBSTITUTE(C32,"'","''")&"', '"&SUBSTITUTE(A32,"'","''")&"');" -> INSERT INTO medical_supply_brand (name, country, code) VALUES ('Khác', '', 'BRAND-031');
A33: BRAND-032 | B33: Lepu Medical | C33: Trung Quốc | D33: ="INSERT INTO medical_supply_brand (name, country, code) VALUES ('"&SUBSTITUTE(B33,"'","''")&"', '"&SUBSTITUTE(C33,"'","''")&"', '"&SUBSTITUTE(A33,"'","''")&"');" -> INSERT INTO medical_supply_brand (name, country, code) VALUES ('Lepu Medical', 'Trung Quốc', 'BRAND-032');
A34: BRAND-033 | B34: Lohmann-Rauscher | C34: Đức | D34: ="INSERT INTO medical_supply_brand (name, country, code) VALUES ('"&SUBSTITUTE(B34,"'","''")&"', '"&SUBSTITUTE(C34,"'","''")&"', '"&SUBSTITUTE(A34,"'","''")&"');" -> INSERT INTO medical_supply_brand (name, country, code) VALUES ('Lohmann-Rauscher', 'Đức', 'BRAND-033');
A35: BRAND-034 | B35: Long-term Health | C35: Trung Quốc | D35: ="INSERT INTO medical_supply_brand (name, country, code) VALUES ('"&SUBSTITUTE(B35,"'","''")&"', '"&SUBSTITUTE(C35,"'","''")&"', '"&SUBSTITUTE(A35,"'","''")&"');" -> INSERT INTO medical_supply_brand (name, country, code) VALUES ('Long-term Health', 'Trung Quốc', 'BRAND-034');
A36: BRAND-035 | B36: Lucass | C36: Mỹ | D36: ="INSERT INTO medical_supply_brand (name, country, code) VALUES ('"&SUBSTITUTE(B36,"'","''")&"', '"&SUBSTITUTE(C36,"'","''")&"', '"&SUBSTITUTE(A36,"'","''")&"');" -> INSERT INTO medical_supply_brand (name, country, code) VALUES ('Lucass', 'Mỹ', 'BRAND-035');
A37: BRAND-036 | B37: Medis Medical | C37: Trung Quốc | D37: ="INSERT INTO medical_supply_brand (name, country, code) VALUES ('"&SUBSTITUTE(B37,"'","''")&"', '"&SUBSTITUTE(C37,"'","''")&"', '"&SUBSTITUTE(A37,"'","''")&"');" -> INSERT INTO medical_supply_brand (name, country, code) VALUES ('Medis Medical', 'Trung Quốc', 'BRAND-036');
A38: BRAND-037 | B38: Meditera | C38: Thổ Nhĩ Kỳ | D38: ="INSERT INTO medical_supply_brand (name, country, code) VALUES ('"&SUBSTITUTE(B38,"'","''")&"', '"&SUBSTITUTE(C38,"'","''")&"', '"&SUBSTITUTE(A38,"'","''")&"');" -> INSERT INTO medical_supply_brand (name, country, code) VALUES ('Meditera', 'Thổ Nhĩ Kỳ', 'BRAND-037');
A39: BRAND-038 | B39: Medtronic | C39: Mỹ | D39: ="INSERT INTO medical_supply_brand (name, country, code) VALUES ('"&SUBSTITUTE(B39,"'","''")&"', '"&SUBSTITUTE(C39,"'","''")&"', '"&SUBSTITUTE(A39,"'","''")&"');" -> INSERT INTO medical_supply_brand (name, country, code) VALUES ('Medtronic', 'Mỹ', 'BRAND-038');
A40: BRAND-039 | B40: Mepro | C40: Việt Nam | D40: ="INSERT INTO medical_supply_brand (name, country, code) VALUES ('"&SUBSTITUTE(B40,"'","''")&"', '"&SUBSTITUTE(C40,"'","''")&"', '"&SUBSTITUTE(A40,"'","''")&"');" -> INSERT INTO medical_supply_brand (name, country, code) VALUES ('Mepro', 'Việt Nam', 'BRAND-039');
A41: BRAND-040 | B41: MERA | C41: Nhật Bản | D41: ="INSERT INTO medical_supply_brand (name, country, code) VALUES ('"&SUBSTITUTE(B41,"'","''")&"', '"&SUBSTITUTE(C41,"'","''")&"', '"&SUBSTITUTE(A41,"'","''")&"');" -> INSERT INTO medical_supply_brand (name, country, code) VALUES ('MERA', 'Nhật Bản', 'BRAND-040');
A42: BRAND-041 | B42: Mera Senko | C42: Nhật Bản | D42: ="INSERT INTO medical_supply_brand (name, country, code) VALUES ('"&SUBSTITUTE(B42,"'","''")&"', '"&SUBSTITUTE(C42,"'","''")&"', '"&SUBSTITUTE(A42,"'","''")&"');" -> INSERT INTO medical_supply_brand (name, country, code) VALUES ('Mera Senko', 'Nhật Bản', 'BRAND-041');
A43: BRAND-042 | B43: Merisocks | C43: Nhật Bản | D43: ="INSERT INTO medical_supply_brand (name, country, code) VALUES ('"&SUBSTITUTE(B43,"'","''")&"', '"&SUBSTITUTE(C43,"'","''")&"', '"&SUBSTITUTE(A43,"'","''")&"');" -> INSERT INTO medical_supply_brand (name, country, code) VALUES ('Merisocks', 'Nhật Bản', 'BRAND-042');
A44: BRAND-043 | B44: MiKiDo | C44: Trung Quốc | D44: ="INSERT INTO medical_supply_brand (name, country, code) VALUES ('"&SUBSTITUTE(B44,"'","''")&"', '"&SUBSTITUTE(C44,"'","''")&"', '"&SUBSTITUTE(A44,"'","''")&"');" -> INSERT INTO medical_supply_brand (name, country, code) VALUES ('MiKiDo', 'Trung Quốc', 'BRAND-043');
... A76: BRAND-075 | B76: Yuwell | C76: Trung Quốc | D76: ="INSERT INTO medical_supply_brand (name, country, code) VALUES ('"&SUBSTITUTE(B76,"'","''")&"', '"&SUBSTITUTE(C76,"'","''")&"', '"&SUBSTITUTE(A76,"'","''")&"');" -> INSERT INTO medical_supply_brand (name, country, code) VALUES ('Yuwell', 'Trung Quốc', 'BRAND-075');

Sheet Product Category
A1: Tên danh mục | B1: Mô tả
A2: Đệm chống lở loét | B2: Phao và đệm hơi giúp phân tán áp lực, phòng ngừa và hỗ trợ điều trị loét tì đè cho người nằm hoặc ngồi lâu.
A3: Máy trợ thính | B3: Thiết bị khuếch đại âm thanh cho người nghe kém, lãng tai; có loại dây đeo, móc vành tai và nhét trong tai.
A4: Máy tăm nước | B4: Máy dùng tia nước áp lực làm sạch kẽ răng, khe nướu, hỗ trợ ngừa viêm nướu, phù hợp người niềng răng, implant.
A5: Miếng dán mụn | B5: Miếng dán hydrocolloid hút dịch mủ, nhân mụn, kháng khuẩn và hạn chế thâm sẹo.
A6: Mặt nạ xông hơi mắt | B6: Mặt nạ tự sinh nhiệt giúp thư giãn mắt, giảm mỏi mắt và hỗ trợ ngủ ngon.
A7: Máy hút áp lực âm (VAC) | B7: Máy điều trị vết thương bằng áp lực âm (NPWT), hút dịch, giảm phù nề và kích thích mô hạt cho vết thương mạn tính, khó lành.
A8: Bộ gạc áp lực âm (VAC) | B8: Bộ gạc xốp phủ vết thương dùng kèm máy hút áp lực âm, có chức năng rửa và dẫn lưu dịch trong hệ thống khép kín.
A9: Miếng dán khép miệng vết thương | B9: Miếng dán thay chỉ khâu hoặc kim bấm da, khép miệng vết thương sau phẫu thuật, tiểu phẫu hoặc chấn thương.
A10: Xịt bảo vệ da | B10: Dung dịch xịt tạo màng phim bảo vệ da khỏi nước tiểu, phân, dịch tiết, ngừa hăm và loét da.
A11: Băng dán hydrocolloid | B11: Băng dán tạo môi trường ẩm cho vết thương tiết dịch ít đến trung bình, giúp mau lành, hạn chế sẹo, chống nước.
A12: Gel bôi vết thương | B12: Gel giữ ẩm, kháng khuẩn và tái tạo mô cho vết thương hở, bỏng, trầy xước, loét, vết mổ.
... A77: Khẩu trang y tế | B77: Khẩu trang y tế lọc bụi mịn, vi khuẩn (N95).

Sheet Product
A1: Mã sản phẩm | B1: Tên sản phẩm (rút gọn) | C1: Thương hiệu | D1: Danh mục | E1: Giới thiệu | F1: Brand Code | G1: UOM (Đơn vị tính) | H1: INSERT INTO medical_supply_product (id, active, category, description, name, sub_category, code, brand_code) VALUES (269, true, 'dasd', 'asdasd', 'asdasd', 'asdasd', 'asdasd', 'IMEDICARE');
A2: PRODUCT-00001 | B2: [Greetmed] Phao chống loét cao su | C2: Greetmed | D2: Đệm chống lở loét | E2: Phao chống loét cao su Greetmed (Ø30cm, van đồng) nâng đỡ và phân tán áp lực lên vùng mông, hông, lưng, giúp phòng ngừa và hỗ trợ điều trị loét tì đè. Phù hợp cho người phải nằm hoặc ngồi lâu, dùng tại nhà hoặc cơ sở y tế. | F2: =IFERROR(INDEX(Brand!$A:$A,MATCH(TRIM(C2),Brand!$B:$B,0)),"NOT FOUND") -> BRAND-020 | G2: cái | H2: ="INSERT INTO medical_supply_product (active, category, description, name, code, brand_code, uom) VALUES (true, '"&SUBSTITUTE(D2,"'","''")&"', '"&SUBSTITUTE(E2,"'","''")&"', '"&SUBSTITUTE(B2,"'","''")&"', '"&SUBSTITUTE(A2,"'","''")&"', '"&SUBSTITUTE(F2,"'","''")&"', '"&SUBSTITUTE(G2,"'","''")&"');" -> INSERT INTO medical_supply_product (active, category, description, name, code, brand_code, uom) VALUES (true, 'Đệm chống lở loét', 'Phao chống loét cao su Greetmed (Ø30cm, van đồng) nâng đỡ và phân tán áp lực lên vùng mông, hông, lưng, giúp phòng ngừa và hỗ trợ điều trị loét tì đè. Phù hợp cho người phải nằm hoặc ngồi lâu, dùng tại nhà hoặc cơ sở y tế.', '[Greetmed] Phao chống loét cao su', 'PRODUCT-00001', 'BRAND-020', 'cái');
A3: PRODUCT-00002 | B3: [iMedicare] Đệm hơi chống lở loét - iAM-8P | C3: iMedicare | D3: Đệm chống lở loét | E3: Đệm hơi chống lở loét iMedicare iAM-8P giúp phòng ngừa và hỗ trợ điều trị lở loét cho người nằm lâu như bệnh nhân liệt, bỏng, gãy xương, sau phẫu thuật, người cao tuổi. Bơm điện chạy êm, đệm dễ gấp gọn, vệ sinh; đạt tiêu chuẩn CE. | F3: =IFERROR(INDEX(Brand!$A:$A,MATCH(TRIM(C3),Brand!$B:$B,0)),"NOT FOUND") -> BRAND-028 | G3: bộ | H3: ="INSERT INTO medical_supply_product (active, category, description, name, code, brand_code, uom) VALUES (true, '"&SUBSTITUTE(D3,"'","''")&"', '"&SUBSTITUTE(E3,"'","''")&"', '"&SUBSTITUTE(B3,"'","''")&"', '"&SUBSTITUTE(A3,"'","''")&"', '"&SUBSTITUTE(F3,"'","''")&"', '"&SUBSTITUTE(G3,"'","''")&"');" -> INSERT INTO medical_supply_product (active, category, description, name, code, brand_code, uom) VALUES (true, 'Đệm chống lở loét', 'Đệm hơi chống lở loét iMedicare iAM-8P giúp phòng ngừa và hỗ trợ điều trị lở loét cho người nằm lâu như bệnh nhân liệt, bỏng, gãy xương, sau phẫu thuật, người cao tuổi. Bơm điện chạy êm, đệm dễ gấp gọn, vệ sinh; đạt tiêu chuẩn CE.', '[iMedicare] Đệm hơi chống lở loét - iAM-8P', 'PRODUCT-00002', 'BRAND-028', 'bộ');
A4: PRODUCT-00003 | B4: [Lucass] Đệm hơi chống lở loét - LC-389 | C4: Lucass | D4: Đệm chống lở loét | E4: Đệm hơi chống lở loét Lucass LC-389 giúp phòng ngừa và hỗ trợ điều trị lở loét cho người nằm lâu như bệnh nhân liệt, bỏng, gãy xương, sau phẫu thuật, người cao tuổi. Bơm điện chạy êm, đệm dễ di chuyển, gấp gọn và vệ sinh. | F4: =IFERROR(INDEX(Brand!$A:$A,MATCH(TRIM(C4),Brand!$B:$B,0)),"NOT FOUND") -> BRAND-035 | G4: bộ | H4: ="INSERT INTO medical_supply_product (active, category, description, name, code, brand_code, uom) VALUES (true, '"&SUBSTITUTE(D4,"'","''")&"', '"&SUBSTITUTE(E4,"'","''")&"', '"&SUBSTITUTE(B4,"'","''")&"', '"&SUBSTITUTE(A4,"'","''")&"', '"&SUBSTITUTE(F4,"'","''")&"', '"&SUBSTITUTE(G4,"'","''")&"');" -> INSERT INTO medical_supply_product (active, category, description, name, code, brand_code, uom) VALUES (true, 'Đệm chống lở loét', 'Đệm hơi chống lở loét Lucass LC-389 giúp phòng ngừa và hỗ trợ điều trị lở loét cho người nằm lâu như bệnh nhân liệt, bỏng, gãy xương, sau phẫu thuật, người cao tuổi. Bơm điện chạy êm, đệm dễ di chuyển, gấp gọn và vệ sinh.', '[Lucass] Đệm hơi chống lở loét - LC-389', 'PRODUCT-00003', 'BRAND-035', 'bộ');
A5: PRODUCT-00004 | B5: [Rionet] Máy trợ thính có dây đeo - HA-20DX | C5: Rionet | D5: Máy trợ thính | E5: Máy trợ thính có dây Rionet HA-20DX khuếch đại âm thanh cho người nghe kém, lãng tai, đặc biệt là người cao tuổi. Nút bấm lớn dễ dùng, 10 mức âm lượng, 3 chế độ âm thanh có lọc tạp âm, dùng pin AA. | F5: =IFERROR(INDEX(Brand!$A:$A,MATCH(TRIM(C5),Brand!$B:$B,0)),"NOT FOUND") -> BRAND-052 | G5: cái | H5: ="INSERT INTO medical_supply_product (active, category, description, name, code, brand_code, uom) VALUES (true, '"&SUBSTITUTE(D5,"'","''")&"', '"&SUBSTITUTE(E5,"'","''")&"', '"&SUBSTITUTE(B5,"'","''")&"', '"&SUBSTITUTE(A5,"'","''")&"', '"&SUBSTITUTE(F5,"'","''")&"', '"&SUBSTITUTE(G5,"'","''")&"');" -> INSERT INTO medical_supply_product (active, category, description, name, code, brand_code, uom) VALUES (true, 'Máy trợ thính', 'Máy trợ thính có dây Rionet HA-20DX khuếch đại âm thanh cho người nghe kém, lãng tai, đặc biệt là người cao tuổi. Nút bấm lớn dễ dùng, 10 mức âm lượng, 3 chế độ âm thanh có lọc tạp âm, dùng pin AA.', '[Rionet] Máy trợ thính có dây đeo - HA-20DX', 'PRODUCT-00004', 'BRAND-052', 'cái');
A6: PRODUCT-00005 | B6: [Rionet] Máy trợ thính không dây - HB-23P | C6: Rionet | D6: Máy trợ thính | E6: Máy trợ thính không dây Rionet HB-23P dạng móc vành tai, màu da kín đáo, hỗ trợ người lãng tai, nghe kém ở mọi lứa tuổi. Âm thanh rõ, có lọc ồn, chỉ 2 nút điều khiển nên dễ sử dụng. | F6: =IFERROR(INDEX(Brand!$A:$A,MATCH(TRIM(C6),Brand!$B:$B,0)),"NOT FOUND") -> BRAND-052 | G6: cái | H6: ="INSERT INTO medical_supply_product (active, category, description, name, code, brand_code, uom) VALUES (true, '"&SUBSTITUTE(D6,"'","''")&"', '"&SUBSTITUTE(E6,"'","''")&"', '"&SUBSTITUTE(B6,"'","''")&"', '"&SUBSTITUTE(A6,"'","''")&"', '"&SUBSTITUTE(F6,"'","''")&"', '"&SUBSTITUTE(G6,"'","''")&"');" -> INSERT INTO medical_supply_product (active, category, description, name, code, brand_code, uom) VALUES (true, 'Máy trợ thính', 'Máy trợ thính không dây Rionet HB-23P dạng móc vành tai, màu da kín đáo, hỗ trợ người lãng tai, nghe kém ở mọi lứa tuổi. Âm thanh rõ, có lọc ồn, chỉ 2 nút điều khiển nên dễ sử dụng.', '[Rionet] Máy trợ thính không dây - HB-23P', 'PRODUCT-00005', 'BRAND-052', 'cái');
A7: PRODUCT-00006 | B7: [Rionet] Máy trợ thính không dây thông minh - HM-06 | C7: Rionet | D7: Máy trợ thính | E7: Máy trợ thính kỹ thuật số Rionet HM-06 siêu nhỏ, đeo trong tai kín đáo và thoải mái khi đeo lâu. Lọc âm và giảm ồn hiệu quả, âm thanh tự nhiên; phù hợp người trẻ, trung niên, dân văn phòng. | F7: =IFERROR(INDEX(Brand!$A:$A,MATCH(TRIM(C7),Brand!$B:$B,0)),"NOT FOUND") -> BRAND-052 | G7: cái | H7: ="INSERT INTO medical_supply_product (active, category, description, name, code, brand_code, uom) VALUES (true, '"&SUBSTITUTE(D7,"'","''")&"', '"&SUBSTITUTE(E7,"'","''")&"', '"&SUBSTITUTE(B7,"'","''")&"', '"&SUBSTITUTE(A7,"'","''")&"', '"&SUBSTITUTE(F7,"'","''")&"', '"&SUBSTITUTE(G7,"'","''")&"');" -> INSERT INTO medical_supply_product (active, category, description, name, code, brand_code, uom) VALUES (true, 'Máy trợ thính', 'Máy trợ thính kỹ thuật số Rionet HM-06 siêu nhỏ, đeo trong tai kín đáo và thoải mái khi đeo lâu. Lọc âm và giảm ồn hiệu quả, âm thanh tự nhiên; phù hợp người trẻ, trung niên, dân văn phòng.', '[Rionet] Máy trợ thính không dây thông minh - HM-06', 'PRODUCT-00006', 'BRAND-052', 'cái');
A8: PRODUCT-00007 | B8: [WaterJet] Máy tăm nước - Cordless Maxi | C8: WaterJet | D8: Máy tăm nước | E8: Máy tăm nước không dây WaterJet Cordless Maxi làm sạch kẽ răng, khe nướu và vùng khó chải, giúp ngừa viêm nướu. Áp lực 40–90 PSI với 4 chế độ, bình chứa lớn; phù hợp người niềng răng, implant, bọc sứ, nướu nhạy cảm. | F8: =IFERROR(INDEX(Brand!$A:$A,MATCH(TRIM(C8),Brand!$B:$B,0)),"NOT FOUND") -> BRAND-069 | G8: cái | H8: ="INSERT INTO medical_supply_product (active, category, description, name, code, brand_code, uom) VALUES (true, '"&SUBSTITUTE(D8,"'","''")&"', '"&SUBSTITUTE(E8,"'","''")&"', '"&SUBSTITUTE(B8,"'","''")&"', '"&SUBSTITUTE(A8,"'","''")&"', '"&SUBSTITUTE(F8,"'","''")&"', '"&SUBSTITUTE(G8,"'","''")&"');" -> INSERT INTO medical_supply_product (active, category, description, name, code, brand_code, uom) VALUES (true, 'Máy tăm nước', 'Máy tăm nước không dây WaterJet Cordless Maxi làm sạch kẽ răng, khe nướu và vùng khó chải, giúp ngừa viêm nướu. Áp lực 40–90 PSI với 4 chế độ, bình chứa lớn; phù hợp người niềng răng, implant, bọc sứ, nướu nhạy cảm.', '[WaterJet] Máy tăm nước - Cordless Maxi', 'PRODUCT-00007', 'BRAND-069', 'cái');
A9: PRODUCT-00008 | B9: [Young Chemical Vina] Miếng dán mụn - Somaderm Spot S (32 miếng) | C9: Young Chemical Vina | D9: Miếng dán mụn | E9: Miếng dán mụn Somaderm Spot chứa hydrocolloid giúp hút dịch mủ, nhân mụn, kháng khuẩn và hạn chế sẹo thâm. Miếng tròn nhỏ, cùng màu da, chống nước, dùng được cho mọi loại da. | F9: =IFERROR(INDEX(Brand!$A:$A,MATCH(TRIM(C9),Brand!$B:$B,0)),"NOT FOUND") -> BRAND-073 | G9: miếng | H9: ="INSERT INTO medical_supply_product (active, category, description, name, code, brand_code, uom) VALUES (true, '"&SUBSTITUTE(D9,"'","''")&"', '"&SUBSTITUTE(E9,"'","''")&"', '"&SUBSTITUTE(B9,"'","''")&"', '"&SUBSTITUTE(A9,"'","''")&"', '"&SUBSTITUTE(F9,"'","''")&"', '"&SUBSTITUTE(G9,"'","''")&"');" -> INSERT INTO medical_supply_product (active, category, description, name, code, brand_code, uom) VALUES (true, 'Miếng dán mụn', 'Miếng dán mụn Somaderm Spot chứa hydrocolloid giúp hút dịch mủ, nhân mụn, kháng khuẩn và hạn chế sẹo thâm. Miếng tròn nhỏ, cùng màu da, chống nước, dùng được cho mọi loại da.', '[Young Chemical Vina] Miếng dán mụn - Somaderm Spot S (32 miếng)', 'PRODUCT-00008', 'BRAND-073', 'miếng');
A10: PRODUCT-00009 | B10: [Young Chemical Vina] Miếng dán mụn - Somaderm-Thin (Ø10mm) | C10: Young Chemical Vina | D10: Miếng dán mụn | E10: Miếng dán mụn Somaderm-Thin chứa hydrocolloid giúp hút dịch mủ, nhân mụn, giữ ẩm và hạn chế thâm sẹo. Miếng tròn siêu mỏng, cùng màu da, ít kích ứng, dùng được cho da nhạy cảm. | F10: =IFERROR(INDEX(Brand!$A:$A,MATCH(TRIM(C10),Brand!$B:$B,0)),"NOT FOUND") -> BRAND-073 | G10: miếng | H10: ="INSERT INTO medical_supply_product (active, category, description, name, code, brand_code, uom) VALUES (true, '"&SUBSTITUTE(D10,"'","''")&"', '"&SUBSTITUTE(E10,"'","''")&"', '"&SUBSTITUTE(B10,"'","''")&"', '"&SUBSTITUTE(A10,"'","''")&"', '"&SUBSTITUTE(F10,"'","''")&"', '"&SUBSTITUTE(G10,"'","''")&"');" -> INSERT INTO medical_supply_product (active, category, description, name, code, brand_code, uom) VALUES (true, 'Miếng dán mụn', 'Miếng dán mụn Somaderm-Thin chứa hydrocolloid giúp hút dịch mủ, nhân mụn, giữ ẩm và hạn chế thâm sẹo. Miếng tròn siêu mỏng, cùng màu da, ít kích ứng, dùng được cho da nhạy cảm.', '[Young Chemical Vina] Miếng dán mụn - Somaderm-Thin (Ø10mm)', 'PRODUCT-00009', 'BRAND-073', 'miếng');
A11: PRODUCT-00010 | B11: Mặt nạ xông hơi mắt ngải cứu - Mugwort Steam Eyes Mask | C11: Khác | D11: Mặt nạ xông hơi mắt | E11: Mặt nạ xông hơi mắt ngải cứu tự sinh nhiệt khoảng 40°C khi mở, giúp thư giãn mắt, giảm mỏi mắt và quầng thâm, hỗ trợ ngủ ngon. Phù hợp người thường dùng máy tính, đọc sách, thức khuya, mất ngủ. | F11: =IFERROR(INDEX(Brand!$A:$A,MATCH(TRIM(C11),Brand!$B:$B,0)),"NOT FOUND") -> BRAND-031 | G11: miếng | H11: ="INSERT INTO medical_supply_product (active, category, description, name, code, brand_code, uom) VALUES (true, '"&SUBSTITUTE(D11,"'","''")&"', '"&SUBSTITUTE(E11,"'","''")&"', '"&SUBSTITUTE(B11,"'","''")&"', '"&SUBSTITUTE(A11,"'","''")&"', '"&SUBSTITUTE(F11,"'","''")&"', '"&SUBSTITUTE(G11,"'","''")&"');" -> INSERT INTO medical_supply_product (active, category, description, name, code, brand_code, uom) VALUES (true, 'Mặt nạ xông hơi mắt', 'Mặt nạ xông hơi mắt ngải cứu tự sinh nhiệt khoảng 40°C khi mở, giúp thư giãn mắt, giảm mỏi mắt và quầng thâm, hỗ trợ ngủ ngon. Phù hợp người thường dùng máy tính, đọc sách, thức khuya, mất ngủ.', 'Mặt nạ xông hơi mắt ngải cứu - Mugwort Steam Eyes Mask', 'PRODUCT-00010', 'BRAND-031', 'miếng');
A12: PRODUCT-00011 | B12: [3M™] Bộ gạc xốp phủ vết thương điều trị áp lực âm VAC kèm chức năng rửa - Veraflo™ | C12: 3M™ | D12: Bộ gạc áp lực âm (VAC) | E12: Bộ gạc xốp 3M™ Veraflo™ dùng kèm máy hút áp lực âm VAC có chức năng rửa, điều trị vết thương mạn tính, khó lành. Hệ thống khép kín giúp rửa, dẫn lưu dịch, giữ ẩm và kích thích mô hạt phát triển. | F12: =IFERROR(INDEX(Brand!$A:$A,MATCH(TRIM(C12),Brand!$B:$B,0)),"NOT FOUND") -> BRAND-001 | G12: bộ | H12: ="INSERT INTO medical_supply_product (active, category, description, name, code, brand_code, uom) VALUES (true, '"&SUBSTITUTE(D12,"'","''")&"', '"&SUBSTITUTE(E12,"'","''")&"', '"&SUBSTITUTE(B12,"'","''")&"', '"&SUBSTITUTE(A12,"'","''")&"', '"&SUBSTITUTE(F12,"'","''")&"', '"&SUBSTITUTE(G12,"'","''")&"');" -> INSERT INTO medical_supply_product (active, category, description, name, code, brand_code, uom) VALUES (true, 'Bộ gạc áp lực âm (VAC)', 'Bộ gạc xốp 3M™ Veraflo™ dùng kèm máy hút áp lực âm VAC có chức năng rửa, điều trị vết thương mạn tính, khó lành. Hệ thống khép kín giúp rửa, dẫn lưu dịch, giữ ẩm và kích thích mô hạt phát triển.', '[3M™] Bộ gạc xốp phủ vết thương điều trị áp lực âm VAC kèm chức năng rửa - Veraflo™', 'PRODUCT-00011', 'BRAND-001', 'bộ');
A13: PRODUCT-00012 | B13: [3M™] Miếng dán vết thương thay chỉ khâu - STERI-STRIP™ (3mmx75mm) | C13: 3M™ | D13: Miếng dán khép miệng vết thương | E13: Miếng dán 3M™ Steri-Strip™ thay chỉ khâu hoặc kim bấm da, giúp khép miệng vết thương sau phẫu thuật, tiểu phẫu hoặc vết rách do chấn thương. Không xâm lấn, thao tác dễ, hạn chế giãn sẹo. | F13: =IFERROR(INDEX(Brand!$A:$A,MATCH(TRIM(C13),Brand!$B:$B,0)),"NOT FOUND") -> BRAND-001 | G13: sợi | H13: ="INSERT INTO medical_supply_product (active, category, description, name, code, brand_code, uom) VALUES (true, '"&SUBSTITUTE(D13,"'","''")&"', '"&SUBSTITUTE(E13,"'","''")&"', '"&SUBSTITUTE(B13,"'","''")&"', '"&SUBSTITUTE(A13,"'","''")&"', '"&SUBSTITUTE(F13,"'","''")&"', '"&SUBSTITUTE(G13,"'","''")&"');" -> INSERT INTO medical_supply_product (active, category, description, name, code, brand_code, uom) VALUES (true, 'Miếng dán khép miệng vết thương', 'Miếng dán 3M™ Steri-Strip™ thay chỉ khâu hoặc kim bấm da, giúp khép miệng vết thương sau phẫu thuật, tiểu phẫu hoặc vết rách do chấn thương. Không xâm lấn, thao tác dễ, hạn chế giãn sẹo.', '[3M™] Miếng dán vết thương thay chỉ khâu - STERI-STRIP™ (3mmx75mm)', 'PRODUCT-00012', 'BRAND-001', 'sợi');
... A219: PRODUCT-00218 | B219: [Bornsun] Hệ thống dẫn lưu phân | C219: Bornsun | D219: Hệ thống dẫn lưu phân | E219: Hệ thống dẫn lưu phân Bornsun bằng gel silica y tế, thu gom phân lỏng, bán lỏng cho bệnh nhân nằm lâu, đặc biệt tại ICU. Bảo vệ da quanh hậu môn, ngừa nhiễm trùng và giảm công chăm sóc; dùng 1 lần. | F219: =IFERROR(INDEX(Brand!$A:$A,MATCH(TRIM(C219),Brand!$B:$B,0)),"NOT FOUND") -> BRAND-007 | G219: bộ | H219: ="INSERT INTO medical_supply_product (active, category, description, name, code, brand_code, uom) VALUES (true, '"&SUBSTITUTE(D219,"'","''")&"', '"&SUBSTITUTE(E219,"'","''")&"', '"&SUBSTITUTE(B219,"'","''")&"', '"&SUBSTITUTE(A219,"'","''")&"', '"&SUBSTITUTE(F219,"'","''")&"', '"&SUBSTITUTE(G219,"'","''")&"');" -> INSERT INTO medical_supply_product (active, category, description, name, code, brand_code, uom) VALUES (true, 'Hệ thống dẫn lưu phân', 'Hệ thống dẫn lưu phân Bornsun bằng gel silica y tế, thu gom phân lỏng, bán lỏng cho bệnh nhân nằm lâu, đặc biệt tại ICU. Bảo vệ da quanh hậu môn, ngừa nhiễm trùng và giảm công chăm sóc; dùng 1 lần.', '[Bornsun] Hệ thống dẫn lưu phân', 'PRODUCT-00218', 'BRAND-007', 'bộ');
A220: PRODUCT-00219 | B220: [Covidien] Máy bơm thức ăn - Kangaroo ePump™ | C220: Covidien | D220: Máy bơm thức ăn | F220: =IFERROR(INDEX(Brand!$A:$A,MATCH(TRIM(C220),Brand!$B:$B,0)),"NOT FOUND") -> BRAND-012 | G220: cái | H220: ="INSERT INTO medical_supply_product (active, category, description, name, code, brand_code, uom) VALUES (true, '"&SUBSTITUTE(D220,"'","''")&"', '"&SUBSTITUTE(E220,"'","''")&"', '"&SUBSTITUTE(B220,"'","''")&"', '"&SUBSTITUTE(A220,"'","''")&"', '"&SUBSTITUTE(F220,"'","''")&"', '"&SUBSTITUTE(G220,"'","''")&"');" -> INSERT INTO medical_supply_product (active, category, description, name, code, brand_code, uom) VALUES (true, 'Máy bơm thức ăn', '', '[Covidien] Máy bơm thức ăn - Kangaroo ePump™', 'PRODUCT-00219', 'BRAND-012', 'cái');
A221: PRODUCT-00220 | B221: [Covidien] Ống thông dạ dày nuôi ăn 29 ngày - Kangaroo | C221: Covidien | D221: Ống thông nuôi ăn | E221: Ống thông dạ dày silicone Kangaroo lưu ống đến 29 ngày, dùng đưa dinh dưỡng, thuốc vào dạ dày hoặc rửa, giảm áp dạ dày. Ít phải thay ống, giảm tổn thương mũi họng. | F221: =IFERROR(INDEX(Brand!$A:$A,MATCH(TRIM(C221),Brand!$B:$B,0)),"NOT FOUND") -> BRAND-012 | G221: cái | H221: ="INSERT INTO medical_supply_product (active, category, description, name, code, brand_code, uom) VALUES (true, '"&SUBSTITUTE(D221,"'","''")&"', '"&SUBSTITUTE(E221,"'","''")&"', '"&SUBSTITUTE(B221,"'","''")&"', '"&SUBSTITUTE(A221,"'","''")&"', '"&SUBSTITUTE(F221,"'","''")&"', '"&SUBSTITUTE(G221,"'","''")&"');" -> INSERT INTO medical_supply_product (active, category, description, name, code, brand_code, uom) VALUES (true, 'Ống thông nuôi ăn', 'Ống thông dạ dày silicone Kangaroo lưu ống đến 29 ngày, dùng đưa dinh dưỡng, thuốc vào dạ dày hoặc rửa, giảm áp dạ dày. Ít phải thay ống, giảm tổn thương mũi họng.', '[Covidien] Ống thông dạ dày nuôi ăn 29 ngày - Kangaroo', 'PRODUCT-00220', 'BRAND-012', 'cái');
A222: PRODUCT-00221 | B222: [Create Medic] Bộ mở thông dạ dày qua da - Cliny | C222: Create Medic | D222: Bộ mở thông dạ dày qua da | E222: Bộ mở thông dạ dày qua da Cliny bằng 100% silicone y tế, không latex, nuôi ăn qua thành bụng cho người tắc nghẽn tiêu hóa, tai biến, chấn thương đầu cổ. Ống 2 nòng: cổng bơm thức ăn có nắp và cổng van bơm bóng cố định. | F222: =IFERROR(INDEX(Brand!$A:$A,MATCH(TRIM(C222),Brand!$B:$B,0)),"NOT FOUND") -> BRAND-013 | G222: cái | H222: ="INSERT INTO medical_supply_product (active, category, description, name, code, brand_code, uom) VALUES (true, '"&SUBSTITUTE(D222,"'","''")&"', '"&SUBSTITUTE(E222,"'","''")&"', '"&SUBSTITUTE(B222,"'","''")&"', '"&SUBSTITUTE(A222,"'","''")&"', '"&SUBSTITUTE(F222,"'","''")&"', '"&SUBSTITUTE(G222,"'","''")&"');" -> INSERT INTO medical_supply_product (active, category, description, name, code, brand_code, uom) VALUES (true, 'Bộ mở thông dạ dày qua da', 'Bộ mở thông dạ dày qua da Cliny bằng 100% silicone y tế, không latex, nuôi ăn qua thành bụng cho người tắc nghẽn tiêu hóa, tai biến, chấn thương đầu cổ. Ống 2 nòng: cổng bơm thức ăn có nắp và cổng van bơm bóng cố định.', '[Create Medic] Bộ mở thông dạ dày qua da - Cliny', 'PRODUCT-00221', 'BRAND-013', 'cái');
A223: PRODUCT-00222 | B223: [Daesang Wellife] Sữa dinh dưỡng dành cho người tiểu đường - Nucare Glucose Plan (200ml) | C223: Daesang Wellife | D223: Sữa dinh dưỡng | E223: Sữa NUCARE Glucose Plan dinh dưỡng cân bằng dành riêng cho người tiểu đường, giúp kiểm soát đường huyết sau ăn. Dùng thay bữa chính hoặc bữa phụ; hương vị dễ uống. | F223: =IFERROR(INDEX(Brand!$A:$A,MATCH(TRIM(C223),Brand!$B:$B,0)),"NOT FOUND") -> BRAND-014 | G223: hộp | H223: ="INSERT INTO medical_supply_product (active, category, description, name, code, brand_code, uom) VALUES (true, '"&SUBSTITUTE(D223,"'","''")&"', '"&SUBSTITUTE(E223,"'","''")&"', '"&SUBSTITUTE(B223,"'","''")&"', '"&SUBSTITUTE(A223,"'","''")&"', '"&SUBSTITUTE(F223,"'","''")&"', '"&SUBSTITUTE(G223,"'","''")&"');" -> INSERT INTO medical_supply_product (active, category, description, name, code, brand_code, uom) VALUES (true, 'Sữa dinh dưỡng', 'Sữa NUCARE Glucose Plan dinh dưỡng cân bằng dành riêng cho người tiểu đường, giúp kiểm soát đường huyết sau ăn. Dùng thay bữa chính hoặc bữa phụ; hương vị dễ uống.', '[Daesang Wellife] Sữa dinh dưỡng dành cho người tiểu đường - Nucare Glucose Plan (200ml)', 'PRODUCT-00222', 'BRAND-014', 'hộp');
A224: PRODUCT-00223 | B224: [Fortune] Bộ mở thông dạ dày qua da | C224: Fortune | D224: Bộ mở thông dạ dày qua da | E224: Bộ mở thông dạ dày qua da Fortune bằng silicone, nuôi ăn qua thành bụng tạm thời hoặc lâu dài. Ống 3 nòng: cổng bơm thức ăn, cổng bơm thuốc và cổng van bơm bóng cố định. | F224: =IFERROR(INDEX(Brand!$A:$A,MATCH(TRIM(C224),Brand!$B:$B,0)),"NOT FOUND") -> BRAND-016 | G224: cái | H224: ="INSERT INTO medical_supply_product (active, category, description, name, code, brand_code, uom) VALUES (true, '"&SUBSTITUTE(D224,"'","''")&"', '"&SUBSTITUTE(E224,"'","''")&"', '"&SUBSTITUTE(B224,"'","''")&"', '"&SUBSTITUTE(A224,"'","''")&"', '"&SUBSTITUTE(F224,"'","''")&"', '"&SUBSTITUTE(G224,"'","''")&"');" -> INSERT INTO medical_supply_product (active, category, description, name, code, brand_code, uom) VALUES (true, 'Bộ mở thông dạ dày qua da', 'Bộ mở thông dạ dày qua da Fortune bằng silicone, nuôi ăn qua thành bụng tạm thời hoặc lâu dài. Ống 3 nòng: cổng bơm thức ăn, cổng bơm thuốc và cổng van bơm bóng cố định.', '[Fortune] Bộ mở thông dạ dày qua da', 'PRODUCT-00223', 'BRAND-016', 'cái');
A225: PRODUCT-00224 | B225: [Fortune] Xông nuôi ăn silicone dài ngày | C225: Fortune | D225: Ống thông nuôi ăn | E225: Xông nuôi ăn silicone Fortune lưu ống đến 29 ngày, dùng đưa dinh dưỡng, thuốc vào dạ dày hoặc rửa, giảm áp dạ dày. Ít phải thay ống, giảm tổn thương mũi họng; tiệt trùng EO. | F225: =IFERROR(INDEX(Brand!$A:$A,MATCH(TRIM(C225),Brand!$B:$B,0)),"NOT FOUND") -> BRAND-016 | G225: cái | H225: ="INSERT INTO medical_supply_product (active, category, description, name, code, brand_code, uom) VALUES (true, '"&SUBSTITUTE(D225,"'","''")&"', '"&SUBSTITUTE(E225,"'","''")&"', '"&SUBSTITUTE(B225,"'","''")&"', '"&SUBSTITUTE(A225,"'","''")&"', '"&SUBSTITUTE(F225,"'","''")&"', '"&SUBSTITUTE(G225,"'","''")&"');" -> INSERT INTO medical_supply_product (active, category, description, name, code, brand_code, uom) VALUES (true, 'Ống thông nuôi ăn', 'Xông nuôi ăn silicone Fortune lưu ống đến 29 ngày, dùng đưa dinh dưỡng, thuốc vào dạ dày hoặc rửa, giảm áp dạ dày. Ít phải thay ống, giảm tổn thương mũi họng; tiệt trùng EO.', '[Fortune] Xông nuôi ăn silicone dài ngày', 'PRODUCT-00224', 'BRAND-016', 'cái');
A226: PRODUCT-00225 | B226: [Mepro] Dây xông dạ dày nuôi ăn silicone 30 ngày | C226: Mepro | D226: Ống thông nuôi ăn | E226: Dây xông dạ dày silicone Mepro (1200mm) lưu ống đến 30 ngày, dùng đưa dinh dưỡng, thuốc vào dạ dày hoặc hút dịch giảm áp. Ít phải thay ống, giảm tổn thương mũi họng; tiệt trùng EO. | F226: =IFERROR(INDEX(Brand!$A:$A,MATCH(TRIM(C226),Brand!$B:$B,0)),"NOT FOUND") -> BRAND-039 | G226: cái | H226: ="INSERT INTO medical_supply_product (active, category, description, name, code, brand_code, uom) VALUES (true, '"&SUBSTITUTE(D226,"'","''")&"', '"&SUBSTITUTE(E226,"'","''")&"', '"&SUBSTITUTE(B226,"'","''")&"', '"&SUBSTITUTE(A226,"'","''")&"', '"&SUBSTITUTE(F226,"'","''")&"', '"&SUBSTITUTE(G226,"'","''")&"');" -> INSERT INTO medical_supply_product (active, category, description, name, code, brand_code, uom) VALUES (true, 'Ống thông nuôi ăn', 'Dây xông dạ dày silicone Mepro (1200mm) lưu ống đến 30 ngày, dùng đưa dinh dưỡng, thuốc vào dạ dày hoặc hút dịch giảm áp. Ít phải thay ống, giảm tổn thương mũi họng; tiệt trùng EO.', '[Mepro] Dây xông dạ dày nuôi ăn silicone 30 ngày', 'PRODUCT-00225', 'BRAND-039', 'cái');
A227: PRODUCT-00226 | B227: [Nutricia] Sữa dinh dưỡng - Fortimel Power (335g) | C227: Nutricia | D227: Sữa dinh dưỡng | E227: Sữa Fortimel Power (Nutricia) giàu đạm, cao hơn 35% so với các sản phẩm thông thường, giúp người bệnh phục hồi nhanh. Phù hợp người sau mổ, người cao tuổi, người ốm cần bổ sung dinh dưỡng; dễ uống. | F227: =IFERROR(INDEX(Brand!$A:$A,MATCH(TRIM(C227),Brand!$B:$B,0)),"NOT FOUND") -> BRAND-044 | G227: hộp | H227: ="INSERT INTO medical_supply_product (active, category, description, name, code, brand_code, uom) VALUES (true, '"&SUBSTITUTE(D227,"'","''")&"', '"&SUBSTITUTE(E227,"'","''")&"', '"&SUBSTITUTE(B227,"'","''")&"', '"&SUBSTITUTE(A227,"'","''")&"', '"&SUBSTITUTE(F227,"'","''")&"', '"&SUBSTITUTE(G227,"'","''")&"');" -> INSERT INTO medical_supply_product (active, category, description, name, code, brand_code, uom) VALUES (true, 'Sữa dinh dưỡng', 'Sữa Fortimel Power (Nutricia) giàu đạm, cao hơn 35% so với các sản phẩm thông thường, giúp người bệnh phục hồi nhanh. Phù hợp người sau mổ, người cao tuổi, người ốm cần bổ sung dinh dưỡng; dễ uống.', '[Nutricia] Sữa dinh dưỡng - Fortimel Power (335g)', 'PRODUCT-00226', 'BRAND-044', 'hộp');
A228: PRODUCT-00227 | B228: [Nutricia] Sữa dinh dưỡng dành cho bệnh nhân ung thư - Forticare (125ml) | C228: Nutricia | D228: Sữa dinh dưỡng | E228: Sữa Forticare (Nutricia) dinh dưỡng chuyên biệt cho bệnh nhân ung thư, giúp ngăn ngừa và hỗ trợ điều trị sụt cân. Bổ sung năng lượng, vitamin, khoáng chất cho người suy kiệt, khó nhai nuốt, mới ốm dậy. | F228: =IFERROR(INDEX(Brand!$A:$A,MATCH(TRIM(C228),Brand!$B:$B,0)),"NOT FOUND") -> BRAND-044 | G228: chai | H228: ="INSERT INTO medical_supply_product (active, category, description, name, code, brand_code, uom) VALUES (true, '"&SUBSTITUTE(D228,"'","''")&"', '"&SUBSTITUTE(E228,"'","''")&"', '"&SUBSTITUTE(B228,"'","''")&"', '"&SUBSTITUTE(A228,"'","''")&"', '"&SUBSTITUTE(F228,"'","''")&"', '"&SUBSTITUTE(G228,"'","''")&"');" -> INSERT INTO medical_supply_product (active, category, description, name, code, brand_code, uom) VALUES (true, 'Sữa dinh dưỡng', 'Sữa Forticare (Nutricia) dinh dưỡng chuyên biệt cho bệnh nhân ung thư, giúp ngăn ngừa và hỗ trợ điều trị sụt cân. Bổ sung năng lượng, vitamin, khoáng chất cho người suy kiệt, khó nhai nuốt, mới ốm dậy.', '[Nutricia] Sữa dinh dưỡng dành cho bệnh nhân ung thư - Forticare (125ml)', 'PRODUCT-00227', 'BRAND-044', 'chai');
A229: PRODUCT-00228 | B229: [Nutricia] Sữa dinh dưỡng nuôi ăn qua ống thông - Nutrison (1000ml) | C229: Nutricia | D229: Sữa dinh dưỡng | E229: Sữa Nutrison (Nutricia) dạng nước dùng nuôi ăn qua ống thông dạ dày, cung cấp đủ dưỡng chất giúp duy trì năng lượng và phục hồi sức khỏe. Dùng 1 lần với dây nuôi ăn, hạn chế nhiễm khuẩn so với pha sữa bột. | F229: =IFERROR(INDEX(Brand!$A:$A,MATCH(TRIM(C229),Brand!$B:$B,0)),"NOT FOUND") -> BRAND-044 | G229: túi | H229: ="INSERT INTO medical_supply_product (active, category, description, name, code, brand_code, uom) VALUES (true, '"&SUBSTITUTE(D229,"'","''")&"', '"&SUBSTITUTE(E229,"'","''")&"', '"&SUBSTITUTE(B229,"'","''")&"', '"&SUBSTITUTE(A229,"'","''")&"', '"&SUBSTITUTE(F229,"'","''")&"', '"&SUBSTITUTE(G229,"'","''")&"');" -> INSERT INTO medical_supply_product (active, category, description, name, code, brand_code, uom) VALUES (true, 'Sữa dinh dưỡng', 'Sữa Nutrison (Nutricia) dạng nước dùng nuôi ăn qua ống thông dạ dày, cung cấp đủ dưỡng chất giúp duy trì năng lượng và phục hồi sức khỏe. Dùng 1 lần với dây nuôi ăn, hạn chế nhiễm khuẩn so với pha sữa bột.', '[Nutricia] Sữa dinh dưỡng nuôi ăn qua ống thông - Nutrison (1000ml)', 'PRODUCT-00228', 'BRAND-044', 'túi');
A230: PRODUCT-00229 | B230: [SeaSight] Bộ mở dạ dày qua da | C230: SeaSight | D230: Bộ mở thông dạ dày qua da | E230: Bộ mở thông dạ dày qua da SeaSight bằng silicone, nuôi ăn qua thành bụng cho người tắc nghẽn tiêu hóa, tai biến, chấn thương đầu cổ. Ống 3 nòng: cổng bơm thức ăn, cổng bơm thuốc và cổng van bơm bóng cố định. | F230: =IFERROR(INDEX(Brand!$A:$A,MATCH(TRIM(C230),Brand!$B:$B,0)),"NOT FOUND") -> BRAND-054 | G230: cái | H230: ="INSERT INTO medical_supply_product (active, category, description, name, code, brand_code, uom) VALUES (true, '"&SUBSTITUTE(D230,"'","''")&"', '"&SUBSTITUTE(E230,"'","''")&"', '"&SUBSTITUTE(B230,"'","''")&"', '"&SUBSTITUTE(A230,"'","''")&"', '"&SUBSTITUTE(F230,"'","''")&"', '"&SUBSTITUTE(G230,"'","''")&"');" -> INSERT INTO medical_supply_product (active, category, description, name, code, brand_code, uom) VALUES (true, 'Bộ mở thông dạ dày qua da', 'Bộ mở thông dạ dày qua da SeaSight bằng silicone, nuôi ăn qua thành bụng cho người tắc nghẽn tiêu hóa, tai biến, chấn thương đầu cổ. Ống 3 nòng: cổng bơm thức ăn, cổng bơm thuốc và cổng van bơm bóng cố định.', '[SeaSight] Bộ mở dạ dày qua da', 'PRODUCT-00229', 'BRAND-054', 'cái');
A231: PRODUCT-00230 | B231: [SeaSight] Dây nuôi ăn mũi - dạ dày silicone dài ngày | C231: SeaSight | D231: Ống thông nuôi ăn | E231: Dây nuôi ăn mũi - dạ dày silicone Seasight (1000mm) lưu ống đến 29 ngày, dùng đưa dinh dưỡng, thuốc vào dạ dày hoặc rửa, giảm áp dạ dày. Ít phải thay ống, giảm tổn thương mũi họng; tiệt trùng EO. | F231: =IFERROR(INDEX(Brand!$A:$A,MATCH(TRIM(C231),Brand!$B:$B,0)),"NOT FOUND") -> BRAND-054 | G231: cái | H231: ="INSERT INTO medical_supply_product (active, category, description, name, code, brand_code, uom) VALUES (true, '"&SUBSTITUTE(D231,"'","''")&"', '"&SUBSTITUTE(E231,"'","''")&"', '"&SUBSTITUTE(B231,"'","''")&"', '"&SUBSTITUTE(A231,"'","''")&"', '"&SUBSTITUTE(F231,"'","''")&"', '"&SUBSTITUTE(G231,"'","''")&"');" -> INSERT INTO medical_supply_product (active, category, description, name, code, brand_code, uom) VALUES (true, 'Ống thông nuôi ăn', 'Dây nuôi ăn mũi - dạ dày silicone Seasight (1000mm) lưu ống đến 29 ngày, dùng đưa dinh dưỡng, thuốc vào dạ dày hoặc rửa, giảm áp dạ dày. Ít phải thay ống, giảm tổn thương mũi họng; tiệt trùng EO.', '[SeaSight] Dây nuôi ăn mũi - dạ dày silicone dài ngày', 'PRODUCT-00230', 'BRAND-054', 'cái');
A232: PRODUCT-00231 | B232: [Teleflex] Ống chẹn thực quản, dạ dày - Sengstaken-Blakemore Tube | C232: Teleflex | D232: Ống chẹn thực quản dạ dày | E232: Ống chẹn thực quản - dạ dày Sengstaken-Blakemore (Teleflex RÜSCH) dùng cầm máu tạm thời khi chảy máu thực quản cấp (thường do xơ gan) trong lúc chờ điều trị triệt để. Ống 3–4 nòng có bóng chèn tại vị trí chảy máu ở thực quản hoặc dạ dày. | F232: =IFERROR(INDEX(Brand!$A:$A,MATCH(TRIM(C232),Brand!$B:$B,0)),"NOT FOUND") -> BRAND-060 | G232: cái | H232: ="INSERT INTO medical_supply_product (active, category, description, name, code, brand_code, uom) VALUES (true, '"&SUBSTITUTE(D232,"'","''")&"', '"&SUBSTITUTE(E232,"'","''")&"', '"&SUBSTITUTE(B232,"'","''")&"', '"&SUBSTITUTE(A232,"'","''")&"', '"&SUBSTITUTE(F232,"'","''")&"', '"&SUBSTITUTE(G232,"'","''")&"');" -> INSERT INTO medical_supply_product (active, category, description, name, code, brand_code, uom) VALUES (true, 'Ống chẹn thực quản dạ dày', 'Ống chẹn thực quản - dạ dày Sengstaken-Blakemore (Teleflex RÜSCH) dùng cầm máu tạm thời khi chảy máu thực quản cấp (thường do xơ gan) trong lúc chờ điều trị triệt để. Ống 3–4 nòng có bóng chèn tại vị trí chảy máu ở thực quản hoặc dạ dày.', '[Teleflex] Ống chẹn thực quản, dạ dày - Sengstaken-Blakemore Tube', 'PRODUCT-00231', 'BRAND-060', 'cái');
... A301: PRODUCT-00300 | B301: [Hollister] Vòng bảo vệ da chống loét hậu môn nhân tạo (Mẫu 7806) | C301: Hollister | D301: Phụ kiện hậu môn nhân tạo | E301: Vòng bảo vệ da Hollister 7805 dùng keo Flextend M bám chắc, tạo hàng rào chống thấm quanh hậu môn nhân tạo. Lấp khoảng hở, ngăn chất thải tiếp xúc da, giảm kích ứng và loét. | F301: =IFERROR(INDEX(Brand!$A:$A,MATCH(TRIM(C301),Brand!$B:$B,0)),"NOT FOUND") -> BRAND-024 | G301: cái | H301: ="INSERT INTO medical_supply_product (active, category, description, name, code, brand_code, uom) VALUES (true, '"&SUBSTITUTE(D301,"'","''")&"', '"&SUBSTITUTE(E301,"'","''")&"', '"&SUBSTITUTE(B301,"'","''")&"', '"&SUBSTITUTE(A301,"'","''")&"', '"&SUBSTITUTE(F301,"'","''")&"', '"&SUBSTITUTE(G301,"'","''")&"');" -> INSERT INTO medical_supply_product (active, category, description, name, code, brand_code, uom) VALUES (true, 'Phụ kiện hậu môn nhân tạo', 'Vòng bảo vệ da Hollister 7805 dùng keo Flextend M bám chắc, tạo hàng rào chống thấm quanh hậu môn nhân tạo. Lấp khoảng hở, ngăn chất thải tiếp xúc da, giảm kích ứng và loét.', '[Hollister] Vòng bảo vệ da chống loét hậu môn nhân tạo (Mẫu 7806)', 'PRODUCT-00300', 'BRAND-024', 'cái');

Sheet Product Variant
A1: Mã biến thể | B1: Mã sản phẩm | C1: Tên sản phẩm (rút gọn) | D1: Thông tin bổ sung | E1: INSERT INTO public.medical_supply_product_variant (id, additional_desc, code, color, size, product_code) VALUES (1, '11', '1', '11', '111', 'PRODUCT-00062');
A2: =B2&"-"&TEXT(COUNTIF(B$2:B2,B2),"000") -> PRODUCT-00001-001 | B2: PRODUCT-00001 | C2: =IFERROR(INDEX(Product!$B:$B,MATCH(B2,Product!$A:$A,0)),"NOT FOUND") -> [Greetmed] Phao chống loét cao su | E2: ="INSERT INTO public.medical_supply_product_variant (additional_desc, code, product_code) VALUES ("&IF(D2="","NULL","'"&SUBSTITUTE(D2,"'","''")&"'")&", '"&A2&"', '"&B2&"');" -> INSERT INTO public.medical_supply_product_variant (additional_desc, code, product_code) VALUES (NULL, 'PRODUCT-00001-001', 'PRODUCT-00001');
A3: =B3&"-"&TEXT(COUNTIF(B$2:B3,B3),"000") -> PRODUCT-00002-001 | B3: PRODUCT-00002 | C3: =IFERROR(INDEX(Product!$B:$B,MATCH(B3,Product!$A:$A,0)),"NOT FOUND") -> [iMedicare] Đệm hơi chống lở loét - iAM-8P | E3: ="INSERT INTO public.medical_supply_product_variant (additional_desc, code, product_code) VALUES ("&IF(D3="","NULL","'"&SUBSTITUTE(D3,"'","''")&"'")&", '"&A3&"', '"&B3&"');" -> INSERT INTO public.medical_supply_product_variant (additional_desc, code, product_code) VALUES (NULL, 'PRODUCT-00002-001', 'PRODUCT-00002');
A4: =B4&"-"&TEXT(COUNTIF(B$2:B4,B4),"000") -> PRODUCT-00003-001 | B4: PRODUCT-00003 | C4: =IFERROR(INDEX(Product!$B:$B,MATCH(B4,Product!$A:$A,0)),"NOT FOUND") -> [Lucass] Đệm hơi chống lở loét - LC-389 | E4: ="INSERT INTO public.medical_supply_product_variant (additional_desc, code, product_code) VALUES ("&IF(D4="","NULL","'"&SUBSTITUTE(D4,"'","''")&"'")&", '"&A4&"', '"&B4&"');" -> INSERT INTO public.medical_supply_product_variant (additional_desc, code, product_code) VALUES (NULL, 'PRODUCT-00003-001', 'PRODUCT-00003');
A5: =B5&"-"&TEXT(COUNTIF(B$2:B5,B5),"000") -> PRODUCT-00004-001 | B5: PRODUCT-00004 | C5: =IFERROR(INDEX(Product!$B:$B,MATCH(B5,Product!$A:$A,0)),"NOT FOUND") -> [Rionet] Máy trợ thính có dây đeo - HA-20DX | E5: ="INSERT INTO public.medical_supply_product_variant (additional_desc, code, product_code) VALUES ("&IF(D5="","NULL","'"&SUBSTITUTE(D5,"'","''")&"'")&", '"&A5&"', '"&B5&"');" -> INSERT INTO public.medical_supply_product_variant (additional_desc, code, product_code) VALUES (NULL, 'PRODUCT-00004-001', 'PRODUCT-00004');
A6: =B6&"-"&TEXT(COUNTIF(B$2:B6,B6),"000") -> PRODUCT-00005-001 | B6: PRODUCT-00005 | C6: =IFERROR(INDEX(Product!$B:$B,MATCH(B6,Product!$A:$A,0)),"NOT FOUND") -> [Rionet] Máy trợ thính không dây - HB-23P | E6: ="INSERT INTO public.medical_supply_product_variant (additional_desc, code, product_code) VALUES ("&IF(D6="","NULL","'"&SUBSTITUTE(D6,"'","''")&"'")&", '"&A6&"', '"&B6&"');" -> INSERT INTO public.medical_supply_product_variant (additional_desc, code, product_code) VALUES (NULL, 'PRODUCT-00005-001', 'PRODUCT-00005');
A7: =B7&"-"&TEXT(COUNTIF(B$2:B7,B7),"000") -> PRODUCT-00006-001 | B7: PRODUCT-00006 | C7: =IFERROR(INDEX(Product!$B:$B,MATCH(B7,Product!$A:$A,0)),"NOT FOUND") -> [Rionet] Máy trợ thính không dây thông minh - HM-06 | E7: ="INSERT INTO public.medical_supply_product_variant (additional_desc, code, product_code) VALUES ("&IF(D7="","NULL","'"&SUBSTITUTE(D7,"'","''")&"'")&", '"&A7&"', '"&B7&"');" -> INSERT INTO public.medical_supply_product_variant (additional_desc, code, product_code) VALUES (NULL, 'PRODUCT-00006-001', 'PRODUCT-00006');
A8: =B8&"-"&TEXT(COUNTIF(B$2:B8,B8),"000") -> PRODUCT-00007-001 | B8: PRODUCT-00007 | C8: =IFERROR(INDEX(Product!$B:$B,MATCH(B8,Product!$A:$A,0)),"NOT FOUND") -> [WaterJet] Máy tăm nước - Cordless Maxi | E8: ="INSERT INTO public.medical_supply_product_variant (additional_desc, code, product_code) VALUES ("&IF(D8="","NULL","'"&SUBSTITUTE(D8,"'","''")&"'")&", '"&A8&"', '"&B8&"');" -> INSERT INTO public.medical_supply_product_variant (additional_desc, code, product_code) VALUES (NULL, 'PRODUCT-00007-001', 'PRODUCT-00007');
A9: =B9&"-"&TEXT(COUNTIF(B$2:B9,B9),"000") -> PRODUCT-00008-001 | B9: PRODUCT-00008 | C9: =IFERROR(INDEX(Product!$B:$B,MATCH(B9,Product!$A:$A,0)),"NOT FOUND") -> [Young Chemical Vina] Miếng dán mụn - Somaderm Spot S (32 miếng) | E9: ="INSERT INTO public.medical_supply_product_variant (additional_desc, code, product_code) VALUES ("&IF(D9="","NULL","'"&SUBSTITUTE(D9,"'","''")&"'")&", '"&A9&"', '"&B9&"');" -> INSERT INTO public.medical_supply_product_variant (additional_desc, code, product_code) VALUES (NULL, 'PRODUCT-00008-001', 'PRODUCT-00008');
A10: =B10&"-"&TEXT(COUNTIF(B$2:B10,B10),"000") -> PRODUCT-00250-001 | B10: PRODUCT-00250 | C10: =IFERROR(INDEX(Product!$B:$B,MATCH(B10,Product!$A:$A,0)),"NOT FOUND") -> [Young Chemical Vina] Miếng dán mụn - Somaderm Spot (24 miếng) | E10: ="INSERT INTO public.medical_supply_product_variant (additional_desc, code, product_code) VALUES ("&IF(D10="","NULL","'"&SUBSTITUTE(D10,"'","''")&"'")&", '"&A10&"', '"&B10&"');" -> INSERT INTO public.medical_supply_product_variant (additional_desc, code, product_code) VALUES (NULL, 'PRODUCT-00250-001', 'PRODUCT-00250');
A11: =B11&"-"&TEXT(COUNTIF(B$2:B11,B11),"000") -> PRODUCT-00251-001 | B11: PRODUCT-00251 | C11: =IFERROR(INDEX(Product!$B:$B,MATCH(B11,Product!$A:$A,0)),"NOT FOUND") -> [Young Chemical Vina] Miếng dán mụn - Somaderm Spot (18 miếng) | E11: ="INSERT INTO public.medical_supply_product_variant (additional_desc, code, product_code) VALUES ("&IF(D11="","NULL","'"&SUBSTITUTE(D11,"'","''")&"'")&", '"&A11&"', '"&B11&"');" -> INSERT INTO public.medical_supply_product_variant (additional_desc, code, product_code) VALUES (NULL, 'PRODUCT-00251-001', 'PRODUCT-00251');
A12: =B12&"-"&TEXT(COUNTIF(B$2:B12,B12),"000") -> PRODUCT-00009-001 | B12: PRODUCT-00009 | C12: =IFERROR(INDEX(Product!$B:$B,MATCH(B12,Product!$A:$A,0)),"NOT FOUND") -> [Young Chemical Vina] Miếng dán mụn - Somaderm-Thin (Ø10mm) | E12: ="INSERT INTO public.medical_supply_product_variant (additional_desc, code, product_code) VALUES ("&IF(D12="","NULL","'"&SUBSTITUTE(D12,"'","''")&"'")&", '"&A12&"', '"&B12&"');" -> INSERT INTO public.medical_supply_product_variant (additional_desc, code, product_code) VALUES (NULL, 'PRODUCT-00009-001', 'PRODUCT-00009');
A13: =B13&"-"&TEXT(COUNTIF(B$2:B13,B13),"000") -> PRODUCT-00010-001 | B13: PRODUCT-00010 | C13: =IFERROR(INDEX(Product!$B:$B,MATCH(B13,Product!$A:$A,0)),"NOT FOUND") -> Mặt nạ xông hơi mắt ngải cứu - Mugwort Steam Eyes Mask | E13: ="INSERT INTO public.medical_supply_product_variant (additional_desc, code, product_code) VALUES ("&IF(D13="","NULL","'"&SUBSTITUTE(D13,"'","''")&"'")&", '"&A13&"', '"&B13&"');" -> INSERT INTO public.medical_supply_product_variant (additional_desc, code, product_code) VALUES (NULL, 'PRODUCT-00010-001', 'PRODUCT-00010');
... A95: =B95&"-"&TEXT(COUNTIF(B$2:B95,B95),"000") -> PRODUCT-00052-001 | B95: PRODUCT-00052 | C95: =IFERROR(INDEX(Product!$B:$B,MATCH(B95,Product!$A:$A,0)),"NOT FOUND") -> [CODY Health] Đai đầu gối tập luyện thể thao | E95: ="INSERT INTO public.medical_supply_product_variant (additional_desc, code, product_code) VALUES ("&IF(D95="","NULL","'"&SUBSTITUTE(D95,"'","''")&"'")&", '"&A95&"', '"&B95&"');" -> INSERT INTO public.medical_supply_product_variant (additional_desc, code, product_code) VALUES (NULL, 'PRODUCT-00052-001', 'PRODUCT-00052');
A96: =B96&"-"&TEXT(COUNTIF(B$2:B96,B96),"000") -> PRODUCT-00053-001 | B96: PRODUCT-00053 | C96: =IFERROR(INDEX(Product!$B:$B,MATCH(B96,Product!$A:$A,0)),"NOT FOUND") -> [CODY Health] Đai lưng cố định cột sống | D96: Số đo vòng bụng: 56 - 71 cm Chiều cao đai: 22 cm | E96: ="INSERT INTO public.medical_supply_product_variant (additional_desc, code, product_code) VALUES ("&IF(D96="","NULL","'"&SUBSTITUTE(D96,"'","''")&"'")&", '"&A96&"', '"&B96&"');" -> INSERT INTO public.medical_supply_product_variant (additional_desc, code, product_code) VALUES ('Số đo vòng bụng: 56 - 71 cm Chiều cao đai: 22 cm', 'PRODUCT-00053-001', 'PRODUCT-00053');
A97: =B97&"-"&TEXT(COUNTIF(B$2:B97,B97),"000") -> PRODUCT-00053-002 | B97: PRODUCT-00053 | C97: =IFERROR(INDEX(Product!$B:$B,MATCH(B97,Product!$A:$A,0)),"NOT FOUND") -> [CODY Health] Đai lưng cố định cột sống | D97: Số đo vòng bụng: 71 - 84 cm Chiều cao đai: 22 cm | E97: ="INSERT INTO public.medical_supply_product_variant (additional_desc, code, product_code) VALUES ("&IF(D97="","NULL","'"&SUBSTITUTE(D97,"'","''")&"'")&", '"&A97&"', '"&B97&"');" -> INSERT INTO public.medical_supply_product_variant (additional_desc, code, product_code) VALUES ('Số đo vòng bụng: 71 - 84 cm Chiều cao đai: 22 cm', 'PRODUCT-00053-002', 'PRODUCT-00053');
A98: =B98&"-"&TEXT(COUNTIF(B$2:B98,B98),"000") -> PRODUCT-00053-003 | B98: PRODUCT-00053 | C98: =IFERROR(INDEX(Product!$B:$B,MATCH(B98,Product!$A:$A,0)),"NOT FOUND") -> [CODY Health] Đai lưng cố định cột sống | D98: Số đo vòng bụng: 84 - 97 cm Chiều cao đai: 22 cm | E98: ="INSERT INTO public.medical_supply_product_variant (additional_desc, code, product_code) VALUES ("&IF(D98="","NULL","'"&SUBSTITUTE(D98,"'","''")&"'")&", '"&A98&"', '"&B98&"');" -> INSERT INTO public.medical_supply_product_variant (additional_desc, code, product_code) VALUES ('Số đo vòng bụng: 84 - 97 cm Chiều cao đai: 22 cm', 'PRODUCT-00053-003', 'PRODUCT-00053');
A99: =B99&"-"&TEXT(COUNTIF(B$2:B99,B99),"000") -> PRODUCT-00053-004 | B99: PRODUCT-00053 | C99: =IFERROR(INDEX(Product!$B:$B,MATCH(B99,Product!$A:$A,0)),"NOT FOUND") -> [CODY Health] Đai lưng cố định cột sống | D99: Số đo vòng bụng: 97 - 109 cm Chiều cao đai: 22 cm | E99: ="INSERT INTO public.medical_supply_product_variant (additional_desc, code, product_code) VALUES ("&IF(D99="","NULL","'"&SUBSTITUTE(D99,"'","''")&"'")&", '"&A99&"', '"&B99&"');" -> INSERT INTO public.medical_supply_product_variant (additional_desc, code, product_code) VALUES ('Số đo vòng bụng: 97 - 109 cm Chiều cao đai: 22 cm', 'PRODUCT-00053-004', 'PRODUCT-00053');
A100: =B100&"-"&TEXT(COUNTIF(B$2:B100,B100),"000") -> PRODUCT-00054-001 | B100: PRODUCT-00054 | C100: =IFERROR(INDEX(Product!$B:$B,MATCH(B100,Product!$A:$A,0)),"NOT FOUND") -> [CODY Health] Vớ đùi y khoa giãn tĩnh mạch có silicone chống trượt | D100: Vòng 1: cổ chân, ngay trên xương mắt cá chân 1cm: 18-20 cm Vòng 2: bắp chân, tại nơi lớn nhất: 31-35 cm Vòng 3: đùi, dưới bẹn 5cm: 45-53 cm Chiều dài từ bàn chân đến vòng 3: 66-76 cm | E100: ="INSERT INTO public.medical_supply_product_variant (additional_desc, code, product_code) VALUES ("&IF(D100="","NULL","'"&SUBSTITUTE(D100,"'","''")&"'")&", '"&A100&"', '"&B100&"');" -> INSERT INTO public.medical_supply_product_variant (additional_desc, code, product_code) VALUES ('Vòng 1: cổ chân, ngay trên xương mắt cá chân 1cm: 18-20 cm Vòng 2: bắp chân, tại nơi lớn nhất: 31-35 cm Vòng 3: đùi, dưới bẹn 5cm: 45-53 cm Chiều dài từ bàn chân đến vòng 3: 66-76 cm', 'PRODUCT-00054-001', 'PRODUCT-00054');
A101: =B101&"-"&TEXT(COUNTIF(B$2:B101,B101),"000") -> PRODUCT-00054-002 | B101: PRODUCT-00054 | C101: =IFERROR(INDEX(Product!$B:$B,MATCH(B101,Product!$A:$A,0)),"NOT FOUND") -> [CODY Health] Vớ đùi y khoa giãn tĩnh mạch có silicone chống trượt | D101: Vòng 1: cổ chân, ngay trên xương mắt cá chân 1cm: 20-22 cm Vòng 2: bắp chân, tại nơi lớn nhất: 33-38 cm Vòng 3: đùi, dưới bẹn 5cm: 48-56 cm Chiều dài từ bàn chân đến vòng 3: 66-76 cm | E101: ="INSERT INTO public.medical_supply_product_variant (additional_desc, code, product_code) VALUES ("&IF(D101="","NULL","'"&SUBSTITUTE(D101,"'","''")&"'")&", '"&A101&"', '"&B101&"');" -> INSERT INTO public.medical_supply_product_variant (additional_desc, code, product_code) VALUES ('Vòng 1: cổ chân, ngay trên xương mắt cá chân 1cm: 20-22 cm Vòng 2: bắp chân, tại nơi lớn nhất: 33-38 cm Vòng 3: đùi, dưới bẹn 5cm: 48-56 cm Chiều dài từ bàn chân đến vòng 3: 66-76 cm', 'PRODUCT-00054-002', 'PRODUCT-00054');
A102: =B102&"-"&TEXT(COUNTIF(B$2:B102,B102),"000") -> PRODUCT-00054-003 | B102: PRODUCT-00054 | C102: =IFERROR(INDEX(Product!$B:$B,MATCH(B102,Product!$A:$A,0)),"NOT FOUND") -> [CODY Health] Vớ đùi y khoa giãn tĩnh mạch có silicone chống trượt | D102: Vòng 1: cổ chân, ngay trên xương mắt cá chân 1cm: 22-24 cm Vòng 2: bắp chân, tại nơi lớn nhất: 34-40 cm Vòng 3: đùi, dưới bẹn 5cm: 51-59 cm Chiều dài từ bàn chân đến vòng 3: 70-80 cm | E102: ="INSERT INTO public.medical_supply_product_variant (additional_desc, code, product_code) VALUES ("&IF(D102="","NULL","'"&SUBSTITUTE(D102,"'","''")&"'")&", '"&A102&"', '"&B102&"');" -> INSERT INTO public.medical_supply_product_variant (additional_desc, code, product_code) VALUES ('Vòng 1: cổ chân, ngay trên xương mắt cá chân 1cm: 22-24 cm Vòng 2: bắp chân, tại nơi lớn nhất: 34-40 cm Vòng 3: đùi, dưới bẹn 5cm: 51-59 cm Chiều dài từ bàn chân đến vòng 3: 70-80 cm', 'PRODUCT-00054-003', 'PRODUCT-00054');
A103: =B103&"-"&TEXT(COUNTIF(B$2:B103,B103),"000") -> PRODUCT-00055-001 | B103: PRODUCT-00055 | C103: =IFERROR(INDEX(Product!$B:$B,MATCH(B103,Product!$A:$A,0)),"NOT FOUND") -> [CODY Health] Vớ gối y khoa giãn tĩnh mạch | D103: Vòng 1: cổ chân, ngay trên xương mắt cá chân 1cm: 18-20 cm Vòng 2: bắp chân, tại nơi lớn nhất: 31-35 cm Chiều dài từ bàn chân đến đoạn dưới gối: 66-76 cm | E103: ="INSERT INTO public.medical_supply_product_variant (additional_desc, code, product_code) VALUES ("&IF(D103="","NULL","'"&SUBSTITUTE(D103,"'","''")&"'")&", '"&A103&"', '"&B103&"');" -> INSERT INTO public.medical_supply_product_variant (additional_desc, code, product_code) VALUES ('Vòng 1: cổ chân, ngay trên xương mắt cá chân 1cm: 18-20 cm Vòng 2: bắp chân, tại nơi lớn nhất: 31-35 cm Chiều dài từ bàn chân đến đoạn dưới gối: 66-76 cm', 'PRODUCT-00055-001', 'PRODUCT-00055');
A104: =B104&"-"&TEXT(COUNTIF(B$2:B104,B104),"000") -> PRODUCT-00055-002 | B104: PRODUCT-00055 | C104: =IFERROR(INDEX(Product!$B:$B,MATCH(B104,Product!$A:$A,0)),"NOT FOUND") -> [CODY Health] Vớ gối y khoa giãn tĩnh mạch | D104: Vòng 1: cổ chân, ngay trên xương mắt cá chân 1cm: 20-22 cm Vòng 2: bắp chân, tại nơi lớn nhất: 33-38 cm Chiều dài từ bàn chân đến đoạn dưới gối: 66-76 cm | E104: ="INSERT INTO public.medical_supply_product_variant (additional_desc, code, product_code) VALUES ("&IF(D104="","NULL","'"&SUBSTITUTE(D104,"'","''")&"'")&", '"&A104&"', '"&B104&"');" -> INSERT INTO public.medical_supply_product_variant (additional_desc, code, product_code) VALUES ('Vòng 1: cổ chân, ngay trên xương mắt cá chân 1cm: 20-22 cm Vòng 2: bắp chân, tại nơi lớn nhất: 33-38 cm Chiều dài từ bàn chân đến đoạn dưới gối: 66-76 cm', 'PRODUCT-00055-002', 'PRODUCT-00055');
A105: =B105&"-"&TEXT(COUNTIF(B$2:B105,B105),"000") -> PRODUCT-00055-003 | B105: PRODUCT-00055 | C105: =IFERROR(INDEX(Product!$B:$B,MATCH(B105,Product!$A:$A,0)),"NOT FOUND") -> [CODY Health] Vớ gối y khoa giãn tĩnh mạch | D105: Vòng 1: cổ chân, ngay trên xương mắt cá chân 1cm: 22-24 cm Vòng 2: bắp chân, tại nơi lớn nhất: 34-40 cm Chiều dài từ bàn chân đến đoạn dưới gối: 70-80 cm | E105: ="INSERT INTO public.medical_supply_product_variant (additional_desc, code, product_code) VALUES ("&IF(D105="","NULL","'"&SUBSTITUTE(D105,"'","''")&"'")&", '"&A105&"', '"&B105&"');" -> INSERT INTO public.medical_supply_product_variant (additional_desc, code, product_code) VALUES ('Vòng 1: cổ chân, ngay trên xương mắt cá chân 1cm: 22-24 cm Vòng 2: bắp chân, tại nơi lớn nhất: 34-40 cm Chiều dài từ bàn chân đến đoạn dưới gối: 70-80 cm', 'PRODUCT-00055-003', 'PRODUCT-00055');
A106: =B106&"-"&TEXT(COUNTIF(B$2:B106,B106),"000") -> PRODUCT-00056-001 | B106: PRODUCT-00056 | C106: =IFERROR(INDEX(Product!$B:$B,MATCH(B106,Product!$A:$A,0)),"NOT FOUND") -> [CODY Health] Vớ y khoa giãn tĩnh mạch (Vớ gối) | D106: Vòng 1: vòng cổ chân, ngay trên xương mắt cá chân 1cm: 18-20 cm Vòng 2: vòng bắp chân, tại nơi lớn nhất: 31-35 cm Vòng 3: vòng đùi, dưới bẹn 5cm: 45-53 cm | E106: ="INSERT INTO public.medical_supply_product_variant (additional_desc, code, product_code) VALUES ("&IF(D106="","NULL","'"&SUBSTITUTE(D106,"'","''")&"'")&", '"&A106&"', '"&B106&"');" -> INSERT INTO public.medical_supply_product_variant (additional_desc, code, product_code) VALUES ('Vòng 1: vòng cổ chân, ngay trên xương mắt cá chân 1cm: 18-20 cm Vòng 2: vòng bắp chân, tại nơi lớn nhất: 31-35 cm Vòng 3: vòng đùi, dưới bẹn 5cm: 45-53 cm', 'PRODUCT-00056-001', 'PRODUCT-00056');
A107: =B107&"-"&TEXT(COUNTIF(B$2:B107,B107),"000") -> PRODUCT-00056-002 | B107: PRODUCT-00056 | C107: =IFERROR(INDEX(Product!$B:$B,MATCH(B107,Product!$A:$A,0)),"NOT FOUND") -> [CODY Health] Vớ y khoa giãn tĩnh mạch (Vớ gối) | D107: Vòng 1: vòng cổ chân, ngay trên xương mắt cá chân 1cm: 20-22 cm Vòng 2: vòng bắp chân, tại nơi lớn nhất: 33-38 cm Vòng 3: vòng đùi, dưới bẹn 5cm: 48-56 cm | E107: ="INSERT INTO public.medical_supply_product_variant (additional_desc, code, product_code) VALUES ("&IF(D107="","NULL","'"&SUBSTITUTE(D107,"'","''")&"'")&", '"&A107&"', '"&B107&"');" -> INSERT INTO public.medical_supply_product_variant (additional_desc, code, product_code) VALUES ('Vòng 1: vòng cổ chân, ngay trên xương mắt cá chân 1cm: 20-22 cm Vòng 2: vòng bắp chân, tại nơi lớn nhất: 33-38 cm Vòng 3: vòng đùi, dưới bẹn 5cm: 48-56 cm', 'PRODUCT-00056-002', 'PRODUCT-00056');
... A111: =B111&"-"&TEXT(COUNTIF(B$2:B111,B111),"000") -> PRODUCT-00296-003 | B111: PRODUCT-00296 | C111: =IFERROR(INDEX(Product!$B:$B,MATCH(B111,Product!$A:$A,0)),"NOT FOUND") -> [CODY Health] Vớ y khoa giãn tĩnh mạch (Vớ đùi) | D111: Vòng 1: vòng cổ chân, ngay trên xương mắt cá chân 1cm: 22-24 cm Vòng 2: vòng bắp chân, tại nơi lớn nhất: 34-40 cm Vòng 3: vòng đùi, dưới bẹn 5cm: 51-59 cm | E111: ="INSERT INTO public.medical_supply_product_variant (additional_desc, code, product_code) VALUES ("&IF(D111="","NULL","'"&SUBSTITUTE(D111,"'","''")&"'")&", '"&A111&"', '"&B111&"');" -> INSERT INTO public.medical_supply_product_variant (additional_desc, code, product_code) VALUES ('Vòng 1: vòng cổ chân, ngay trên xương mắt cá chân 1cm: 22-24 cm Vòng 2: vòng bắp chân, tại nơi lớn nhất: 34-40 cm Vòng 3: vòng đùi, dưới bẹn 5cm: 51-59 cm', 'PRODUCT-00296-003', 'PRODUCT-00296');
A112: =B112&"-"&TEXT(COUNTIF(B$2:B112,B112),"000") -> PRODUCT-00057-001 | B112: PRODUCT-00057 | C112: =IFERROR(INDEX(Product!$B:$B,MATCH(B112,Product!$A:$A,0)),"NOT FOUND") -> [Hapaku] Đai chườm thảo dược bàn chân làm nóng bằng điện | E112: ="INSERT INTO public.medical_supply_product_variant (additional_desc, code, product_code) VALUES ("&IF(D112="","NULL","'"&SUBSTITUTE(D112,"'","''")&"'")&", '"&A112&"', '"&B112&"');" -> INSERT INTO public.medical_supply_product_variant (additional_desc, code, product_code) VALUES (NULL, 'PRODUCT-00057-001', 'PRODUCT-00057');
A113: =B113&"-"&TEXT(COUNTIF(B$2:B113,B113),"000") -> PRODUCT-00058-001 | B113: PRODUCT-00058 | C113: =IFERROR(INDEX(Product!$B:$B,MATCH(B113,Product!$A:$A,0)),"NOT FOUND") -> [Hapaku] Đai chườm thảo dược cổ gáy làm nóng bằng điện (50cmx11cm) | E113: ="INSERT INTO public.medical_supply_product_variant (additional_desc, code, product_code) VALUES ("&IF(D113="","NULL","'"&SUBSTITUTE(D113,"'","''")&"'")&", '"&A113&"', '"&B113&"');" -> INSERT INTO public.medical_supply_product_variant (additional_desc, code, product_code) VALUES (NULL, 'PRODUCT-00058-001', 'PRODUCT-00058');
A114: =B114&"-"&TEXT(COUNTIF(B$2:B114,B114),"000") -> PRODUCT-00059-001 | B114: PRODUCT-00059 | C114: =IFERROR(INDEX(Product!$B:$B,MATCH(B114,Product!$A:$A,0)),"NOT FOUND") -> [Hapaku] Đai chườm thảo dược lưng bụng làm nóng bằng điện | E114: ="INSERT INTO public.medical_supply_product_variant (additional_desc, code, product_code) VALUES ("&IF(D114="","NULL","'"&SUBSTITUTE(D114,"'","''")&"'")&", '"&A114&"', '"&B114&"');" -> INSERT INTO public.medical_supply_product_variant (additional_desc, code, product_code) VALUES (NULL, 'PRODUCT-00059-001', 'PRODUCT-00059');
A115: =B115&"-"&TEXT(COUNTIF(B$2:B115,B115),"000") -> PRODUCT-00060-001 | B115: PRODUCT-00060 | C115: =IFERROR(INDEX(Product!$B:$B,MATCH(B115,Product!$A:$A,0)),"NOT FOUND") -> [Hapaku] Đai chườm thảo dược vai gáy cổ làm nóng bằng điện (35cmx48cm) | E115: ="INSERT INTO public.medical_supply_product_variant (additional_desc, code, product_code) VALUES ("&IF(D115="","NULL","'"&SUBSTITUTE(D115,"'","''")&"'")&", '"&A115&"', '"&B115&"');" -> INSERT INTO public.medical_supply_product_variant (additional_desc, code, product_code) VALUES (NULL, 'PRODUCT-00060-001', 'PRODUCT-00060');
A116: =B116&"-"&TEXT(COUNTIF(B$2:B116,B116),"000") -> PRODUCT-00061-001 | B116: PRODUCT-00061 | C116: =IFERROR(INDEX(Product!$B:$B,MATCH(B116,Product!$A:$A,0)),"NOT FOUND") -> [Hapaku] Gối chườm thảo dược đa năng làm nóng bằng điện (34cmx24cm) | E116: ="INSERT INTO public.medical_supply_product_variant (additional_desc, code, product_code) VALUES ("&IF(D116="","NULL","'"&SUBSTITUTE(D116,"'","''")&"'")&", '"&A116&"', '"&B116&"');" -> INSERT INTO public.medical_supply_product_variant (additional_desc, code, product_code) VALUES (NULL, 'PRODUCT-00061-001', 'PRODUCT-00061');
A117: =B117&"-"&TEXT(COUNTIF(B$2:B117,B117),"000") -> PRODUCT-00062-001 | B117: PRODUCT-00062 | C117: =IFERROR(INDEX(Product!$B:$B,MATCH(B117,Product!$A:$A,0)),"NOT FOUND") -> [Merisocks] Đai hỗ trợ đầu gối | E117: ="INSERT INTO public.medical_supply_product_variant (additional_desc, code, product_code) VALUES ("&IF(D117="","NULL","'"&SUBSTITUTE(D117,"'","''")&"'")&", '"&A117&"', '"&B117&"');" -> INSERT INTO public.medical_supply_product_variant (additional_desc, code, product_code) VALUES (NULL, 'PRODUCT-00062-001', 'PRODUCT-00062');
A118: =B118&"-"&TEXT(COUNTIF(B$2:B118,B118),"000") -> PRODUCT-00062-002 | B118: PRODUCT-00062 | C118: =IFERROR(INDEX(Product!$B:$B,MATCH(B118,Product!$A:$A,0)),"NOT FOUND") -> [Merisocks] Đai hỗ trợ đầu gối | E118: ="INSERT INTO public.medical_supply_product_variant (additional_desc, code, product_code) VALUES ("&IF(D118="","NULL","'"&SUBSTITUTE(D118,"'","''")&"'")&", '"&A118&"', '"&B118&"');" -> INSERT INTO public.medical_supply_product_variant (additional_desc, code, product_code) VALUES (NULL, 'PRODUCT-00062-002', 'PRODUCT-00062');
A119: =B119&"-"&TEXT(COUNTIF(B$2:B119,B119),"000") -> PRODUCT-00062-003 | B119: PRODUCT-00062 | C119: =IFERROR(INDEX(Product!$B:$B,MATCH(B119,Product!$A:$A,0)),"NOT FOUND") -> [Merisocks] Đai hỗ trợ đầu gối | E119: ="INSERT INTO public.medical_supply_product_variant (additional_desc, code, product_code) VALUES ("&IF(D119="","NULL","'"&SUBSTITUTE(D119,"'","''")&"'")&", '"&A119&"', '"&B119&"');" -> INSERT INTO public.medical_supply_product_variant (additional_desc, code, product_code) VALUES (NULL, 'PRODUCT-00062-003', 'PRODUCT-00062');
A120: =B120&"-"&TEXT(COUNTIF(B$2:B120,B120),"000") -> PRODUCT-00063-001 | B120: PRODUCT-00063 | C120: =IFERROR(INDEX(Product!$B:$B,MATCH(B120,Product!$A:$A,0)),"NOT FOUND") -> [Merisocks] Vớ nén bắp chân chống suy giãn tĩnh mạch | D120: Vòng 1: cổ chân, ngay trên mắt cá chân: 17-22cm Vòng 2: bắp chân ở vị trí lớn nhất: 29-38cm | E120: ="INSERT INTO public.medical_supply_product_variant (additional_desc, code, product_code) VALUES ("&IF(D120="","NULL","'"&SUBSTITUTE(D120,"'","''")&"'")&", '"&A120&"', '"&B120&"');" -> INSERT INTO public.medical_supply_product_variant (additional_desc, code, product_code) VALUES ('Vòng 1: cổ chân, ngay trên mắt cá chân: 17-22cm Vòng 2: bắp chân ở vị trí lớn nhất: 29-38cm', 'PRODUCT-00063-001', 'PRODUCT-00063');
A121: =B121&"-"&TEXT(COUNTIF(B$2:B121,B121),"000") -> PRODUCT-00063-002 | B121: PRODUCT-00063 | C121: =IFERROR(INDEX(Product!$B:$B,MATCH(B121,Product!$A:$A,0)),"NOT FOUND") -> [Merisocks] Vớ nén bắp chân chống suy giãn tĩnh mạch | D121: Vòng 1: cổ chân, ngay trên mắt cá chân: 19-24cm Vòng 2: bắp chân ở vị trí lớn nhất: 31-40cm | E121: ="INSERT INTO public.medical_supply_product_variant (additional_desc, code, product_code) VALUES ("&IF(D121="","NULL","'"&SUBSTITUTE(D121,"'","''")&"'")&", '"&A121&"', '"&B121&"');" -> INSERT INTO public.medical_supply_product_variant (additional_desc, code, product_code) VALUES ('Vòng 1: cổ chân, ngay trên mắt cá chân: 19-24cm Vòng 2: bắp chân ở vị trí lớn nhất: 31-40cm', 'PRODUCT-00063-002', 'PRODUCT-00063');
A122: =B122&"-"&TEXT(COUNTIF(B$2:B122,B122),"000") -> PRODUCT-00063-003 | B122: PRODUCT-00063 | C122: =IFERROR(INDEX(Product!$B:$B,MATCH(B122,Product!$A:$A,0)),"NOT FOUND") -> [Merisocks] Vớ nén bắp chân chống suy giãn tĩnh mạch | D122: Vòng 1: cổ chân, ngay trên mắt cá chân: 21-26cm Vòng 2: bắp chân ở vị trí lớn nhất: 33-43cm | E122: ="INSERT INTO public.medical_supply_product_variant (additional_desc, code, product_code) VALUES ("&IF(D122="","NULL","'"&SUBSTITUTE(D122,"'","''")&"'")&", '"&A122&"', '"&B122&"');" -> INSERT INTO public.medical_supply_product_variant (additional_desc, code, product_code) VALUES ('Vòng 1: cổ chân, ngay trên mắt cá chân: 21-26cm Vòng 2: bắp chân ở vị trí lớn nhất: 33-43cm', 'PRODUCT-00063-003', 'PRODUCT-00063');
A123: =B123&"-"&TEXT(COUNTIF(B$2:B123,B123),"000") -> PRODUCT-00063-004 | B123: PRODUCT-00063 | C123: =IFERROR(INDEX(Product!$B:$B,MATCH(B123,Product!$A:$A,0)),"NOT FOUND") -> [Merisocks] Vớ nén bắp chân chống suy giãn tĩnh mạch | D123: Vòng 1: cổ chân, ngay trên mắt cá chân: 24-29cm Vòng 2: bắp chân ở vị trí lớn nhất: 36-45cm | E123: ="INSERT INTO public.medical_supply_product_variant (additional_desc, code, product_code) VALUES ("&IF(D123="","NULL","'"&SUBSTITUTE(D123,"'","''")&"'")&", '"&A123&"', '"&B123&"');" -> INSERT INTO public.medical_supply_product_variant (additional_desc, code, product_code) VALUES ('Vòng 1: cổ chân, ngay trên mắt cá chân: 24-29cm Vòng 2: bắp chân ở vị trí lớn nhất: 36-45cm', 'PRODUCT-00063-004', 'PRODUCT-00063');
A124: =B124&"-"&TEXT(COUNTIF(B$2:B124,B124),"000") -> PRODUCT-00063-005 | B124: PRODUCT-00063 | C124: =IFERROR(INDEX(Product!$B:$B,MATCH(B124,Product!$A:$A,0)),"NOT FOUND") -> [Merisocks] Vớ nén bắp chân chống suy giãn tĩnh mạch | D124: Vòng 1: cổ chân, ngay trên mắt cá chân: 17-22cm Vòng 2: bắp chân ở vị trí lớn nhất: 29-38cm | E124: ="INSERT INTO public.medical_supply_product_variant (additional_desc, code, product_code) VALUES ("&IF(D124="","NULL","'"&SUBSTITUTE(D124,"'","''")&"'")&", '"&A124&"', '"&B124&"');" -> INSERT INTO public.medical_supply_product_variant (additional_desc, code, product_code) VALUES ('Vòng 1: cổ chân, ngay trên mắt cá chân: 17-22cm Vòng 2: bắp chân ở vị trí lớn nhất: 29-38cm', 'PRODUCT-00063-005', 'PRODUCT-00063');
A125: =B125&"-"&TEXT(COUNTIF(B$2:B125,B125),"000") -> PRODUCT-00063-006 | B125: PRODUCT-00063 | C125: =IFERROR(INDEX(Product!$B:$B,MATCH(B125,Product!$A:$A,0)),"NOT FOUND") -> [Merisocks] Vớ nén bắp chân chống suy giãn tĩnh mạch | D125: Vòng 1: cổ chân, ngay trên mắt cá chân: 19-24cm Vòng 2: bắp chân ở vị trí lớn nhất: 31-40cm | E125: ="INSERT INTO public.medical_supply_product_variant (additional_desc, code, product_code) VALUES ("&IF(D125="","NULL","'"&SUBSTITUTE(D125,"'","''")&"'")&", '"&A125&"', '"&B125&"');" -> INSERT INTO public.medical_supply_product_variant (additional_desc, code, product_code) VALUES ('Vòng 1: cổ chân, ngay trên mắt cá chân: 19-24cm Vòng 2: bắp chân ở vị trí lớn nhất: 31-40cm', 'PRODUCT-00063-006', 'PRODUCT-00063');
A126: =B126&"-"&TEXT(COUNTIF(B$2:B126,B126),"000") -> PRODUCT-00063-007 | B126: PRODUCT-00063 | C126: =IFERROR(INDEX(Product!$B:$B,MATCH(B126,Product!$A:$A,0)),"NOT FOUND") -> [Merisocks] Vớ nén bắp chân chống suy giãn tĩnh mạch | D126: Vòng 1: cổ chân, ngay trên mắt cá chân: 21-26cm Vòng 2: bắp chân ở vị trí lớn nhất: 33-43cm | E126: ="INSERT INTO public.medical_supply_product_variant (additional_desc, code, product_code) VALUES ("&IF(D126="","NULL","'"&SUBSTITUTE(D126,"'","''")&"'")&", '"&A126&"', '"&B126&"');" -> INSERT INTO public.medical_supply_product_variant (additional_desc, code, product_code) VALUES ('Vòng 1: cổ chân, ngay trên mắt cá chân: 21-26cm Vòng 2: bắp chân ở vị trí lớn nhất: 33-43cm', 'PRODUCT-00063-007', 'PRODUCT-00063');
A127: =B127&"-"&TEXT(COUNTIF(B$2:B127,B127),"000") -> PRODUCT-00063-008 | B127: PRODUCT-00063 | C127: =IFERROR(INDEX(Product!$B:$B,MATCH(B127,Product!$A:$A,0)),"NOT FOUND") -> [Merisocks] Vớ nén bắp chân chống suy giãn tĩnh mạch | D127: Vòng 1: cổ chân, ngay trên mắt cá chân: 24-29cm Vòng 2: bắp chân ở vị trí lớn nhất: 36-45cm | E127: ="INSERT INTO public.medical_supply_product_variant (additional_desc, code, product_code) VALUES ("&IF(D127="","NULL","'"&SUBSTITUTE(D127,"'","''")&"'")&", '"&A127&"', '"&B127&"');" -> INSERT INTO public.medical_supply_product_variant (additional_desc, code, product_code) VALUES ('Vòng 1: cổ chân, ngay trên mắt cá chân: 24-29cm Vòng 2: bắp chân ở vị trí lớn nhất: 36-45cm', 'PRODUCT-00063-008', 'PRODUCT-00063');
A128: =B128&"-"&TEXT(COUNTIF(B$2:B128,B128),"000") -> PRODUCT-00063-009 | B128: PRODUCT-00063 | C128: =IFERROR(INDEX(Product!$B:$B,MATCH(B128,Product!$A:$A,0)),"NOT FOUND") -> [Merisocks] Vớ nén bắp chân chống suy giãn tĩnh mạch | D128: Vòng 1: cổ chân, ngay trên mắt cá chân: 17-22cm Vòng 2: bắp chân ở vị trí lớn nhất: 29-38cm | E128: ="INSERT INTO public.medical_supply_product_variant (additional_desc, code, product_code) VALUES ("&IF(D128="","NULL","'"&SUBSTITUTE(D128,"'","''")&"'")&", '"&A128&"', '"&B128&"');" -> INSERT INTO public.medical_supply_product_variant (additional_desc, code, product_code) VALUES ('Vòng 1: cổ chân, ngay trên mắt cá chân: 17-22cm Vòng 2: bắp chân ở vị trí lớn nhất: 29-38cm', 'PRODUCT-00063-009', 'PRODUCT-00063');
A129: =B129&"-"&TEXT(COUNTIF(B$2:B129,B129),"000") -> PRODUCT-00063-010 | B129: PRODUCT-00063 | C129: =IFERROR(INDEX(Product!$B:$B,MATCH(B129,Product!$A:$A,0)),"NOT FOUND") -> [Merisocks] Vớ nén bắp chân chống suy giãn tĩnh mạch | D129: Vòng 1: cổ chân, ngay trên mắt cá chân: 19-24cm Vòng 2: bắp chân ở vị trí lớn nhất: 31-40cm | E129: ="INSERT INTO public.medical_supply_product_variant (additional_desc, code, product_code) VALUES ("&IF(D129="","NULL","'"&SUBSTITUTE(D129,"'","''")&"'")&", '"&A129&"', '"&B129&"');" -> INSERT INTO public.medical_supply_product_variant (additional_desc, code, product_code) VALUES ('Vòng 1: cổ chân, ngay trên mắt cá chân: 19-24cm Vòng 2: bắp chân ở vị trí lớn nhất: 31-40cm', 'PRODUCT-00063-010', 'PRODUCT-00063');
A130: =B130&"-"&TEXT(COUNTIF(B$2:B130,B130),"000") -> PRODUCT-00063-011 | B130: PRODUCT-00063 | C130: =IFERROR(INDEX(Product!$B:$B,MATCH(B130,Product!$A:$A,0)),"NOT FOUND") -> [Merisocks] Vớ nén bắp chân chống suy giãn tĩnh mạch | D130: Vòng 1: cổ chân, ngay trên mắt cá chân: 21-26cm Vòng 2: bắp chân ở vị trí lớn nhất: 33-43cm | E130: ="INSERT INTO public.medical_supply_product_variant (additional_desc, code, product_code) VALUES ("&IF(D130="","NULL","'"&SUBSTITUTE(D130,"'","''")&"'")&", '"&A130&"', '"&B130&"');" -> INSERT INTO public.medical_supply_product_variant (additional_desc, code, product_code) VALUES ('Vòng 1: cổ chân, ngay trên mắt cá chân: 21-26cm Vòng 2: bắp chân ở vị trí lớn nhất: 33-43cm', 'PRODUCT-00063-011', 'PRODUCT-00063');
A131: =B131&"-"&TEXT(COUNTIF(B$2:B131,B131),"000") -> PRODUCT-00063-012 | B131: PRODUCT-00063 | C131: =IFERROR(INDEX(Product!$B:$B,MATCH(B131,Product!$A:$A,0)),"NOT FOUND") -> [Merisocks] Vớ nén bắp chân chống suy giãn tĩnh mạch | D131: Vòng 1: cổ chân, ngay trên mắt cá chân: 24-29cm Vòng 2: bắp chân ở vị trí lớn nhất: 36-45cm | E131: ="INSERT INTO public.medical_supply_product_variant (additional_desc, code, product_code) VALUES ("&IF(D131="","NULL","'"&SUBSTITUTE(D131,"'","''")&"'")&", '"&A131&"', '"&B131&"');" -> INSERT INTO public.medical_supply_product_variant (additional_desc, code, product_code) VALUES ('Vòng 1: cổ chân, ngay trên mắt cá chân: 24-29cm Vòng 2: bắp chân ở vị trí lớn nhất: 36-45cm', 'PRODUCT-00063-012', 'PRODUCT-00063');
A132: =B132&"-"&TEXT(COUNTIF(B$2:B132,B132),"000") -> PRODUCT-00064-001 | B132: PRODUCT-00064 | C132: =IFERROR(INDEX(Product!$B:$B,MATCH(B132,Product!$A:$A,0)),"NOT FOUND") -> [Omron] Máy massage xung điện trị liệu - HV-F013 | E132: ="INSERT INTO public.medical_supply_product_variant (additional_desc, code, product_code) VALUES ("&IF(D132="","NULL","'"&SUBSTITUTE(D132,"'","''")&"'")&", '"&A132&"', '"&B132&"');" -> INSERT INTO public.medical_supply_product_variant (additional_desc, code, product_code) VALUES (NULL, 'PRODUCT-00064-001', 'PRODUCT-00064');
A133: =B133&"-"&TEXT(COUNTIF(B$2:B133,B133),"000") -> PRODUCT-00065-001 | B133: PRODUCT-00065 | C133: =IFERROR(INDEX(Product!$B:$B,MATCH(B133,Product!$A:$A,0)),"NOT FOUND") -> [Omron] Máy massage xung điện trị liệu - HV-F127 | E133: ="INSERT INTO public.medical_supply_product_variant (additional_desc, code, product_code) VALUES ("&IF(D133="","NULL","'"&SUBSTITUTE(D133,"'","''")&"'")&", '"&A133&"', '"&B133&"');" -> INSERT INTO public.medical_supply_product_variant (additional_desc, code, product_code) VALUES (NULL, 'PRODUCT-00065-001', 'PRODUCT-00065');
A134: =B134&"-"&TEXT(COUNTIF(B$2:B134,B134),"000") -> PRODUCT-00066-001 | B134: PRODUCT-00066 | C134: =IFERROR(INDEX(Product!$B:$B,MATCH(B134,Product!$A:$A,0)),"NOT FOUND") -> [Omron] Máy massage xung điện trị liệu - HV-F128 | E134: ="INSERT INTO public.medical_supply_product_variant (additional_desc, code, product_code) VALUES ("&IF(D134="","NULL","'"&SUBSTITUTE(D134,"'","''")&"'")&", '"&A134&"', '"&B134&"');" -> INSERT INTO public.medical_supply_product_variant (additional_desc, code, product_code) VALUES (NULL, 'PRODUCT-00066-001', 'PRODUCT-00066');
A135: =B135&"-"&TEXT(COUNTIF(B$2:B135,B135),"000") -> PRODUCT-00067-001 | B135: PRODUCT-00067 | C135: =IFERROR(INDEX(Product!$B:$B,MATCH(B135,Product!$A:$A,0)),"NOT FOUND") -> [Omron] Miếng dán điện cực máy massage xung điện - Long Life Pad HV-LLPAD-C1 | E135: ="INSERT INTO public.medical_supply_product_variant (additional_desc, code, product_code) VALUES ("&IF(D135="","NULL","'"&SUBSTITUTE(D135,"'","''")&"'")&", '"&A135&"', '"&B135&"');" -> INSERT INTO public.medical_supply_product_variant (additional_desc, code, product_code) VALUES (NULL, 'PRODUCT-00067-001', 'PRODUCT-00067');
A136: =B136&"-"&TEXT(COUNTIF(B$2:B136,B136),"000") -> PRODUCT-00068-001 | B136: PRODUCT-00068 | C136: =IFERROR(INDEX(Product!$B:$B,MATCH(B136,Product!$A:$A,0)),"NOT FOUND") -> [Orbe] Đai chống gù lưng | D136: Số đo vòng chân ngực: <50 cm | E136: ="INSERT INTO public.medical_supply_product_variant (additional_desc, code, product_code) VALUES ("&IF(D136="","NULL","'"&SUBSTITUTE(D136,"'","''")&"'")&", '"&A136&"', '"&B136&"');" -> INSERT INTO public.medical_supply_product_variant (additional_desc, code, product_code) VALUES ('Số đo vòng chân ngực: <50 cm', 'PRODUCT-00068-001', 'PRODUCT-00068');
A137: =B137&"-"&TEXT(COUNTIF(B$2:B137,B137),"000") -> PRODUCT-00068-002 | B137: PRODUCT-00068 | C137: =IFERROR(INDEX(Product!$B:$B,MATCH(B137,Product!$A:$A,0)),"NOT FOUND") -> [Orbe] Đai chống gù lưng | D137: Số đo vòng chân ngực: 50 - 65 cm | E137: ="INSERT INTO public.medical_supply_product_variant (additional_desc, code, product_code) VALUES ("&IF(D137="","NULL","'"&SUBSTITUTE(D137,"'","''")&"'")&", '"&A137&"', '"&B137&"');" -> INSERT INTO public.medical_supply_product_variant (additional_desc, code, product_code) VALUES ('Số đo vòng chân ngực: 50 - 65 cm', 'PRODUCT-00068-002', 'PRODUCT-00068');
A138: =B138&"-"&TEXT(COUNTIF(B$2:B138,B138),"000") -> PRODUCT-00068-003 | B138: PRODUCT-00068 | C138: =IFERROR(INDEX(Product!$B:$B,MATCH(B138,Product!$A:$A,0)),"NOT FOUND") -> [Orbe] Đai chống gù lưng | D138: Số đo vòng chân ngực: 65 - 80 cm | E138: ="INSERT INTO public.medical_supply_product_variant (additional_desc, code, product_code) VALUES ("&IF(D138="","NULL","'"&SUBSTITUTE(D138,"'","''")&"'")&", '"&A138&"', '"&B138&"');" -> INSERT INTO public.medical_supply_product_variant (additional_desc, code, product_code) VALUES ('Số đo vòng chân ngực: 65 - 80 cm', 'PRODUCT-00068-003', 'PRODUCT-00068');
A139: =B139&"-"&TEXT(COUNTIF(B$2:B139,B139),"000") -> PRODUCT-00068-004 | B139: PRODUCT-00068 | C139: =IFERROR(INDEX(Product!$B:$B,MATCH(B139,Product!$A:$A,0)),"NOT FOUND") -> [Orbe] Đai chống gù lưng | D139: Số đo vòng chân ngực: 80 - 95 cm | E139: ="INSERT INTO public.medical_supply_product_variant (additional_desc, code, product_code) VALUES ("&IF(D139="","NULL","'"&SUBSTITUTE(D139,"'","''")&"'")&", '"&A139&"', '"&B139&"');" -> INSERT INTO public.medical_supply_product_variant (additional_desc, code, product_code) VALUES ('Số đo vòng chân ngực: 80 - 95 cm', 'PRODUCT-00068-004', 'PRODUCT-00068');
A140: =B140&"-"&TEXT(COUNTIF(B$2:B140,B140),"000") -> PRODUCT-00068-005 | B140: PRODUCT-00068 | C140: =IFERROR(INDEX(Product!$B:$B,MATCH(B140,Product!$A:$A,0)),"NOT FOUND") -> [Orbe] Đai chống gù lưng | D140: Số đo vòng chân ngực: >95 cm | E140: ="INSERT INTO public.medical_supply_product_variant (additional_desc, code, product_code) VALUES ("&IF(D140="","NULL","'"&SUBSTITUTE(D140,"'","''")&"'")&", '"&A140&"', '"&B140&"');" -> INSERT INTO public.medical_supply_product_variant (additional_desc, code, product_code) VALUES ('Số đo vòng chân ngực: >95 cm', 'PRODUCT-00068-005', 'PRODUCT-00068');
A141: =B141&"-"&TEXT(COUNTIF(B$2:B141,B141),"000") -> PRODUCT-00069-001 | B141: PRODUCT-00069 | C141: =IFERROR(INDEX(Product!$B:$B,MATCH(B141,Product!$A:$A,0)),"NOT FOUND") -> [Orbe] Đai thắt lưng cột sống cao cấp - Olumba | D141: Số đo vòng bụng: 50 - 65 cm Chiều cao đai: 22 cm | E141: ="INSERT INTO public.medical_supply_product_variant (additional_desc, code, product_code) VALUES ("&IF(D141="","NULL","'"&SUBSTITUTE(D141,"'","''")&"'")&", '"&A141&"', '"&B141&"');" -> INSERT INTO public.medical_supply_product_variant (additional_desc, code, product_code) VALUES ('Số đo vòng bụng: 50 - 65 cm Chiều cao đai: 22 cm', 'PRODUCT-00069-001', 'PRODUCT-00069');
A142: =B142&"-"&TEXT(COUNTIF(B$2:B142,B142),"000") -> PRODUCT-00069-002 | B142: PRODUCT-00069 | C142: =IFERROR(INDEX(Product!$B:$B,MATCH(B142,Product!$A:$A,0)),"NOT FOUND") -> [Orbe] Đai thắt lưng cột sống cao cấp - Olumba | D142: Số đo vòng bụng: 65 - 80 cm Chiều cao đai: 22 cm | E142: ="INSERT INTO public.medical_supply_product_variant (additional_desc, code, product_code) VALUES ("&IF(D142="","NULL","'"&SUBSTITUTE(D142,"'","''")&"'")&", '"&A142&"', '"&B142&"');" -> INSERT INTO public.medical_supply_product_variant (additional_desc, code, product_code) VALUES ('Số đo vòng bụng: 65 - 80 cm Chiều cao đai: 22 cm', 'PRODUCT-00069-002', 'PRODUCT-00069');
A143: =B143&"-"&TEXT(COUNTIF(B$2:B143,B143),"000") -> PRODUCT-00069-003 | B143: PRODUCT-00069 | C143: =IFERROR(INDEX(Product!$B:$B,MATCH(B143,Product!$A:$A,0)),"NOT FOUND") -> [Orbe] Đai thắt lưng cột sống cao cấp - Olumba | D143: Số đo vòng bụng: 80 - 95 cm Chiều cao đai: 22 cm | E143: ="INSERT INTO public.medical_supply_product_variant (additional_desc, code, product_code) VALUES ("&IF(D143="","NULL","'"&SUBSTITUTE(D143,"'","''")&"'")&", '"&A143&"', '"&B143&"');" -> INSERT INTO public.medical_supply_product_variant (additional_desc, code, product_code) VALUES ('Số đo vòng bụng: 80 - 95 cm Chiều cao đai: 22 cm', 'PRODUCT-00069-003', 'PRODUCT-00069');
A144: =B144&"-"&TEXT(COUNTIF(B$2:B144,B144),"000") -> PRODUCT-00069-004 | B144: PRODUCT-00069 | C144: =IFERROR(INDEX(Product!$B:$B,MATCH(B144,Product!$A:$A,0)),"NOT FOUND") -> [Orbe] Đai thắt lưng cột sống cao cấp - Olumba | D144: Số đo vòng bụng: 95 - 110 cm Chiều cao đai: 22 cm | E144: ="INSERT INTO public.medical_supply_product_variant (additional_desc, code, product_code) VALUES ("&IF(D144="","NULL","'"&SUBSTITUTE(D144,"'","''")&"'")&", '"&A144&"', '"&B144&"');" -> INSERT INTO public.medical_supply_product_variant (additional_desc, code, product_code) VALUES ('Số đo vòng bụng: 95 - 110 cm Chiều cao đai: 22 cm', 'PRODUCT-00069-004', 'PRODUCT-00069');
A145: =B145&"-"&TEXT(COUNTIF(B$2:B145,B145),"000") -> PRODUCT-00069-005 | B145: PRODUCT-00069 | C145: =IFERROR(INDEX(Product!$B:$B,MATCH(B145,Product!$A:$A,0)),"NOT FOUND") -> [Orbe] Đai thắt lưng cột sống cao cấp - Olumba | D145: Số đo vòng bụng: 110 - 125 cm Chiều cao đai: 22 cm | E145: ="INSERT INTO public.medical_supply_product_variant (additional_desc, code, product_code) VALUES ("&IF(D145="","NULL","'"&SUBSTITUTE(D145,"'","''")&"'")&", '"&A145&"', '"&B145&"');" -> INSERT INTO public.medical_supply_product_variant (additional_desc, code, product_code) VALUES ('Số đo vòng bụng: 110 - 125 cm Chiều cao đai: 22 cm', 'PRODUCT-00069-005', 'PRODUCT-00069');
A146: =B146&"-"&TEXT(COUNTIF(B$2:B146,B146),"000") -> PRODUCT-00070-001 | B146: PRODUCT-00070 | C146: =IFERROR(INDEX(Product!$B:$B,MATCH(B146,Product!$A:$A,0)),"NOT FOUND") -> [Timelock] Găng tay robot phục hồi chức năng bàn tay (Bên trái) | D146: Chiều dài: 16.6-17.5 cm Chiều rộng: 9-9.5 cm | E146: ="INSERT INTO public.medical_supply_product_variant (additional_desc, code, product_code) VALUES ("&IF(D146="","NULL","'"&SUBSTITUTE(D146,"'","''")&"'")&", '"&A146&"', '"&B146&"');" -> INSERT INTO public.medical_supply_product_variant (additional_desc, code, product_code) VALUES ('Chiều dài: 16.6-17.5 cm Chiều rộng: 9-9.5 cm', 'PRODUCT-00070-001', 'PRODUCT-00070');
A147: =B147&"-"&TEXT(COUNTIF(B$2:B147,B147),"000") -> PRODUCT-00297-001 | B147: PRODUCT-00297 | C147: =IFERROR(INDEX(Product!$B:$B,MATCH(B147,Product!$A:$A,0)),"NOT FOUND") -> [Timelock] Găng tay robot phục hồi chức năng bàn tay (Bên phải) | D147: Chiều dài: 16.6-17.5 cm Chiều rộng: 9-9.5 cm | E147: ="INSERT INTO public.medical_supply_product_variant (additional_desc, code, product_code) VALUES ("&IF(D147="","NULL","'"&SUBSTITUTE(D147,"'","''")&"'")&", '"&A147&"', '"&B147&"');" -> INSERT INTO public.medical_supply_product_variant (additional_desc, code, product_code) VALUES ('Chiều dài: 16.6-17.5 cm Chiều rộng: 9-9.5 cm', 'PRODUCT-00297-001', 'PRODUCT-00297');
... A154: =B154&"-"&TEXT(COUNTIF(B$2:B154,B154),"000") -> PRODUCT-00071-005 | B154: PRODUCT-00071 | C154: =IFERROR(INDEX(Product!$B:$B,MATCH(B154,Product!$A:$A,0)),"NOT FOUND") -> [Venosan] Vớ y khoa hỗ trợ điều trị suy giãn tĩnh mạch - Venosan 6000 | D154: Vòng 1: cổ chân, ngay trên xương mắt cá chân 1cm: 29-31 cm Vòng 2: bắp chân, tại nơi lớn nhất: 39-47 cm Vòng 3: chỗ nhỏ nhất dưới gối: 38-46 cm Vòng 4: đùi, dưới bẹn 5-8cm: 63-74 cm | E154: ="INSERT INTO public.medical_supply_product_variant (additional_desc, code, product_code) VALUES ("&IF(D154="","NULL","'"&SUBSTITUTE(D154,"'","''")&"'")&", '"&A154&"', '"&B154&"');" -> INSERT INTO public.medical_supply_product_variant (additional_desc, code, product_code) VALUES ('Vòng 1: cổ chân, ngay trên xương mắt cá chân 1cm: 29-31 cm Vòng 2: bắp chân, tại nơi lớn nhất: 39-47 cm Vòng 3: chỗ nhỏ nhất dưới gối: 38-46 cm Vòng 4: đùi, dưới bẹn 5-8cm: 63-74 cm', 'PRODUCT-00071-005', 'PRODUCT-00071');
A155: =B155&"-"&TEXT(COUNTIF(B$2:B155,B155),"000") -> PRODUCT-00298-001 | B155: PRODUCT-00298 | C155: =IFERROR(INDEX(Product!$B:$B,MATCH(B155,Product!$A:$A,0)),"NOT FOUND") -> [Venosan] Vớ y khoa hỗ trợ điều trị suy giãn tĩnh mạch - Venosan 6000 (Vớ gối) | E155: ="INSERT INTO public.medical_supply_product_variant (additional_desc, code, product_code) VALUES ("&IF(D155="","NULL","'"&SUBSTITUTE(D155,"'","''")&"'")&", '"&A155&"', '"&B155&"');" -> INSERT INTO public.medical_supply_product_variant (additional_desc, code, product_code) VALUES (NULL, 'PRODUCT-00298-001', 'PRODUCT-00298');
A156: =B156&"-"&TEXT(COUNTIF(B$2:B156,B156),"000") -> PRODUCT-00299-001 | B156: PRODUCT-00299 | C156: =IFERROR(INDEX(Product!$B:$B,MATCH(B156,Product!$A:$A,0)),"NOT FOUND") -> [Venosan] Vớ y khoa hỗ trợ điều trị suy giãn tĩnh mạch - Venosan 6000 (Vớ đùi) | E156: ="INSERT INTO public.medical_supply_product_variant (additional_desc, code, product_code) VALUES ("&IF(D156="","NULL","'"&SUBSTITUTE(D156,"'","''")&"'")&", '"&A156&"', '"&B156&"');" -> INSERT INTO public.medical_supply_product_variant (additional_desc, code, product_code) VALUES (NULL, 'PRODUCT-00299-001', 'PRODUCT-00299');
A157: =B157&"-"&TEXT(COUNTIF(B$2:B157,B157),"000") -> PRODUCT-00072-001 | B157: PRODUCT-00072 | C157: =IFERROR(INDEX(Product!$B:$B,MATCH(B157,Product!$A:$A,0)),"NOT FOUND") -> [ConvaTec] Bột hút ẩm chống loét hậu môn nhân tạo (28.3g) | E157: ="INSERT INTO public.medical_supply_product_variant (additional_desc, code, product_code) VALUES ("&IF(D157="","NULL","'"&SUBSTITUTE(D157,"'","''")&"'")&", '"&A157&"', '"&B157&"');" -> INSERT INTO public.medical_supply_product_variant (additional_desc, code, product_code) VALUES (NULL, 'PRODUCT-00072-001', 'PRODUCT-00072');
A158: =B158&"-"&TEXT(COUNTIF(B$2:B158,B158),"000") -> PRODUCT-00073-001 | B158: PRODUCT-00073 | C158: =IFERROR(INDEX(Product!$B:$B,MATCH(B158,Product!$A:$A,0)),"NOT FOUND") -> [ConvaTec] Keo làm đầy chống rò rỉ hậu môn nhân tạo (56.7g) | E158: ="INSERT INTO public.medical_supply_product_variant (additional_desc, code, product_code) VALUES ("&IF(D158="","NULL","'"&SUBSTITUTE(D158,"'","''")&"'")&", '"&A158&"', '"&B158&"');" -> INSERT INTO public.medical_supply_product_variant (additional_desc, code, product_code) VALUES (NULL, 'PRODUCT-00073-001', 'PRODUCT-00073');
A159: =B159&"-"&TEXT(COUNTIF(B$2:B159,B159),"000") -> PRODUCT-00074-001 | B159: PRODUCT-00074 | C159: =IFERROR(INDEX(Product!$B:$B,MATCH(B159,Product!$A:$A,0)),"NOT FOUND") -> [ConvaTec] Túi hậu môn nhân tạo 1 mảnh loại đục | E159: ="INSERT INTO public.medical_supply_product_variant (additional_desc, code, product_code) VALUES ("&IF(D159="","NULL","'"&SUBSTITUTE(D159,"'","''")&"'")&", '"&A159&"', '"&B159&"');" -> INSERT INTO public.medical_supply_product_variant (additional_desc, code, product_code) VALUES (NULL, 'PRODUCT-00074-001', 'PRODUCT-00074');
A160: =B160&"-"&TEXT(COUNTIF(B$2:B160,B160),"000") -> PRODUCT-00075-001 | B160: PRODUCT-00075 | C160: =IFERROR(INDEX(Product!$B:$B,MATCH(B160,Product!$A:$A,0)),"NOT FOUND") -> [ConvaTec] Túi hậu môn nhân tạo 1 mảnh trong suốt | E160: ="INSERT INTO public.medical_supply_product_variant (additional_desc, code, product_code) VALUES ("&IF(D160="","NULL","'"&SUBSTITUTE(D160,"'","''")&"'")&", '"&A160&"', '"&B160&"');" -> INSERT INTO public.medical_supply_product_variant (additional_desc, code, product_code) VALUES (NULL, 'PRODUCT-00075-001', 'PRODUCT-00075');
A161: =B161&"-"&TEXT(COUNTIF(B$2:B161,B161),"000") -> PRODUCT-00076-001 | B161: PRODUCT-00076 | C161: =IFERROR(INDEX(Product!$B:$B,MATCH(B161,Product!$A:$A,0)),"NOT FOUND") -> [ConvaTec] Túi hậu môn nhân tạo 1 mảnh trong suốt - ActiveLife 22771 | E161: ="INSERT INTO public.medical_supply_product_variant (additional_desc, code, product_code) VALUES ("&IF(D161="","NULL","'"&SUBSTITUTE(D161,"'","''")&"'")&", '"&A161&"', '"&B161&"');" -> INSERT INTO public.medical_supply_product_variant (additional_desc, code, product_code) VALUES (NULL, 'PRODUCT-00076-001', 'PRODUCT-00076');
A162: =B162&"-"&TEXT(COUNTIF(B$2:B162,B162),"000") -> PRODUCT-00077-001 | B162: PRODUCT-00077 | C162: =IFERROR(INDEX(Product!$B:$B,MATCH(B162,Product!$A:$A,0)),"NOT FOUND") -> [Hollister] Túi hậu môn nhân tạo 1 mảnh - 8631 | E162: ="INSERT INTO public.medical_supply_product_variant (additional_desc, code, product_code) VALUES ("&IF(D162="","NULL","'"&SUBSTITUTE(D162,"'","''")&"'")&", '"&A162&"', '"&B162&"');" -> INSERT INTO public.medical_supply_product_variant (additional_desc, code, product_code) VALUES (NULL, 'PRODUCT-00077-001', 'PRODUCT-00077');
A163: =B163&"-"&TEXT(COUNTIF(B$2:B163,B163),"000") -> PRODUCT-00078-001 | B163: PRODUCT-00078 | C163: =IFERROR(INDEX(Product!$B:$B,MATCH(B163,Product!$A:$A,0)),"NOT FOUND") -> [Hollister] Túi hậu môn nhân tạo cho trẻ sơ sinh - 3778 | E163: ="INSERT INTO public.medical_supply_product_variant (additional_desc, code, product_code) VALUES ("&IF(D163="","NULL","'"&SUBSTITUTE(D163,"'","''")&"'")&", '"&A163&"', '"&B163&"');" -> INSERT INTO public.medical_supply_product_variant (additional_desc, code, product_code) VALUES (NULL, 'PRODUCT-00078-001', 'PRODUCT-00078');
A164: =B164&"-"&TEXT(COUNTIF(B$2:B164,B164),"000") -> PRODUCT-00079-001 | B164: PRODUCT-00079 | C164: =IFERROR(INDEX(Product!$B:$B,MATCH(B164,Product!$A:$A,0)),"NOT FOUND") -> [Hollister] Bột hút ẩm chống loét hậu môn nhân tạo - Adapt Stoma Powder 7906 (28.3g) | E164: ="INSERT INTO public.medical_supply_product_variant (additional_desc, code, product_code) VALUES ("&IF(D164="","NULL","'"&SUBSTITUTE(D164,"'","''")&"'")&", '"&A164&"', '"&B164&"');" -> INSERT INTO public.medical_supply_product_variant (additional_desc, code, product_code) VALUES (NULL, 'PRODUCT-00079-001', 'PRODUCT-00079');
A165: =B165&"-"&TEXT(COUNTIF(B$2:B165,B165),"000") -> PRODUCT-00080-001 | B165: PRODUCT-00080 | C165: =IFERROR(INDEX(Product!$B:$B,MATCH(B165,Product!$A:$A,0)),"NOT FOUND") -> [Hollister] Chai xịt tẩy chất keo - 7737 | E165: ="INSERT INTO public.medical_supply_product_variant (additional_desc, code, product_code) VALUES ("&IF(D165="","NULL","'"&SUBSTITUTE(D165,"'","''")&"'")&", '"&A165&"', '"&B165&"');" -> INSERT INTO public.medical_supply_product_variant (additional_desc, code, product_code) VALUES (NULL, 'PRODUCT-00080-001', 'PRODUCT-00080');
A166: =B166&"-"&TEXT(COUNTIF(B$2:B166,B166),"000") -> PRODUCT-00081-001 | B166: PRODUCT-00081 | C166: =IFERROR(INDEX(Product!$B:$B,MATCH(B166,Product!$A:$A,0)),"NOT FOUND") -> [Hollister] Dây nịt đeo túi hậu môn nhân tạo - 7300 | E166: ="INSERT INTO public.medical_supply_product_variant (additional_desc, code, product_code) VALUES ("&IF(D166="","NULL","'"&SUBSTITUTE(D166,"'","''")&"'")&", '"&A166&"', '"&B166&"');" -> INSERT INTO public.medical_supply_product_variant (additional_desc, code, product_code) VALUES (NULL, 'PRODUCT-00081-001', 'PRODUCT-00081');
... A199: =B199&"-"&TEXT(COUNTIF(B$2:B199,B199),"000") -> PRODUCT-00112-002 | B199: PRODUCT-00112 | C199: =IFERROR(INDEX(Product!$B:$B,MATCH(B199,Product!$A:$A,0)),"NOT FOUND") -> [Biotek] Mask thanh quản 2 nòng - Laryngeal Mask Airway | E199: ="INSERT INTO public.medical_supply_product_variant (additional_desc, code, product_code) VALUES ("&IF(D199="","NULL","'"&SUBSTITUTE(D199,"'","''")&"'")&", '"&A199&"', '"&B199&"');" -> INSERT INTO public.medical_supply_product_variant (additional_desc, code, product_code) VALUES (NULL, 'PRODUCT-00112-002', 'PRODUCT-00112');
A200: =B200&"-"&TEXT(COUNTIF(B$2:B200,B200),"000") -> PRODUCT-00113-001 | B200: PRODUCT-00113 | C200: =IFERROR(INDEX(Product!$B:$B,MATCH(B200,Product!$A:$A,0)),"NOT FOUND") -> [Bornsun] Dây thở oxy 2 nhánh | D200: Kích cỡ (size): S (trẻ em) Chiều dài: 2m | E200: ="INSERT INTO public.medical_supply_product_variant (additional_desc, code, product_code) VALUES ("&IF(D200="","NULL","'"&SUBSTITUTE(D200,"'","''")&"'")&", '"&A200&"', '"&B200&"');" -> INSERT INTO public.medical_supply_product_variant (additional_desc, code, product_code) VALUES ('Kích cỡ (size): S (trẻ em) Chiều dài: 2m', 'PRODUCT-00113-001', 'PRODUCT-00113');
A201: =B201&"-"&TEXT(COUNTIF(B$2:B201,B201),"000") -> PRODUCT-00113-002 | B201: PRODUCT-00113 | C201: =IFERROR(INDEX(Product!$B:$B,MATCH(B201,Product!$A:$A,0)),"NOT FOUND") -> [Bornsun] Dây thở oxy 2 nhánh | D201: Kích cỡ (size): L (Người lớn) Chiều dài: 2m | E201: ="INSERT INTO public.medical_supply_product_variant (additional_desc, code, product_code) VALUES ("&IF(D201="","NULL","'"&SUBSTITUTE(D201,"'","''")&"'")&", '"&A201&"', '"&B201&"');" -> INSERT INTO public.medical_supply_product_variant (additional_desc, code, product_code) VALUES ('Kích cỡ (size): L (Người lớn) Chiều dài: 2m', 'PRODUCT-00113-002', 'PRODUCT-00113');
A202: =B202&"-"&TEXT(COUNTIF(B$2:B202,B202),"000") -> PRODUCT-00114-001 | B202: PRODUCT-00114 | C202: =IFERROR(INDEX(Product!$B:$B,MATCH(B202,Product!$A:$A,0)),"NOT FOUND") -> [Bornsun] Mặt nạ thở oxy | D202: Size S: dành cho trẻ sơ sinh Chiều dài dây dẫn có van nối 2 đầu: 2m | E202: ="INSERT INTO public.medical_supply_product_variant (additional_desc, code, product_code) VALUES ("&IF(D202="","NULL","'"&SUBSTITUTE(D202,"'","''")&"'")&", '"&A202&"', '"&B202&"');" -> INSERT INTO public.medical_supply_product_variant (additional_desc, code, product_code) VALUES ('Size S: dành cho trẻ sơ sinh Chiều dài dây dẫn có van nối 2 đầu: 2m', 'PRODUCT-00114-001', 'PRODUCT-00114');
A203: =B203&"-"&TEXT(COUNTIF(B$2:B203,B203),"000") -> PRODUCT-00114-002 | B203: PRODUCT-00114 | C203: =IFERROR(INDEX(Product!$B:$B,MATCH(B203,Product!$A:$A,0)),"NOT FOUND") -> [Bornsun] Mặt nạ thở oxy | D203: Size M: dành cho trẻ em Chiều dài dây dẫn có van nối 2 đầu: 2m | E203: ="INSERT INTO public.medical_supply_product_variant (additional_desc, code, product_code) VALUES ("&IF(D203="","NULL","'"&SUBSTITUTE(D203,"'","''")&"'")&", '"&A203&"', '"&B203&"');" -> INSERT INTO public.medical_supply_product_variant (additional_desc, code, product_code) VALUES ('Size M: dành cho trẻ em Chiều dài dây dẫn có van nối 2 đầu: 2m', 'PRODUCT-00114-002', 'PRODUCT-00114');
A204: =B204&"-"&TEXT(COUNTIF(B$2:B204,B204),"000") -> PRODUCT-00114-003 | B204: PRODUCT-00114 | C204: =IFERROR(INDEX(Product!$B:$B,MATCH(B204,Product!$A:$A,0)),"NOT FOUND") -> [Bornsun] Mặt nạ thở oxy | D204: Size L: dành cho người lớn Chiều dài dây dẫn có van nối 2 đầu: 2m | E204: ="INSERT INTO public.medical_supply_product_variant (additional_desc, code, product_code) VALUES ("&IF(D204="","NULL","'"&SUBSTITUTE(D204,"'","''")&"'")&", '"&A204&"', '"&B204&"');" -> INSERT INTO public.medical_supply_product_variant (additional_desc, code, product_code) VALUES ('Size L: dành cho người lớn Chiều dài dây dẫn có van nối 2 đầu: 2m', 'PRODUCT-00114-003', 'PRODUCT-00114');
A205: =B205&"-"&TEXT(COUNTIF(B$2:B205,B205),"000") -> PRODUCT-00114-004 | B205: PRODUCT-00114 | C205: =IFERROR(INDEX(Product!$B:$B,MATCH(B205,Product!$A:$A,0)),"NOT FOUND") -> [Bornsun] Mặt nạ thở oxy | D205: Size XL: dành cho người lớn Chiều dài dây dẫn có van nối 2 đầu: 2m | E205: ="INSERT INTO public.medical_supply_product_variant (additional_desc, code, product_code) VALUES ("&IF(D205="","NULL","'"&SUBSTITUTE(D205,"'","''")&"'")&", '"&A205&"', '"&B205&"');" -> INSERT INTO public.medical_supply_product_variant (additional_desc, code, product_code) VALUES ('Size XL: dành cho người lớn Chiều dài dây dẫn có van nối 2 đầu: 2m', 'PRODUCT-00114-004', 'PRODUCT-00114');
A206: =B206&"-"&TEXT(COUNTIF(B$2:B206,B206),"000") -> PRODUCT-00115-001 | B206: PRODUCT-00115 | C206: =IFERROR(INDEX(Product!$B:$B,MATCH(B206,Product!$A:$A,0)),"NOT FOUND") -> [Bornsun] Mặt nạ xông khí dung | E206: ="INSERT INTO public.medical_supply_product_variant (additional_desc, code, product_code) VALUES ("&IF(D206="","NULL","'"&SUBSTITUTE(D206,"'","''")&"'")&", '"&A206&"', '"&B206&"');" -> INSERT INTO public.medical_supply_product_variant (additional_desc, code, product_code) VALUES (NULL, 'PRODUCT-00115-001', 'PRODUCT-00115');
A207: =B207&"-"&TEXT(COUNTIF(B$2:B207,B207),"000") -> PRODUCT-00116-001 | B207: PRODUCT-00116 | C207: =IFERROR(INDEX(Product!$B:$B,MATCH(B207,Product!$A:$A,0)),"NOT FOUND") -> [Bornsun] Xông hút đờm kín | E207: ="INSERT INTO public.medical_supply_product_variant (additional_desc, code, product_code) VALUES ("&IF(D207="","NULL","'"&SUBSTITUTE(D207,"'","''")&"'")&", '"&A207&"', '"&B207&"');" -> INSERT INTO public.medical_supply_product_variant (additional_desc, code, product_code) VALUES (NULL, 'PRODUCT-00116-001', 'PRODUCT-00116');
A208: =B208&"-"&TEXT(COUNTIF(B$2:B208,B208),"000") -> PRODUCT-00116-002 | B208: PRODUCT-00116 | C208: =IFERROR(INDEX(Product!$B:$B,MATCH(B208,Product!$A:$A,0)),"NOT FOUND") -> [Bornsun] Xông hút đờm kín | E208: ="INSERT INTO public.medical_supply_product_variant (additional_desc, code, product_code) VALUES ("&IF(D208="","NULL","'"&SUBSTITUTE(D208,"'","''")&"'")&", '"&A208&"', '"&B208&"');" -> INSERT INTO public.medical_supply_product_variant (additional_desc, code, product_code) VALUES (NULL, 'PRODUCT-00116-002', 'PRODUCT-00116');
A209: =B209&"-"&TEXT(COUNTIF(B$2:B209,B209),"000") -> PRODUCT-00117-001 | B209: PRODUCT-00117 | C209: =IFERROR(INDEX(Product!$B:$B,MATCH(B209,Product!$A:$A,0)),"NOT FOUND") -> [Covidien] Nòng trong ống mở khí quản - Shiley SIC | E209: ="INSERT INTO public.medical_supply_product_variant (additional_desc, code, product_code) VALUES ("&IF(D209="","NULL","'"&SUBSTITUTE(D209,"'","''")&"'")&", '"&A209&"', '"&B209&"');" -> INSERT INTO public.medical_supply_product_variant (additional_desc, code, product_code) VALUES (NULL, 'PRODUCT-00117-001', 'PRODUCT-00117');
A210: =B210&"-"&TEXT(COUNTIF(B$2:B210,B210),"000") -> PRODUCT-00117-002 | B210: PRODUCT-00117 | C210: =IFERROR(INDEX(Product!$B:$B,MATCH(B210,Product!$A:$A,0)),"NOT FOUND") -> [Covidien] Nòng trong ống mở khí quản - Shiley SIC | E210: ="INSERT INTO public.medical_supply_product_variant (additional_desc, code, product_code) VALUES ("&IF(D210="","NULL","'"&SUBSTITUTE(D210,"'","''")&"'")&", '"&A210&"', '"&B210&"');" -> INSERT INTO public.medical_supply_product_variant (additional_desc, code, product_code) VALUES (NULL, 'PRODUCT-00117-002', 'PRODUCT-00117');
A211: =B211&"-"&TEXT(COUNTIF(B$2:B211,B211),"000") -> PRODUCT-00118-001 | B211: PRODUCT-00118 | C211: =IFERROR(INDEX(Product!$B:$B,MATCH(B211,Product!$A:$A,0)),"NOT FOUND") -> [Covidien] Ống mở khí quản 2 nòng có bóng - Shiley LPC | D211: Đường kính trong ID: 6.4 mm Đường kính ngoài OD: 10.8 mm Chiều dài: 76 mm | E211: ="INSERT INTO public.medical_supply_product_variant (additional_desc, code, product_code) VALUES ("&IF(D211="","NULL","'"&SUBSTITUTE(D211,"'","''")&"'")&", '"&A211&"', '"&B211&"');" -> INSERT INTO public.medical_supply_product_variant (additional_desc, code, product_code) VALUES ('Đường kính trong ID: 6.4 mm Đường kính ngoài OD: 10.8 mm Chiều dài: 76 mm', 'PRODUCT-00118-001', 'PRODUCT-00118');
A212: =B212&"-"&TEXT(COUNTIF(B$2:B212,B212),"000") -> PRODUCT-00118-002 | B212: PRODUCT-00118 | C212: =IFERROR(INDEX(Product!$B:$B,MATCH(B212,Product!$A:$A,0)),"NOT FOUND") -> [Covidien] Ống mở khí quản 2 nòng có bóng - Shiley LPC | D212: Đường kính trong ID: 7.6 mm Đường kính ngoài OD: 12.2 mm Chiều dài: 81 mm | E212: ="INSERT INTO public.medical_supply_product_variant (additional_desc, code, product_code) VALUES ("&IF(D212="","NULL","'"&SUBSTITUTE(D212,"'","''")&"'")&", '"&A212&"', '"&B212&"');" -> INSERT INTO public.medical_supply_product_variant (additional_desc, code, product_code) VALUES ('Đường kính trong ID: 7.6 mm Đường kính ngoài OD: 12.2 mm Chiều dài: 81 mm', 'PRODUCT-00118-002', 'PRODUCT-00118');
A213: =B213&"-"&TEXT(COUNTIF(B$2:B213,B213),"000") -> PRODUCT-00119-001 | B213: PRODUCT-00119 | C213: =IFERROR(INDEX(Product!$B:$B,MATCH(B213,Product!$A:$A,0)),"NOT FOUND") -> [Covidien] Ống mở khí quản 2 nòng có bóng, có cửa sổ - Shiley FEN | D213: Đường kính trong ID: 6.4 mm Đường kính ngoài OD: 10.8 mm Chiều dài: 76 mm | E213: ="INSERT INTO public.medical_supply_product_variant (additional_desc, code, product_code) VALUES ("&IF(D213="","NULL","'"&SUBSTITUTE(D213,"'","''")&"'")&", '"&A213&"', '"&B213&"');" -> INSERT INTO public.medical_supply_product_variant (additional_desc, code, product_code) VALUES ('Đường kính trong ID: 6.4 mm Đường kính ngoài OD: 10.8 mm Chiều dài: 76 mm', 'PRODUCT-00119-001', 'PRODUCT-00119');
A214: =B214&"-"&TEXT(COUNTIF(B$2:B214,B214),"000") -> PRODUCT-00119-002 | B214: PRODUCT-00119 | C214: =IFERROR(INDEX(Product!$B:$B,MATCH(B214,Product!$A:$A,0)),"NOT FOUND") -> [Covidien] Ống mở khí quản 2 nòng có bóng, có cửa sổ - Shiley FEN | D214: Đường kính trong ID: 7.6 mm Đường kính ngoài OD: 12.2 mm Chiều dài: 81 mm | E214: ="INSERT INTO public.medical_supply_product_variant (additional_desc, code, product_code) VALUES ("&IF(D214="","NULL","'"&SUBSTITUTE(D214,"'","''")&"'")&", '"&A214&"', '"&B214&"');" -> INSERT INTO public.medical_supply_product_variant (additional_desc, code, product_code) VALUES ('Đường kính trong ID: 7.6 mm Đường kính ngoài OD: 12.2 mm Chiều dài: 81 mm', 'PRODUCT-00119-002', 'PRODUCT-00119');
A215: =B215&"-"&TEXT(COUNTIF(B$2:B215,B215),"000") -> PRODUCT-00120-001 | B215: PRODUCT-00120 | C215: =IFERROR(INDEX(Product!$B:$B,MATCH(B215,Product!$A:$A,0)),"NOT FOUND") -> [Covidien] Ống mở khí quản 2 nòng không bóng, có cửa sổ - Shiley CFN | D215: Đường kính trong ID: 6.4 mm Đường kính ngoài OD: 10.8 mm Chiều dài: 76 mm | E215: ="INSERT INTO public.medical_supply_product_variant (additional_desc, code, product_code) VALUES ("&IF(D215="","NULL","'"&SUBSTITUTE(D215,"'","''")&"'")&", '"&A215&"', '"&B215&"');" -> INSERT INTO public.medical_supply_product_variant (additional_desc, code, product_code) VALUES ('Đường kính trong ID: 6.4 mm Đường kính ngoài OD: 10.8 mm Chiều dài: 76 mm', 'PRODUCT-00120-001', 'PRODUCT-00120');
A216: =B216&"-"&TEXT(COUNTIF(B$2:B216,B216),"000") -> PRODUCT-00120-002 | B216: PRODUCT-00120 | C216: =IFERROR(INDEX(Product!$B:$B,MATCH(B216,Product!$A:$A,0)),"NOT FOUND") -> [Covidien] Ống mở khí quản 2 nòng không bóng, có cửa sổ - Shiley CFN | D216: Đường kính trong ID: 7.6 mm Đường kính ngoài OD: 12.2 mm Chiều dài: 81 mm | E216: ="INSERT INTO public.medical_supply_product_variant (additional_desc, code, product_code) VALUES ("&IF(D216="","NULL","'"&SUBSTITUTE(D216,"'","''")&"'")&", '"&A216&"', '"&B216&"');" -> INSERT INTO public.medical_supply_product_variant (additional_desc, code, product_code) VALUES ('Đường kính trong ID: 7.6 mm Đường kính ngoài OD: 12.2 mm Chiều dài: 81 mm', 'PRODUCT-00120-002', 'PRODUCT-00120');
A217: =B217&"-"&TEXT(COUNTIF(B$2:B217,B217),"000") -> PRODUCT-00121-001 | B217: PRODUCT-00121 | C217: =IFERROR(INDEX(Product!$B:$B,MATCH(B217,Product!$A:$A,0)),"NOT FOUND") -> [Fuji System] Ống chẹn phế quản cô lập phổi - Uniblocker | D217: Size: 5Fr (trẻ em) OD: 1.7 mm Chiều dài: 325 mm Thể tích bơm bóng tối đa: 3 mL | E217: ="INSERT INTO public.medical_supply_product_variant (additional_desc, code, product_code) VALUES ("&IF(D217="","NULL","'"&SUBSTITUTE(D217,"'","''")&"'")&", '"&A217&"', '"&B217&"');" -> INSERT INTO public.medical_supply_product_variant (additional_desc, code, product_code) VALUES ('Size: 5Fr (trẻ em) OD: 1.7 mm Chiều dài: 325 mm Thể tích bơm bóng tối đa: 3 mL', 'PRODUCT-00121-001', 'PRODUCT-00121');
A218: =B218&"-"&TEXT(COUNTIF(B$2:B218,B218),"000") -> PRODUCT-00121-002 | B218: PRODUCT-00121 | C218: =IFERROR(INDEX(Product!$B:$B,MATCH(B218,Product!$A:$A,0)),"NOT FOUND") -> [Fuji System] Ống chẹn phế quản cô lập phổi - Uniblocker | D218: Size: 9Fr (người lớn) OD: 3.0 mm Chiều dài: 500 mm Thể tích bơm bóng tối đa: 8 mL | E218: ="INSERT INTO public.medical_supply_product_variant (additional_desc, code, product_code) VALUES ("&IF(D218="","NULL","'"&SUBSTITUTE(D218,"'","''")&"'")&", '"&A218&"', '"&B218&"');" -> INSERT INTO public.medical_supply_product_variant (additional_desc, code, product_code) VALUES ('Size: 9Fr (người lớn) OD: 3.0 mm Chiều dài: 500 mm Thể tích bơm bóng tối đa: 8 mL', 'PRODUCT-00121-002', 'PRODUCT-00121');
A219: =B219&"-"&TEXT(COUNTIF(B$2:B219,B219),"000") -> PRODUCT-00122-001 | B219: PRODUCT-00122 | C219: =IFERROR(INDEX(Product!$B:$B,MATCH(B219,Product!$A:$A,0)),"NOT FOUND") -> [Fuji System] Ống nội khí quản 2 nòng - Silbroncho (Carlens) | D219: Đường kính trong: 4.1/6.5 ID (mm): 9.5/12.3 Đường kính ngoài: 40 OD (mm): 5 Thế tích tối đa của cuff (mL): 35 Bóng chèn khí quản: 4.5/7.0 Bóng chèn phế quản: 10.0/13.3 | E219: ="INSERT INTO public.medical_supply_product_variant (additional_desc, code, product_code) VALUES ("&IF(D219="","NULL","'"&SUBSTITUTE(D219,"'","''")&"'")&", '"&A219&"', '"&B219&"');" -> INSERT INTO public.medical_supply_product_variant (additional_desc, code, product_code) VALUES ('Đường kính trong: 4.1/6.5 ID (mm): 9.5/12.3 Đường kính ngoài: 40 OD (mm): 5 Thế tích tối đa của cuff (mL): 35 Bóng chèn khí quản: 4.5/7.0 Bóng chèn phế quản: 10.0/13.3', 'PRODUCT-00122-001', 'PRODUCT-00122');
A220: =B220&"-"&TEXT(COUNTIF(B$2:B220,B220),"000") -> PRODUCT-00122-002 | B220: PRODUCT-00122 | C220: =IFERROR(INDEX(Product!$B:$B,MATCH(B220,Product!$A:$A,0)),"NOT FOUND") -> [Fuji System] Ống nội khí quản 2 nòng - Silbroncho (Carlens) | E220: ="INSERT INTO public.medical_supply_product_variant (additional_desc, code, product_code) VALUES ("&IF(D220="","NULL","'"&SUBSTITUTE(D220,"'","''")&"'")&", '"&A220&"', '"&B220&"');" -> INSERT INTO public.medical_supply_product_variant (additional_desc, code, product_code) VALUES (NULL, 'PRODUCT-00122-002', 'PRODUCT-00122');
A221: =B221&"-"&TEXT(COUNTIF(B$2:B221,B221),"000") -> PRODUCT-00122-003 | B221: PRODUCT-00122 | C221: =IFERROR(INDEX(Product!$B:$B,MATCH(B221,Product!$A:$A,0)),"NOT FOUND") -> [Fuji System] Ống nội khí quản 2 nòng - Silbroncho (Carlens) | E221: ="INSERT INTO public.medical_supply_product_variant (additional_desc, code, product_code) VALUES ("&IF(D221="","NULL","'"&SUBSTITUTE(D221,"'","''")&"'")&", '"&A221&"', '"&B221&"');" -> INSERT INTO public.medical_supply_product_variant (additional_desc, code, product_code) VALUES (NULL, 'PRODUCT-00122-003', 'PRODUCT-00122');
A222: =B222&"-"&TEXT(COUNTIF(B$2:B222,B222),"000") -> PRODUCT-00123-001 | B222: PRODUCT-00123 | C222: =IFERROR(INDEX(Product!$B:$B,MATCH(B222,Product!$A:$A,0)),"NOT FOUND") -> [Fuji System] Ống nội khí quản tích hợp sẵn ống chặn phổi - Univent™ | E222: ="INSERT INTO public.medical_supply_product_variant (additional_desc, code, product_code) VALUES ("&IF(D222="","NULL","'"&SUBSTITUTE(D222,"'","''")&"'")&", '"&A222&"', '"&B222&"');" -> INSERT INTO public.medical_supply_product_variant (additional_desc, code, product_code) VALUES (NULL, 'PRODUCT-00123-001', 'PRODUCT-00123');
...

Sheet Sellable Unit
A1: Mã đơn vị bán | B1: Mã biến thể | C1: Mã sản phẩm | D1: Tên sản phẩm (rút gọn) | E1: Biến thể | F1: Đơn vị bán lẻ | G1: Quy cách đóng gói | H1: Số lượng / đơn vị | I1: UOM | J1: Giá bán lẻ (VND) | K1: Nguồn giá | L1: Dòng giá (Draft Product) | M1: Tên sản phẩm (nguồn) | N1: Dòng nguồn | O1: INSERT INTO public.medical_supply_sellable_unit (id, code, price, quantity, sale_uom, product_variant_code) VALUES (1, '1', 1, 1, '1', 'PRODUCT-00068-003');
A2: =B2&"-"&TEXT(COUNTIF(B$2:B2,B2),"00") -> PRODUCT-00001-001-01 | B2: PRODUCT-00001-001 | C2: =_xlfn.XLOOKUP(B2,'Product Variant'!$A:$A,'Product Variant'!$B:$B,"NOT FOUND") -> PRODUCT-00001 | D2: =_xlfn.XLOOKUP(B2,'Product Variant'!$A:$A,'Product Variant'!$C:$C,"NOT FOUND") -> [Greetmed] Phao chống loét cao su | E2: {=_xlfn.TEXTJOIN(" / ",TRUE,_xlfn.XLOOKUP(B2&"|ATTR-27",'Product Variant Attribute'!$A$2:$A$2000&"|"&'Product Variant Attribute'!$D$2:$D$2000,'Product Variant Attribute'!$F$2:$F$2000,""),_xlfn.XLOOKUP(B2&"|ATTR-24",'Product Variant Attribute'!$A$2:$A$2000&"|"&'Product Variant Attribute'!$D$2:$D$2000,'Product Variant Attribute'!$F$2:$F$2000,""))} | F2: Cái | G2: 1 cái | H2: =IFERROR(--LEFT(G2,FIND(" ",G2&" ")-1),"") -> 1 | I2: =_xlfn.XLOOKUP(C2,Product!$A:$A,Product!$G:$G,"NOT FOUND") -> cái | J2: 100000 | K2: Giá sản phẩm (chung) | L2: 8 | M2: Phao chống loét cao su hiệu Greetmed | N2: 448 | O2: ="INSERT INTO public.medical_supply_sellable_unit (code, price, quantity, sale_uom, product_variant_code) VALUES ('"&A2&"', "&IF(J2="","NULL",J2)&", "&IF(H2="","NULL",H2)&", "&IF(F2="","NULL","'"&SUBSTITUTE(F2,"'","''")&"'")&", '"&B2&"');" -> INSERT INTO public.medical_supply_sellable_unit (code, price, quantity, sale_uom, product_variant_code) VALUES ('PRODUCT-00001-001-01', 100000, 1, 'Cái', 'PRODUCT-00001-001');
A3: =B3&"-"&TEXT(COUNTIF(B$2:B3,B3),"00") -> PRODUCT-00002-001-01 | B3: PRODUCT-00002-001 | C3: =_xlfn.XLOOKUP(B3,'Product Variant'!$A:$A,'Product Variant'!$B:$B,"NOT FOUND") -> PRODUCT-00002 | D3: =_xlfn.XLOOKUP(B3,'Product Variant'!$A:$A,'Product Variant'!$C:$C,"NOT FOUND") -> [iMedicare] Đệm hơi chống lở loét - iAM-8P | E3: {=_xlfn.TEXTJOIN(" / ",TRUE,_xlfn.XLOOKUP(B3&"|ATTR-27",'Product Variant Attribute'!$A$2:$A$2000&"|"&'Product Variant Attribute'!$D$2:$D$2000,'Product Variant Attribute'!$F$2:$F$2000,""),_xlfn.XLOOKUP(B3&"|ATTR-24",'Product Variant Attribute'!$A$2:$A$2000&"|"&'Product Variant Attribute'!$D$2:$D$2000,'Product Variant Attribute'!$F$2:$F$2000,""))} | F3: Bộ | G3: 1 bộ | H3: =IFERROR(--LEFT(G3,FIND(" ",G3&" ")-1),"") -> 1 | I3: =_xlfn.XLOOKUP(C3,Product!$A:$A,Product!$G:$G,"NOT FOUND") -> bộ | J3: 750000 | K3: Giá sản phẩm (chung) – khớp theo tên | L3: 537 | M3: Đệm hơi chống lở loét iMediCare iAM-8P | N3: 214 | O3: ="INSERT INTO public.medical_supply_sellable_unit (code, price, quantity, sale_uom, product_variant_code) VALUES ('"&A3&"', "&IF(J3="","NULL",J3)&", "&IF(H3="","NULL",H3)&", "&IF(F3="","NULL","'"&SUBSTITUTE(F3,"'","''")&"'")&", '"&B3&"');" -> INSERT INTO public.medical_supply_sellable_unit (code, price, quantity, sale_uom, product_variant_code) VALUES ('PRODUCT-00002-001-01', 750000, 1, 'Bộ', 'PRODUCT-00002-001');
A4: =B4&"-"&TEXT(COUNTIF(B$2:B4,B4),"00") -> PRODUCT-00003-001-01 | B4: PRODUCT-00003-001 | C4: =_xlfn.XLOOKUP(B4,'Product Variant'!$A:$A,'Product Variant'!$B:$B,"NOT FOUND") -> PRODUCT-00003 | D4: =_xlfn.XLOOKUP(B4,'Product Variant'!$A:$A,'Product Variant'!$C:$C,"NOT FOUND") -> [Lucass] Đệm hơi chống lở loét - LC-389 | E4: {=_xlfn.TEXTJOIN(" / ",TRUE,_xlfn.XLOOKUP(B4&"|ATTR-27",'Product Variant Attribute'!$A$2:$A$2000&"|"&'Product Variant Attribute'!$D$2:$D$2000,'Product Variant Attribute'!$F$2:$F$2000,""),_xlfn.XLOOKUP(B4&"|ATTR-24",'Product Variant Attribute'!$A$2:$A$2000&"|"&'Product Variant Attribute'!$D$2:$D$2000,'Product Variant Attribute'!$F$2:$F$2000,""))} | F4: Bộ | G4: 1 bộ | H4: =IFERROR(--LEFT(G4,FIND(" ",G4&" ")-1),"") -> 1 | I4: =_xlfn.XLOOKUP(C4,Product!$A:$A,Product!$G:$G,"NOT FOUND") -> bộ | J4: 700000 | K4: Giá sản phẩm (chung) – khớp theo tên | L4: 194 | M4: Đệm hơi chống lở loét Lucass LC-389 | N4: 215 | O4: ="INSERT INTO public.medical_supply_sellable_unit (code, price, quantity, sale_uom, product_variant_code) VALUES ('"&A4&"', "&IF(J4="","NULL",J4)&", "&IF(H4="","NULL",H4)&", "&IF(F4="","NULL","'"&SUBSTITUTE(F4,"'","''")&"'")&", '"&B4&"');" -> INSERT INTO public.medical_supply_sellable_unit (code, price, quantity, sale_uom, product_variant_code) VALUES ('PRODUCT-00003-001-01', 700000, 1, 'Bộ', 'PRODUCT-00003-001');
A5: =B5&"-"&TEXT(COUNTIF(B$2:B5,B5),"00") -> PRODUCT-00004-001-01 | B5: PRODUCT-00004-001 | C5: =_xlfn.XLOOKUP(B5,'Product Variant'!$A:$A,'Product Variant'!$B:$B,"NOT FOUND") -> PRODUCT-00004 | D5: =_xlfn.XLOOKUP(B5,'Product Variant'!$A:$A,'Product Variant'!$C:$C,"NOT FOUND") -> [Rionet] Máy trợ thính có dây đeo - HA-20DX | E5: {=_xlfn.TEXTJOIN(" / ",TRUE,_xlfn.XLOOKUP(B5&"|ATTR-27",'Product Variant Attribute'!$A$2:$A$2000&"|"&'Product Variant Attribute'!$D$2:$D$2000,'Product Variant Attribute'!$F$2:$F$2000,""),_xlfn.XLOOKUP(B5&"|ATTR-24",'Product Variant Attribute'!$A$2:$A$2000&"|"&'Product Variant Attribute'!$D$2:$D$2000,'Product Variant Attribute'!$F$2:$F$2000,""))} | F5: Cái | G5: 1 cái | H5: =IFERROR(--LEFT(G5,FIND(" ",G5&" ")-1),"") -> 1 | I5: =_xlfn.XLOOKUP(C5,Product!$A:$A,Product!$G:$G,"NOT FOUND") -> cái | J5: 1150000 | K5: Giá sản phẩm (chung) | L5: 410 | M5: Máy trợ thính có dây đeo Rionet HA-20DX | N5: 332 | O5: ="INSERT INTO public.medical_supply_sellable_unit (code, price, quantity, sale_uom, product_variant_code) VALUES ('"&A5&"', "&IF(J5="","NULL",J5)&", "&IF(H5="","NULL",H5)&", "&IF(F5="","NULL","'"&SUBSTITUTE(F5,"'","''")&"'")&", '"&B5&"');" -> INSERT INTO public.medical_supply_sellable_unit (code, price, quantity, sale_uom, product_variant_code) VALUES ('PRODUCT-00004-001-01', 1150000, 1, 'Cái', 'PRODUCT-00004-001');
A6: =B6&"-"&TEXT(COUNTIF(B$2:B6,B6),"00") -> PRODUCT-00005-001-01 | B6: PRODUCT-00005-001 | C6: =_xlfn.XLOOKUP(B6,'Product Variant'!$A:$A,'Product Variant'!$B:$B,"NOT FOUND") -> PRODUCT-00005 | D6: =_xlfn.XLOOKUP(B6,'Product Variant'!$A:$A,'Product Variant'!$C:$C,"NOT FOUND") -> [Rionet] Máy trợ thính không dây - HB-23P | E6: {=_xlfn.TEXTJOIN(" / ",TRUE,_xlfn.XLOOKUP(B6&"|ATTR-27",'Product Variant Attribute'!$A$2:$A$2000&"|"&'Product Variant Attribute'!$D$2:$D$2000,'Product Variant Attribute'!$F$2:$F$2000,""),_xlfn.XLOOKUP(B6&"|ATTR-24",'Product Variant Attribute'!$A$2:$A$2000&"|"&'Product Variant Attribute'!$D$2:$D$2000,'Product Variant Attribute'!$F$2:$F$2000,""))} | F6: Cái | G6: 1 cái | H6: =IFERROR(--LEFT(G6,FIND(" ",G6&" ")-1),"") -> 1 | I6: =_xlfn.XLOOKUP(C6,Product!$A:$A,Product!$G:$G,"NOT FOUND") -> cái | J6: 2150000 | K6: Giá sản phẩm (chung) | L6: 409 | M6: Máy trợ thính không dây Rionet HB-23P | N6: 333 | O6: ="INSERT INTO public.medical_supply_sellable_unit (code, price, quantity, sale_uom, product_variant_code) VALUES ('"&A6&"', "&IF(J6="","NULL",J6)&", "&IF(H6="","NULL",H6)&", "&IF(F6="","NULL","'"&SUBSTITUTE(F6,"'","''")&"'")&", '"&B6&"');" -> INSERT INTO public.medical_supply_sellable_unit (code, price, quantity, sale_uom, product_variant_code) VALUES ('PRODUCT-00005-001-01', 2150000, 1, 'Cái', 'PRODUCT-00005-001');
A7: =B7&"-"&TEXT(COUNTIF(B$2:B7,B7),"00") -> PRODUCT-00006-001-01 | B7: PRODUCT-00006-001 | C7: =_xlfn.XLOOKUP(B7,'Product Variant'!$A:$A,'Product Variant'!$B:$B,"NOT FOUND") -> PRODUCT-00006 | D7: =_xlfn.XLOOKUP(B7,'Product Variant'!$A:$A,'Product Variant'!$C:$C,"NOT FOUND") -> [Rionet] Máy trợ thính không dây thông minh - HM-06 | E7: {=_xlfn.TEXTJOIN(" / ",TRUE,_xlfn.XLOOKUP(B7&"|ATTR-27",'Product Variant Attribute'!$A$2:$A$2000&"|"&'Product Variant Attribute'!$D$2:$D$2000,'Product Variant Attribute'!$F$2:$F$2000,""),_xlfn.XLOOKUP(B7&"|ATTR-24",'Product Variant Attribute'!$A$2:$A$2000&"|"&'Product Variant Attribute'!$D$2:$D$2000,'Product Variant Attribute'!$F$2:$F$2000,""))} | F7: Cái | G7: 1 cái | H7: =IFERROR(--LEFT(G7,FIND(" ",G7&" ")-1),"") -> 1 | I7: =_xlfn.XLOOKUP(C7,Product!$A:$A,Product!$G:$G,"NOT FOUND") -> cái | J7: 3900000 | K7: Giá sản phẩm (chung) | L7: 408 | M7: Máy trợ thính không dây thông minh Rionet HM-06 | N7: 334 | O7: ="INSERT INTO public.medical_supply_sellable_unit (code, price, quantity, sale_uom, product_variant_code) VALUES ('"&A7&"', "&IF(J7="","NULL",J7)&", "&IF(H7="","NULL",H7)&", "&IF(F7="","NULL","'"&SUBSTITUTE(F7,"'","''")&"'")&", '"&B7&"');" -> INSERT INTO public.medical_supply_sellable_unit (code, price, quantity, sale_uom, product_variant_code) VALUES ('PRODUCT-00006-001-01', 3900000, 1, 'Cái', 'PRODUCT-00006-001');
A8: =B8&"-"&TEXT(COUNTIF(B$2:B8,B8),"00") -> PRODUCT-00007-001-01 | B8: PRODUCT-00007-001 | C8: =_xlfn.XLOOKUP(B8,'Product Variant'!$A:$A,'Product Variant'!$B:$B,"NOT FOUND") -> PRODUCT-00007 | D8: =_xlfn.XLOOKUP(B8,'Product Variant'!$A:$A,'Product Variant'!$C:$C,"NOT FOUND") -> [WaterJet] Máy tăm nước - Cordless Maxi | E8: {=_xlfn.TEXTJOIN(" / ",TRUE,_xlfn.XLOOKUP(B8&"|ATTR-27",'Product Variant Attribute'!$A$2:$A$2000&"|"&'Product Variant Attribute'!$D$2:$D$2000,'Product Variant Attribute'!$F$2:$F$2000,""),_xlfn.XLOOKUP(B8&"|ATTR-24",'Product Variant Attribute'!$A$2:$A$2000&"|"&'Product Variant Attribute'!$D$2:$D$2000,'Product Variant Attribute'!$F$2:$F$2000,""))} | F8: Cái | G8: 1 cái | H8: =IFERROR(--LEFT(G8,FIND(" ",G8&" ")-1),"") -> 1 | I8: =_xlfn.XLOOKUP(C8,Product!$A:$A,Product!$G:$G,"NOT FOUND") -> cái | J8: 1350000 | K8: Giá sản phẩm (chung) | L8: 451 | M8: Máy tăm nước Waterjet Cordloss Maxi | N8: 327 | O8: ="INSERT INTO public.medical_supply_sellable_unit (code, price, quantity, sale_uom, product_variant_code) VALUES ('"&A8&"', "&IF(J8="","NULL",J8)&", "&IF(H8="","NULL",H8)&", "&IF(F8="","NULL","'"&SUBSTITUTE(F8,"'","''")&"'")&", '"&B8&"');" -> INSERT INTO public.medical_supply_sellable_unit (code, price, quantity, sale_uom, product_variant_code) VALUES ('PRODUCT-00007-001-01', 1350000, 1, 'Cái', 'PRODUCT-00007-001');
A9: =B9&"-"&TEXT(COUNTIF(B$2:B9,B9),"00") -> PRODUCT-00008-001-01 | B9: PRODUCT-00008-001 | C9: =_xlfn.XLOOKUP(B9,'Product Variant'!$A:$A,'Product Variant'!$B:$B,"NOT FOUND") -> PRODUCT-00008 | D9: =_xlfn.XLOOKUP(B9,'Product Variant'!$A:$A,'Product Variant'!$C:$C,"NOT FOUND") -> [Young Chemical Vina] Miếng dán mụn - Somaderm Spot S (32 miếng) | E9: {=_xlfn.TEXTJOIN(" / ",TRUE,_xlfn.XLOOKUP(B9&"|ATTR-27",'Product Variant Attribute'!$A$2:$A$2000&"|"&'Product Variant Attribute'!$D$2:$D$2000,'Product Variant Attribute'!$F$2:$F$2000,""),_xlfn.XLOOKUP(B9&"|ATTR-24",'Product Variant Attribute'!$A$2:$A$2000&"|"&'Product Variant Attribute'!$D$2:$D$2000,'Product Variant Attribute'!$F$2:$F$2000,""))} | F9: Hộp | G9: 32 miếng | H9: =IFERROR(--LEFT(G9,FIND(" ",G9&" ")-1),"") -> 32 | I9: =_xlfn.XLOOKUP(C9,Product!$A:$A,Product!$G:$G,"NOT FOUND") -> miếng | J9: 73000 | K9: Giá sản phẩm (chung) – khớp theo tên | L9: 390 | M9: Miếng dán mụn Somaderm Spot - S ngăn ngừa sẹo do mụn (32 miếng) | N9: 346 | O9: ="INSERT INTO public.medical_supply_sellable_unit (code, price, quantity, sale_uom, product_variant_code) VALUES ('"&A9&"', "&IF(J9="","NULL",J9)&", "&IF(H9="","NULL",H9)&", "&IF(F9="","NULL","'"&SUBSTITUTE(F9,"'","''")&"'")&", '"&B9&"');" -> INSERT INTO public.medical_supply_sellable_unit (code, price, quantity, sale_uom, product_variant_code) VALUES ('PRODUCT-00008-001-01', 73000, 32, 'Hộp', 'PRODUCT-00008-001');
A10: =B10&"-"&TEXT(COUNTIF(B$2:B10,B10),"00") -> PRODUCT-00250-001-01 | B10: PRODUCT-00250-001 | C10: =_xlfn.XLOOKUP(B10,'Product Variant'!$A:$A,'Product Variant'!$B:$B,"NOT FOUND") -> PRODUCT-00250 | D10: =_xlfn.XLOOKUP(B10,'Product Variant'!$A:$A,'Product Variant'!$C:$C,"NOT FOUND") -> [Young Chemical Vina] Miếng dán mụn - Somaderm Spot (24 miếng) | E10: {=_xlfn.TEXTJOIN(" / ",TRUE,_xlfn.XLOOKUP(B10&"|ATTR-27",'Product Variant Attribute'!$A$2:$A$2000&"|"&'Product Variant Attribute'!$D$2:$D$2000,'Product Variant Attribute'!$F$2:$F$2000,""),_xlfn.XLOOKUP(B10&"|ATTR-24",'Product Variant Attribute'!$A$2:$A$2000&"|"&'Product Variant Attribute'!$D$2:$D$2000,'Product Variant Attribute'!$F$2:$F$2000,""))} | F10: Hộp | G10: 24 miếng | H10: =IFERROR(--LEFT(G10,FIND(" ",G10&" ")-1),"") -> 24 | I10: =_xlfn.XLOOKUP(C10,Product!$A:$A,Product!$G:$G,"NOT FOUND") -> miếng | J10: 58000 | K10: Giá sản phẩm (chung) – khớp theo tên | L10: 436 | M10: Miếng dán mụn Somaderm Spot hỗ trợ làm lành vết thương (24 miếng) | N10: 347 | O10: ="INSERT INTO public.medical_supply_sellable_unit (code, price, quantity, sale_uom, product_variant_code) VALUES ('"&A10&"', "&IF(J10="","NULL",J10)&", "&IF(H10="","NULL",H10)&", "&IF(F10="","NULL","'"&SUBSTITUTE(F10,"'","''")&"'")&", '"&B10&"');" -> INSERT INTO public.medical_supply_sellable_unit (code, price, quantity, sale_uom, product_variant_code) VALUES ('PRODUCT-00250-001-01', 58000, 24, 'Hộp', 'PRODUCT-00250-001');
A11: =B11&"-"&TEXT(COUNTIF(B$2:B11,B11),"00") -> PRODUCT-00251-001-01 | B11: PRODUCT-00251-001 | C11: =_xlfn.XLOOKUP(B11,'Product Variant'!$A:$A,'Product Variant'!$B:$B,"NOT FOUND") -> PRODUCT-00251 | D11: =_xlfn.XLOOKUP(B11,'Product Variant'!$A:$A,'Product Variant'!$C:$C,"NOT FOUND") -> [Young Chemical Vina] Miếng dán mụn - Somaderm Spot (18 miếng) | E11: {=_xlfn.TEXTJOIN(" / ",TRUE,_xlfn.XLOOKUP(B11&"|ATTR-27",'Product Variant Attribute'!$A$2:$A$2000&"|"&'Product Variant Attribute'!$D$2:$D$2000,'Product Variant Attribute'!$F$2:$F$2000,""),_xlfn.XLOOKUP(B11&"|ATTR-24",'Product Variant Attribute'!$A$2:$A$2000&"|"&'Product Variant Attribute'!$D$2:$D$2000,'Product Variant Attribute'!$F$2:$F$2000,""))} | F11: Hộp | G11: 18 miếng | H11: =IFERROR(--LEFT(G11,FIND(" ",G11&" ")-1),"") -> 18 | I11: =_xlfn.XLOOKUP(C11,Product!$A:$A,Product!$G:$G,"NOT FOUND") -> miếng | J11: 45000 | K11: Giá sản phẩm (chung) – khớp theo tên | L11: 391 | M11: Miếng dán mụn Somaderm Spot hỗ trợ nhanh lành vết thương (18 miếng) | N11: 348 | O11: ="INSERT INTO public.medical_supply_sellable_unit (code, price, quantity, sale_uom, product_variant_code) VALUES ('"&A11&"', "&IF(J11="","NULL",J11)&", "&IF(H11="","NULL",H11)&", "&IF(F11="","NULL","'"&SUBSTITUTE(F11,"'","''")&"'")&", '"&B11&"');" -> INSERT INTO public.medical_supply_sellable_unit (code, price, quantity, sale_uom, product_variant_code) VALUES ('PRODUCT-00251-001-01', 45000, 18, 'Hộp', 'PRODUCT-00251-001');
A12: =B12&"-"&TEXT(COUNTIF(B$2:B12,B12),"00") -> PRODUCT-00009-001-01 | B12: PRODUCT-00009-001 | C12: =_xlfn.XLOOKUP(B12,'Product Variant'!$A:$A,'Product Variant'!$B:$B,"NOT FOUND") -> PRODUCT-00009 | D12: =_xlfn.XLOOKUP(B12,'Product Variant'!$A:$A,'Product Variant'!$C:$C,"NOT FOUND") -> [Young Chemical Vina] Miếng dán mụn - Somaderm-Thin (Ø10mm) | E12: {=_xlfn.TEXTJOIN(" / ",TRUE,_xlfn.XLOOKUP(B12&"|ATTR-27",'Product Variant Attribute'!$A$2:$A$2000&"|"&'Product Variant Attribute'!$D$2:$D$2000,'Product Variant Attribute'!$F$2:$F$2000,""),_xlfn.XLOOKUP(B12&"|ATTR-24",'Product Variant Attribute'!$A$2:$A$2000&"|"&'Product Variant Attribute'!$D$2:$D$2000,'Product Variant Attribute'!$F$2:$F$2000,""))} | F12: Hộp | G12: 12 miếng | H12: =IFERROR(--LEFT(G12,FIND(" ",G12&" ")-1),"") -> 12 | I12: =_xlfn.XLOOKUP(C12,Product!$A:$A,Product!$G:$G,"NOT FOUND") -> miếng | J12: 48000 | K12: Giá sản phẩm (chung) – khớp theo tên | L12: 437 | M12: Miếng dán mụn mỏng Somaderm-Thin ngăn sẹo, giảm thâm (12 miếng) | N12: 345 | O12: ="INSERT INTO public.medical_supply_sellable_unit (code, price, quantity, sale_uom, product_variant_code) VALUES ('"&A12&"', "&IF(J12="","NULL",J12)&", "&IF(H12="","NULL",H12)&", "&IF(F12="","NULL","'"&SUBSTITUTE(F12,"'","''")&"'")&", '"&B12&"');" -> INSERT INTO public.medical_supply_sellable_unit (code, price, quantity, sale_uom, product_variant_code) VALUES ('PRODUCT-00009-001-01', 48000, 12, 'Hộp', 'PRODUCT-00009-001');
A13: =B13&"-"&TEXT(COUNTIF(B$2:B13,B13),"00") -> PRODUCT-00009-001-02 | B13: PRODUCT-00009-001 | C13: =_xlfn.XLOOKUP(B13,'Product Variant'!$A:$A,'Product Variant'!$B:$B,"NOT FOUND") -> PRODUCT-00009 | D13: =_xlfn.XLOOKUP(B13,'Product Variant'!$A:$A,'Product Variant'!$C:$C,"NOT FOUND") -> [Young Chemical Vina] Miếng dán mụn - Somaderm-Thin (Ø10mm) | E13: {=_xlfn.TEXTJOIN(" / ",TRUE,_xlfn.XLOOKUP(B13&"|ATTR-27",'Product Variant Attribute'!$A$2:$A$2000&"|"&'Product Variant Attribute'!$D$2:$D$2000,'Product Variant Attribute'!$F$2:$F$2000,""),_xlfn.XLOOKUP(B13&"|ATTR-24",'Product Variant Attribute'!$A$2:$A$2000&"|"&'Product Variant Attribute'!$D$2:$D$2000,'Product Variant Attribute'!$F$2:$F$2000,""))} | F13: Hộp | G13: 24 miếng | H13: =IFERROR(--LEFT(G13,FIND(" ",G13&" ")-1),"") -> 24 | I13: =_xlfn.XLOOKUP(C13,Product!$A:$A,Product!$G:$G,"NOT FOUND") -> miếng | J13: 84000 | K13: Giá sản phẩm (chung) – khớp theo tên | L13: 389 | M13: Miếng dán mụn Somaderm-Thin giảm hình thành sẹo loại mỏng (24 miếng) | N13: 349 | O13: ="INSERT INTO public.medical_supply_sellable_unit (code, price, quantity, sale_uom, product_variant_code) VALUES ('"&A13&"', "&IF(J13="","NULL",J13)&", "&IF(H13="","NULL",H13)&", "&IF(F13="","NULL","'"&SUBSTITUTE(F13,"'","''")&"'")&", '"&B13&"');" -> INSERT INTO public.medical_supply_sellable_unit (code, price, quantity, sale_uom, product_variant_code) VALUES ('PRODUCT-00009-001-02', 84000, 24, 'Hộp', 'PRODUCT-00009-001');
A14: =B14&"-"&TEXT(COUNTIF(B$2:B14,B14),"00") -> PRODUCT-00010-001-01 | B14: PRODUCT-00010-001 | C14: =_xlfn.XLOOKUP(B14,'Product Variant'!$A:$A,'Product Variant'!$B:$B,"NOT FOUND") -> PRODUCT-00010 | D14: =_xlfn.XLOOKUP(B14,'Product Variant'!$A:$A,'Product Variant'!$C:$C,"NOT FOUND") -> Mặt nạ xông hơi mắt ngải cứu - Mugwort Steam Eyes Mask | E14: {=_xlfn.TEXTJOIN(" / ",TRUE,_xlfn.XLOOKUP(B14&"|ATTR-27",'Product Variant Attribute'!$A$2:$A$2000&"|"&'Product Variant Attribute'!$D$2:$D$2000,'Product Variant Attribute'!$F$2:$F$2000,""),_xlfn.XLOOKUP(B14&"|ATTR-24",'Product Variant Attribute'!$A$2:$A$2000&"|"&'Product Variant Attribute'!$D$2:$D$2000,'Product Variant Attribute'!$F$2:$F$2000,""))} | F14: Túi | G14: 1 miếng | H14: 1 | I14: =_xlfn.XLOOKUP(C14,Product!$A:$A,Product!$G:$G,"NOT FOUND") -> miếng | J14: 15000 | K14: Giá (theo biến thể) – nguồn có nhiều giá: 15000 / 70000 | L14: 352, 353 | M14: Mặt nạ xông hơi mắt ngải cứu Mugwort Steam Eyes Mask loại bỏ quầng thâm, giảm mỏi mắt căng thẳng | N14: 297, 298 | O14: ="INSERT INTO public.medical_supply_sellable_unit (code, price, quantity, sale_uom, product_variant_code) VALUES ('"&A14&"', "&IF(J14="","NULL",J14)&", "&IF(H14="","NULL",H14)&", "&IF(F14="","NULL","'"&SUBSTITUTE(F14,"'","''")&"'")&", '"&B14&"');" -> INSERT INTO public.medical_supply_sellable_unit (code, price, quantity, sale_uom, product_variant_code) VALUES ('PRODUCT-00010-001-01', 15000, 1, 'Túi', 'PRODUCT-00010-001');
A15: =B15&"-"&TEXT(COUNTIF(B$2:B15,B15),"00") -> PRODUCT-00011-001-01 | B15: PRODUCT-00011-001 | C15: =_xlfn.XLOOKUP(B15,'Product Variant'!$A:$A,'Product Variant'!$B:$B,"NOT FOUND") -> PRODUCT-00011 | D15: =_xlfn.XLOOKUP(B15,'Product Variant'!$A:$A,'Product Variant'!$C:$C,"NOT FOUND") -> [3M™] Bộ gạc xốp phủ vết thương điều trị áp lực âm VAC kèm chức năng rửa - Veraflo™ | E15: {=_xlfn.TEXTJOIN(" / ",TRUE,_xlfn.XLOOKUP(B15&"|ATTR-27",'Product Variant Attribute'!$A$2:$A$2000&"|"&'Product Variant Attribute'!$D$2:$D$2000,'Product Variant Attribute'!$F$2:$F$2000,""),_xlfn.XLOOKUP(B15&"|ATTR-24",'Product Variant Attribute'!$A$2:$A$2000&"|"&'Product Variant Attribute'!$D$2:$D$2000,'Product Variant Attribute'!$F$2:$F$2000,""))} | F15: Bộ | G15: 1 bộ | H15: =IFERROR(--LEFT(G15,FIND(" ",G15&" ")-1),"") -> 1 | I15: =_xlfn.XLOOKUP(C15,Product!$A:$A,Product!$G:$G,"NOT FOUND") -> bộ | K15: Liên hệ – merinco.com.vn không công bố giá | L15: 239 | M15: Bộ gạc xốp phủ vết thương trong điều trị áp lực âm VAC kèm chức năng rửa 3M™ Veraflo™ | N15: 92 | O15: ="INSERT INTO public.medical_supply_sellable_unit (code, price, quantity, sale_uom, product_variant_code) VALUES ('"&A15&"', "&IF(J15="","NULL",J15)&", "&IF(H15="","NULL",H15)&", "&IF(F15="","NULL","'"&SUBSTITUTE(F15,"'","''")&"'")&", '"&B15&"');" -> INSERT INTO public.medical_supply_sellable_unit (code, price, quantity, sale_uom, product_variant_code) VALUES ('PRODUCT-00011-001-01', NULL, 1, 'Bộ', 'PRODUCT-00011-001');
A16: =B16&"-"&TEXT(COUNTIF(B$2:B16,B16),"00") -> PRODUCT-00012-001-01 | B16: PRODUCT-00012-001 | C16: =_xlfn.XLOOKUP(B16,'Product Variant'!$A:$A,'Product Variant'!$B:$B,"NOT FOUND") -> PRODUCT-00012 | D16: =_xlfn.XLOOKUP(B16,'Product Variant'!$A:$A,'Product Variant'!$C:$C,"NOT FOUND") -> [3M™] Miếng dán vết thương thay chỉ khâu - STERI-STRIP™ (3mmx75mm) | E16: {=_xlfn.TEXTJOIN(" / ",TRUE,_xlfn.XLOOKUP(B16&"|ATTR-27",'Product Variant Attribute'!$A$2:$A$2000&"|"&'Product Variant Attribute'!$D$2:$D$2000,'Product Variant Attribute'!$F$2:$F$2000,""),_xlfn.XLOOKUP(B16&"|ATTR-24",'Product Variant Attribute'!$A$2:$A$2000&"|"&'Product Variant Attribute'!$D$2:$D$2000,'Product Variant Attribute'!$F$2:$F$2000,""))} | F16: Túi | G16: 5 sợi | H16: =IFERROR(--LEFT(G16,FIND(" ",G16&" ")-1),"") -> 5 | I16: =_xlfn.XLOOKUP(C16,Product!$A:$A,Product!$G:$G,"NOT FOUND") -> sợi | J16: 27000 | K16: Giá (theo biến thể) – nguồn có nhiều giá: 27,000 / 22,000 | L16: 122, 444 | M16: Miếng dán vết thương thay chỉ khâu phẫu thuật 3M STERI-STRIP™ | N16: 356, 367 | O16: ="INSERT INTO public.medical_supply_sellable_unit (code, price, quantity, sale_uom, product_variant_code) VALUES ('"&A16&"', "&IF(J16="","NULL",J16)&", "&IF(H16="","NULL",H16)&", "&IF(F16="","NULL","'"&SUBSTITUTE(F16,"'","''")&"'")&", '"&B16&"');" -> INSERT INTO public.medical_supply_sellable_unit (code, price, quantity, sale_uom, product_variant_code) VALUES ('PRODUCT-00012-001-01', 27000, 5, 'Túi', 'PRODUCT-00012-001');
A17: =B17&"-"&TEXT(COUNTIF(B$2:B17,B17),"00") -> PRODUCT-00252-001-01 | B17: PRODUCT-00252-001 | C17: =_xlfn.XLOOKUP(B17,'Product Variant'!$A:$A,'Product Variant'!$B:$B,"NOT FOUND") -> PRODUCT-00252 | D17: =_xlfn.XLOOKUP(B17,'Product Variant'!$A:$A,'Product Variant'!$C:$C,"NOT FOUND") -> [3M™] Miếng dán vết thương thay chỉ khâu - STERI-STRIP™ (6mmx100mm) | E17: {=_xlfn.TEXTJOIN(" / ",TRUE,_xlfn.XLOOKUP(B17&"|ATTR-27",'Product Variant Attribute'!$A$2:$A$2000&"|"&'Product Variant Attribute'!$D$2:$D$2000,'Product Variant Attribute'!$F$2:$F$2000,""),_xlfn.XLOOKUP(B17&"|ATTR-24",'Product Variant Attribute'!$A$2:$A$2000&"|"&'Product Variant Attribute'!$D$2:$D$2000,'Product Variant Attribute'!$F$2:$F$2000,""))} | F17: Túi | G17: 10 sợi | H17: =IFERROR(--LEFT(G17,FIND(" ",G17&" ")-1),"") -> 10 | I17: =_xlfn.XLOOKUP(C17,Product!$A:$A,Product!$G:$G,"NOT FOUND") -> sợi | J17: 30000 | K17: Giá (theo biến thể) – nguồn có nhiều giá: 30,000 / 27,000 | L17: 123, 445 | M17: Miếng dán vết thương thay chỉ khâu phẫu thuật 3M STERI-STRIP™ | N17: 357, 369 | O17: ="INSERT INTO public.medical_supply_sellable_unit (code, price, quantity, sale_uom, product_variant_code) VALUES ('"&A17&"', "&IF(J17="","NULL",J17)&", "&IF(H17="","NULL",H17)&", "&IF(F17="","NULL","'"&SUBSTITUTE(F17,"'","''")&"'")&", '"&B17&"');" -> INSERT INTO public.medical_supply_sellable_unit (code, price, quantity, sale_uom, product_variant_code) VALUES ('PRODUCT-00252-001-01', 30000, 10, 'Túi', 'PRODUCT-00252-001');
A18: =B18&"-"&TEXT(COUNTIF(B$2:B18,B18),"00") -> PRODUCT-00253-001-01 | B18: PRODUCT-00253-001 | C18: =_xlfn.XLOOKUP(B18,'Product Variant'!$A:$A,'Product Variant'!$B:$B,"NOT FOUND") -> PRODUCT-00253 | D18: =_xlfn.XLOOKUP(B18,'Product Variant'!$A:$A,'Product Variant'!$C:$C,"NOT FOUND") -> [3M™] Miếng dán vết thương thay chỉ khâu - STERI-STRIP™ (12mmx100mm) | E18: {=_xlfn.TEXTJOIN(" / ",TRUE,_xlfn.XLOOKUP(B18&"|ATTR-27",'Product Variant Attribute'!$A$2:$A$2000&"|"&'Product Variant Attribute'!$D$2:$D$2000,'Product Variant Attribute'!$F$2:$F$2000,""),_xlfn.XLOOKUP(B18&"|ATTR-24",'Product Variant Attribute'!$A$2:$A$2000&"|"&'Product Variant Attribute'!$D$2:$D$2000,'Product Variant Attribute'!$F$2:$F$2000,""))} | F18: Túi | G18: 6 sợi | H18: =IFERROR(--LEFT(G18,FIND(" ",G18&" ")-1),"") -> 6 | I18: =_xlfn.XLOOKUP(C18,Product!$A:$A,Product!$G:$G,"NOT FOUND") -> sợi | J18: 38000 | K18: Giá (theo biến thể) – nguồn có nhiều giá: 38,000 / 30,000 | L18: 124, 418 | M18: Miếng dán vết thương thay chỉ khâu phẫu thuật 3M STERI-STRIP™ | N18: 358, 368 | O18: ="INSERT INTO public.medical_supply_sellable_unit (code, price, quantity, sale_uom, product_variant_code) VALUES ('"&A18&"', "&IF(J18="","NULL",J18)&", "&IF(H18="","NULL",H18)&", "&IF(F18="","NULL","'"&SUBSTITUTE(F18,"'","''")&"'")&", '"&B18&"');" -> INSERT INTO public.medical_supply_sellable_unit (code, price, quantity, sale_uom, product_variant_code) VALUES ('PRODUCT-00253-001-01', 38000, 6, 'Túi', 'PRODUCT-00253-001');
A19: =B19&"-"&TEXT(COUNTIF(B$2:B19,B19),"00") -> PRODUCT-00013-001-01 | B19: PRODUCT-00013-001 | C19: =_xlfn.XLOOKUP(B19,'Product Variant'!$A:$A,'Product Variant'!$B:$B,"NOT FOUND") -> PRODUCT-00013 | D19: =_xlfn.XLOOKUP(B19,'Product Variant'!$A:$A,'Product Variant'!$C:$C,"NOT FOUND") -> [3M™] Xịt bảo vệ chống hăm loét da - Cavilon (28ml) | E19: {=_xlfn.TEXTJOIN(" / ",TRUE,_xlfn.XLOOKUP(B19&"|ATTR-27",'Product Variant Attribute'!$A$2:$A$2000&"|"&'Product Variant Attribute'!$D$2:$D$2000,'Product Variant Attribute'!$F$2:$F$2000,""),_xlfn.XLOOKUP(B19&"|ATTR-24",'Product Variant Attribute'!$A$2:$A$2000&"|"&'Product Variant Attribute'!$D$2:$D$2000,'Product Variant Attribute'!$F$2:$F$2000,""))} | F19: Hộp | G19: 1 chai 28ml | H19: 1 | I19: =_xlfn.XLOOKUP(C19,Product!$A:$A,Product!$G:$G,"NOT FOUND") -> chai | J19: 240000 | K19: Giá sản phẩm (chung) – khớp theo tên | L19: 195 | M19: Xịt bảo vệ và hỗ trợ điều trị hăm loét da 3M Cavilon 28ml chống loét, giảm hăm da | N19: 551 | O19: ="INSERT INTO public.medical_supply_sellable_unit (code, price, quantity, sale_uom, product_variant_code) VALUES ('"&A19&"', "&IF(J19="","NULL",J19)&", "&IF(H19="","NULL",H19)&", "&IF(F19="","NULL","'"&SUBSTITUTE(F19,"'","''")&"'")&", '"&B19&"');" -> INSERT INTO public.medical_supply_sellable_unit (code, price, quantity, sale_uom, product_variant_code) VALUES ('PRODUCT-00013-001-01', 240000, 1, 'Hộp', 'PRODUCT-00013-001');
A20: =B20&"-"&TEXT(COUNTIF(B$2:B20,B20),"00") -> PRODUCT-00014-001-01 | B20: PRODUCT-00014-001 | C20: =_xlfn.XLOOKUP(B20,'Product Variant'!$A:$A,'Product Variant'!$B:$B,"NOT FOUND") -> PRODUCT-00014 | D20: =_xlfn.XLOOKUP(B20,'Product Variant'!$A:$A,'Product Variant'!$C:$C,"NOT FOUND") -> [ConvaTec] Băng dán vết thương - DuoDerm Extra Thin (10cmx10cm) | E20: {=_xlfn.TEXTJOIN(" / ",TRUE,_xlfn.XLOOKUP(B20&"|ATTR-27",'Product Variant Attribute'!$A$2:$A$2000&"|"&'Product Variant Attribute'!$D$2:$D$2000,'Product Variant Attribute'!$F$2:$F$2000,""),_xlfn.XLOOKUP(B20&"|ATTR-24",'Product Variant Attribute'!$A$2:$A$2000&"|"&'Product Variant Attribute'!$D$2:$D$2000,'Product Variant Attribute'!$F$2:$F$2000,""))} | F20: Túi | G20: 1 miếng | H20: =IFERROR(--LEFT(G20,FIND(" ",G20&" ")-1),"") -> 1 | I20: =_xlfn.XLOOKUP(C20,Product!$A:$A,Product!$G:$G,"NOT FOUND") -> miếng | J20: 69000 | K20: Giá (theo biến thể) | L20: 118 | M20: Băng dán vết thương DuoDerm Extra Thin | N20: 2 | O20: ="INSERT INTO public.medical_supply_sellable_unit (code, price, quantity, sale_uom, product_variant_code) VALUES ('"&A20&"', "&IF(J20="","NULL",J20)&", "&IF(H20="","NULL",H20)&", "&IF(F20="","NULL","'"&SUBSTITUTE(F20,"'","''")&"'")&", '"&B20&"');" -> INSERT INTO public.medical_supply_sellable_unit (code, price, quantity, sale_uom, product_variant_code) VALUES ('PRODUCT-00014-001-01', 69000, 1, 'Túi', 'PRODUCT-00014-001');
A21: =B21&"-"&TEXT(COUNTIF(B$2:B21,B21),"00") -> PRODUCT-00254-001-01 | B21: PRODUCT-00254-001 | C21: =_xlfn.XLOOKUP(B21,'Product Variant'!$A:$A,'Product Variant'!$B:$B,"NOT FOUND") -> PRODUCT-00254 | D21: =_xlfn.XLOOKUP(B21,'Product Variant'!$A:$A,'Product Variant'!$C:$C,"NOT FOUND") -> [ConvaTec] Băng dán vết thương - DuoDerm Extra Thin (5cmx20cm) | E21: {=_xlfn.TEXTJOIN(" / ",TRUE,_xlfn.XLOOKUP(B21&"|ATTR-27",'Product Variant Attribute'!$A$2:$A$2000&"|"&'Product Variant Attribute'!$D$2:$D$2000,'Product Variant Attribute'!$F$2:$F$2000,""),_xlfn.XLOOKUP(B21&"|ATTR-24",'Product Variant Attribute'!$A$2:$A$2000&"|"&'Product Variant Attribute'!$D$2:$D$2000,'Product Variant Attribute'!$F$2:$F$2000,""))} | F21: Túi | G21: 1 miếng | H21: =IFERROR(--LEFT(G21,FIND(" ",G21&" ")-1),"") -> 1 | I21: =_xlfn.XLOOKUP(C21,Product!$A:$A,Product!$G:$G,"NOT FOUND") -> miếng | J21: 83000 | K21: Giá (theo biến thể) | L21: 119 | M21: Băng dán vết thương DuoDerm Extra Thin | N21: 3 | O21: ="INSERT INTO public.medical_supply_sellable_unit (code, price, quantity, sale_uom, product_variant_code) VALUES ('"&A21&"', "&IF(J21="","NULL",J21)&", "&IF(H21="","NULL",H21)&", "&IF(F21="","NULL","'"&SUBSTITUTE(F21,"'","''")&"'")&", '"&B21&"');" -> INSERT INTO public.medical_supply_sellable_unit (code, price, quantity, sale_uom, product_variant_code) VALUES ('PRODUCT-00254-001-01', 83000, 1, 'Túi', 'PRODUCT-00254-001');
A22: =B22&"-"&TEXT(COUNTIF(B$2:B22,B22),"00") -> PRODUCT-00255-001-01 | B22: PRODUCT-00255-001 | C22: =_xlfn.XLOOKUP(B22,'Product Variant'!$A:$A,'Product Variant'!$B:$B,"NOT FOUND") -> PRODUCT-00255 | D22: =_xlfn.XLOOKUP(B22,'Product Variant'!$A:$A,'Product Variant'!$C:$C,"NOT FOUND") -> [ConvaTec] Băng dán vết thương - DuoDerm Extra Thin (5cmx10cm) | E22: {=_xlfn.TEXTJOIN(" / ",TRUE,_xlfn.XLOOKUP(B22&"|ATTR-27",'Product Variant Attribute'!$A$2:$A$2000&"|"&'Product Variant Attribute'!$D$2:$D$2000,'Product Variant Attribute'!$F$2:$F$2000,""),_xlfn.XLOOKUP(B22&"|ATTR-24",'Product Variant Attribute'!$A$2:$A$2000&"|"&'Product Variant Attribute'!$D$2:$D$2000,'Product Variant Attribute'!$F$2:$F$2000,""))} | F22: Túi | G22: 1 miếng | H22: =IFERROR(--LEFT(G22,FIND(" ",G22&" ")-1),"") -> 1 | I22: =_xlfn.XLOOKUP(C22,Product!$A:$A,Product!$G:$G,"NOT FOUND") -> miếng | J22: 50000 | K22: Giá (theo biến thể) | L22: 120 | M22: Băng dán vết thương DuoDerm Extra Thin | N22: 4 | O22: ="INSERT INTO public.medical_supply_sellable_unit (code, price, quantity, sale_uom, product_variant_code) VALUES ('"&A22&"', "&IF(J22="","NULL",J22)&", "&IF(H22="","NULL",H22)&", "&IF(F22="","NULL","'"&SUBSTITUTE(F22,"'","''")&"'")&", '"&B22&"');" -> INSERT INTO public.medical_supply_sellable_unit (code, price, quantity, sale_uom, product_variant_code) VALUES ('PRODUCT-00255-001-01', 50000, 1, 'Túi', 'PRODUCT-00255-001');
A23: =B23&"-"&TEXT(COUNTIF(B$2:B23,B23),"00") -> PRODUCT-00015-001-01 | B23: PRODUCT-00015-001 | C23: =_xlfn.XLOOKUP(B23,'Product Variant'!$A:$A,'Product Variant'!$B:$B,"NOT FOUND") -> PRODUCT-00015 | D23: =_xlfn.XLOOKUP(B23,'Product Variant'!$A:$A,'Product Variant'!$C:$C,"NOT FOUND") -> [Dr.Muller Pharma] Gel bôi vết thương hở - Okuskin (10g) | E23: {=_xlfn.TEXTJOIN(" / ",TRUE,_xlfn.XLOOKUP(B23&"|ATTR-27",'Product Variant Attribute'!$A$2:$A$2000&"|"&'Product Variant Attribute'!$D$2:$D$2000,'Product Variant Attribute'!$F$2:$F$2000,""),_xlfn.XLOOKUP(B23&"|ATTR-24",'Product Variant Attribute'!$A$2:$A$2000&"|"&'Product Variant Attribute'!$D$2:$D$2000,'Product Variant Attribute'!$F$2:$F$2000,""))} | F23: Hộp | G23: 1 tuýp 10g | H23: =IFERROR(--LEFT(G23,FIND(" ",G23&" ")-1),"") -> 1 | I23: =_xlfn.XLOOKUP(C23,Product!$A:$A,Product!$G:$G,"NOT FOUND") -> tuýp | J23: 180000 | K23: Giá sản phẩm (chung) – khớp theo tên | L23: 154 | M23: Gel bôi vết thương hở Okuskin 10g hỗ trợ nhanh lành vết thương, hạn chế sẹo xấu | N23: 260 | O23: ="INSERT INTO public.medical_supply_sellable_unit (code, price, quantity, sale_uom, product_variant_code) VALUES ('"&A23&"', "&IF(J23="","NULL",J23)&", "&IF(H23="","NULL",H23)&", "&IF(F23="","NULL","'"&SUBSTITUTE(F23,"'","''")&"'")&", '"&B23&"');" -> INSERT INTO public.medical_supply_sellable_unit (code, price, quantity, sale_uom, product_variant_code) VALUES ('PRODUCT-00015-001-01', 180000, 1, 'Hộp', 'PRODUCT-00015-001');
A24: =B24&"-"&TEXT(COUNTIF(B$2:B24,B24),"00") -> PRODUCT-00256-001-01 | B24: PRODUCT-00256-001 | C24: =_xlfn.XLOOKUP(B24,'Product Variant'!$A:$A,'Product Variant'!$B:$B,"NOT FOUND") -> PRODUCT-00256 | D24: =_xlfn.XLOOKUP(B24,'Product Variant'!$A:$A,'Product Variant'!$C:$C,"NOT FOUND") -> [Dr.Muller Pharma] Gel bôi vết thương hở - Okuskin (30g) | E24: {=_xlfn.TEXTJOIN(" / ",TRUE,_xlfn.XLOOKUP(B24&"|ATTR-27",'Product Variant Attribute'!$A$2:$A$2000&"|"&'Product Variant Attribute'!$D$2:$D$2000,'Product Variant Attribute'!$F$2:$F$2000,""),_xlfn.XLOOKUP(B24&"|ATTR-24",'Product Variant Attribute'!$A$2:$A$2000&"|"&'Product Variant Attribute'!$D$2:$D$2000,'Product Variant Attribute'!$F$2:$F$2000,""))} | F24: Hộp | G24: 1 tuýp 30g | H24: =IFERROR(--LEFT(G24,FIND(" ",G24&" ")-1),"") -> 1 | I24: =_xlfn.XLOOKUP(C24,Product!$A:$A,Product!$G:$G,"NOT FOUND") -> tuýp | J24: 380000 | K24: Giá sản phẩm (chung) – khớp theo tên | L24: 167 | M24: Gel bôi vết thương hở Okuskin 30g hỗ trợ nhanh lành vết thương, hạn chế sẹo xấu | N24: 261 | O24: ="INSERT INTO public.medical_supply_sellable_unit (code, price, quantity, sale_uom, product_variant_code) VALUES ('"&A24&"', "&IF(J24="","NULL",J24)&", "&IF(H24="","NULL",H24)&", "&IF(F24="","NULL","'"&SUBSTITUTE(F24,"'","''")&"'")&", '"&B24&"');" -> INSERT INTO public.medical_supply_sellable_unit (code, price, quantity, sale_uom, product_variant_code) VALUES ('PRODUCT-00256-001-01', 380000, 1, 'Hộp', 'PRODUCT-00256-001');
A25: =B25&"-"&TEXT(COUNTIF(B$2:B25,B25),"00") -> PRODUCT-00016-001-01 | B25: PRODUCT-00016-001 | C25: =_xlfn.XLOOKUP(B25,'Product Variant'!$A:$A,'Product Variant'!$B:$B,"NOT FOUND") -> PRODUCT-00016 | D25: =_xlfn.XLOOKUP(B25,'Product Variant'!$A:$A,'Product Variant'!$C:$C,"NOT FOUND") -> [ICM] Dung dịch sát khuẩn rửa vết thương - Berbemed (150ml) | E25: {=_xlfn.TEXTJOIN(" / ",TRUE,_xlfn.XLOOKUP(B25&"|ATTR-27",'Product Variant Attribute'!$A$2:$A$2000&"|"&'Product Variant Attribute'!$D$2:$D$2000,'Product Variant Attribute'!$F$2:$F$2000,""),_xlfn.XLOOKUP(B25&"|ATTR-24",'Product Variant Attribute'!$A$2:$A$2000&"|"&'Product Variant Attribute'!$D$2:$D$2000,'Product Variant Attribute'!$F$2:$F$2000,""))} | F25: Hộp | G25: 1 chai | H25: =IFERROR(--LEFT(G25,FIND(" ",G25&" ")-1),"") -> 1 | I25: =_xlfn.XLOOKUP(C25,Product!$A:$A,Product!$G:$G,"NOT FOUND") -> chai | J25: 120000 | K25: Giá sản phẩm (chung) – khớp theo tên | L25: 166 | M25: Dung dịch sát khuẩn vết thương Berbemed rửa vết thương, làm sạch vi khuẩn 150ml | N25: 225 | O25: ="INSERT INTO public.medical_supply_sellable_unit (code, price, quantity, sale_uom, product_variant_code) VALUES ('"&A25&"', "&IF(J25="","NULL",J25)&", "&IF(H25="","NULL",H25)&", "&IF(F25="","NULL","'"&SUBSTITUTE(F25,"'","''")&"'")&", '"&B25&"');" -> INSERT INTO public.medical_supply_sellable_unit (code, price, quantity, sale_uom, product_variant_code) VALUES ('PRODUCT-00016-001-01', 120000, 1, 'Hộp', 'PRODUCT-00016-001');
A26: =B26&"-"&TEXT(COUNTIF(B$2:B26,B26),"00") -> PRODUCT-00017-001-01 | B26: PRODUCT-00017-001 | C26: =_xlfn.XLOOKUP(B26,'Product Variant'!$A:$A,'Product Variant'!$B:$B,"NOT FOUND") -> PRODUCT-00017 | D26: =_xlfn.XLOOKUP(B26,'Product Variant'!$A:$A,'Product Variant'!$C:$C,"NOT FOUND") -> [Mepro] Bông tẩm cồn sát trùng - Alcohol Swab | E26: {=_xlfn.TEXTJOIN(" / ",TRUE,_xlfn.XLOOKUP(B26&"|ATTR-27",'Product Variant Attribute'!$A$2:$A$2000&"|"&'Product Variant Attribute'!$D$2:$D$2000,'Product Variant Attribute'!$F$2:$F$2000,""),_xlfn.XLOOKUP(B26&"|ATTR-24",'Product Variant Attribute'!$A$2:$A$2000&"|"&'Product Variant Attribute'!$D$2:$D$2000,'Product Variant Attribute'!$F$2:$F$2000,""))} | F26: Hộp | G26: 100 miếng | H26: =IFERROR(--LEFT(G26,FIND(" ",G26&" ")-1),"") -> 100 | I26: =_xlfn.XLOOKUP(C26,Product!$A:$A,Product!$G:$G,"NOT FOUND") -> miếng | J26: 16000 | K26: Giá sản phẩm (chung) – khớp theo tên | L26: 346 | M26: Bông tẩm cồn Mepro Alcohol Swab sát trùng, giảm nhiễm khuẩn huyết | N26: 125 | O26: ="INSERT INTO public.medical_supply_sellable_unit (code, price, quantity, sale_uom, product_variant_code) VALUES ('"&A26&"', "&IF(J26="","NULL",J26)&", "&IF(H26="","NULL",H26)&", "&IF(F26="","NULL","'"&SUBSTITUTE(F26,"'","''")&"'")&", '"&B26&"');" -> INSERT INTO public.medical_supply_sellable_unit (code, price, quantity, sale_uom, product_variant_code) VALUES ('PRODUCT-00017-001-01', 16000, 100, 'Hộp', 'PRODUCT-00017-001');
A27: =B27&"-"&TEXT(COUNTIF(B$2:B27,B27),"00") -> PRODUCT-00018-001-01 | B27: PRODUCT-00018-001 | C27: =_xlfn.XLOOKUP(B27,'Product Variant'!$A:$A,'Product Variant'!$B:$B,"NOT FOUND") -> PRODUCT-00018 | D27: =_xlfn.XLOOKUP(B27,'Product Variant'!$A:$A,'Product Variant'!$C:$C,"NOT FOUND") -> [SeaSight] Gạc xốp hút dịch chống loét có viền dính silicone (18.5cmx24cm) | E27: {=_xlfn.TEXTJOIN(" / ",TRUE,_xlfn.XLOOKUP(B27&"|ATTR-27",'Product Variant Attribute'!$A$2:$A$2000&"|"&'Product Variant Attribute'!$D$2:$D$2000,'Product Variant Attribute'!$F$2:$F$2000,""),_xlfn.XLOOKUP(B27&"|ATTR-24",'Product Variant Attribute'!$A$2:$A$2000&"|"&'Product Variant Attribute'!$D$2:$D$2000,'Product Variant Attribute'!$F$2:$F$2000,""))} | F27: Túi | G27: 1 miếng | H27: =IFERROR(--LEFT(G27,FIND(" ",G27&" ")-1),"") -> 1 | I27: =_xlfn.XLOOKUP(C27,Product!$A:$A,Product!$G:$G,"NOT FOUND") -> miếng | J27: 150000 | K27: Giá sản phẩm (chung) – khớp theo tên | L27: 153 | M27: Gạc xốp hút dịch chống loét mông, loét gót chân có viền dính silicone Seasight | N27: 235 | O27: ="INSERT INTO public.medical_supply_sellable_unit (code, price, quantity, sale_uom, product_variant_code) VALUES ('"&A27&"', "&IF(J27="","NULL",J27)&", "&IF(H27="","NULL",H27)&", "&IF(F27="","NULL","'"&SUBSTITUTE(F27,"'","''")&"'")&", '"&B27&"');" -> INSERT INTO public.medical_supply_sellable_unit (code, price, quantity, sale_uom, product_variant_code) VALUES ('PRODUCT-00018-001-01', 150000, 1, 'Túi', 'PRODUCT-00018-001');
A28: =B28&"-"&TEXT(COUNTIF(B$2:B28,B28),"00") -> PRODUCT-00019-001-01 | B28: PRODUCT-00019-001 | C28: =_xlfn.XLOOKUP(B28,'Product Variant'!$A:$A,'Product Variant'!$B:$B,"NOT FOUND") -> PRODUCT-00019 | D28: =_xlfn.XLOOKUP(B28,'Product Variant'!$A:$A,'Product Variant'!$C:$C,"NOT FOUND") -> [SeaSight] Miếng dán vết thương thay chỉ khâu (3mmx75mm) | E28: {=_xlfn.TEXTJOIN(" / ",TRUE,_xlfn.XLOOKUP(B28&"|ATTR-27",'Product Variant Attribute'!$A$2:$A$2000&"|"&'Product Variant Attribute'!$D$2:$D$2000,'Product Variant Attribute'!$F$2:$F$2000,""),_xlfn.XLOOKUP(B28&"|ATTR-24",'Product Variant Attribute'!$A$2:$A$2000&"|"&'Product Variant Attribute'!$D$2:$D$2000,'Product Variant Attribute'!$F$2:$F$2000,""))} | F28: Túi | G28: 5 sợi | H28: =IFERROR(--LEFT(G28,FIND(" ",G28&" ")-1),"") -> 5 | I28: =_xlfn.XLOOKUP(C28,Product!$A:$A,Product!$G:$G,"NOT FOUND") -> sợi | J28: 20000 | K28: Giá (theo biến thể) | L28: 125, 258 | M28: Miếng dán vết thương thay chỉ khâu Seasight tránh giãn sẹo | N28: 359, 364 | O28: ="INSERT INTO public.medical_supply_sellable_unit (code, price, quantity, sale_uom, product_variant_code) VALUES ('"&A28&"', "&IF(J28="","NULL",J28)&", "&IF(H28="","NULL",H28)&", "&IF(F28="","NULL","'"&SUBSTITUTE(F28,"'","''")&"'")&", '"&B28&"');" -> INSERT INTO public.medical_supply_sellable_unit (code, price, quantity, sale_uom, product_variant_code) VALUES ('PRODUCT-00019-001-01', 20000, 5, 'Túi', 'PRODUCT-00019-001');
A29: =B29&"-"&TEXT(COUNTIF(B$2:B29,B29),"00") -> PRODUCT-00257-001-01 | B29: PRODUCT-00257-001 | C29: =_xlfn.XLOOKUP(B29,'Product Variant'!$A:$A,'Product Variant'!$B:$B,"NOT FOUND") -> PRODUCT-00257 | D29: =_xlfn.XLOOKUP(B29,'Product Variant'!$A:$A,'Product Variant'!$C:$C,"NOT FOUND") -> [SeaSight] Miếng dán vết thương thay chỉ khâu (6mmx38mm) | E29: {=_xlfn.TEXTJOIN(" / ",TRUE,_xlfn.XLOOKUP(B29&"|ATTR-27",'Product Variant Attribute'!$A$2:$A$2000&"|"&'Product Variant Attribute'!$D$2:$D$2000,'Product Variant Attribute'!$F$2:$F$2000,""),_xlfn.XLOOKUP(B29&"|ATTR-24",'Product Variant Attribute'!$A$2:$A$2000&"|"&'Product Variant Attribute'!$D$2:$D$2000,'Product Variant Attribute'!$F$2:$F$2000,""))} | F29: Túi | G29: 6 sợi | H29: =IFERROR(--LEFT(G29,FIND(" ",G29&" ")-1),"") -> 6 | I29: =_xlfn.XLOOKUP(C29,Product!$A:$A,Product!$G:$G,"NOT FOUND") -> sợi | J29: 20000 | K29: Giá (theo biến thể) | L29: 121, 126 | M29: Miếng dán vết thương thay chỉ khâu Seasight tránh giãn sẹo | N29: 360, 366 | O29: ="INSERT INTO public.medical_supply_sellable_unit (code, price, quantity, sale_uom, product_variant_code) VALUES ('"&A29&"', "&IF(J29="","NULL",J29)&", "&IF(H29="","NULL",H29)&", "&IF(F29="","NULL","'"&SUBSTITUTE(F29,"'","''")&"'")&", '"&B29&"');" -> INSERT INTO public.medical_supply_sellable_unit (code, price, quantity, sale_uom, product_variant_code) VALUES ('PRODUCT-00257-001-01', 20000, 6, 'Túi', 'PRODUCT-00257-001');
A30: =B30&"-"&TEXT(COUNTIF(B$2:B30,B30),"00") -> PRODUCT-00258-001-01 | B30: PRODUCT-00258-001 | C30: =_xlfn.XLOOKUP(B30,'Product Variant'!$A:$A,'Product Variant'!$B:$B,"NOT FOUND") -> PRODUCT-00258 | D30: =_xlfn.XLOOKUP(B30,'Product Variant'!$A:$A,'Product Variant'!$C:$C,"NOT FOUND") -> [SeaSight] Miếng dán vết thương thay chỉ khâu (6mmx100mm) | E30: {=_xlfn.TEXTJOIN(" / ",TRUE,_xlfn.XLOOKUP(B30&"|ATTR-27",'Product Variant Attribute'!$A$2:$A$2000&"|"&'Product Variant Attribute'!$D$2:$D$2000,'Product Variant Attribute'!$F$2:$F$2000,""),_xlfn.XLOOKUP(B30&"|ATTR-24",'Product Variant Attribute'!$A$2:$A$2000&"|"&'Product Variant Attribute'!$D$2:$D$2000,'Product Variant Attribute'!$F$2:$F$2000,""))} | F30: Túi | G30: 5 sợi | H30: =IFERROR(--LEFT(G30,FIND(" ",G30&" ")-1),"") -> 5 | I30: =_xlfn.XLOOKUP(C30,Product!$A:$A,Product!$G:$G,"NOT FOUND") -> sợi | J30: 25000 | K30: Giá (theo biến thể) | L30: 127, 129 | M30: Miếng dán vết thương thay chỉ khâu Seasight tránh giãn sẹo | N30: 361, 365 | O30: ="INSERT INTO public.medical_supply_sellable_unit (code, price, quantity, sale_uom, product_variant_code) VALUES ('"&A30&"', "&IF(J30="","NULL",J30)&", "&IF(H30="","NULL",H30)&", "&IF(F30="","NULL","'"&SUBSTITUTE(F30,"'","''")&"'")&", '"&B30&"');" -> INSERT INTO public.medical_supply_sellable_unit (code, price, quantity, sale_uom, product_variant_code) VALUES ('PRODUCT-00258-001-01', 25000, 5, 'Túi', 'PRODUCT-00258-001');
A31: =B31&"-"&TEXT(COUNTIF(B$2:B31,B31),"00") -> PRODUCT-00259-001-01 | B31: PRODUCT-00259-001 | C31: =_xlfn.XLOOKUP(B31,'Product Variant'!$A:$A,'Product Variant'!$B:$B,"NOT FOUND") -> PRODUCT-00259 | D31: =_xlfn.XLOOKUP(B31,'Product Variant'!$A:$A,'Product Variant'!$C:$C,"NOT FOUND") -> [SeaSight] Miếng dán vết thương thay chỉ khâu (12mmx100mm) | E31: {=_xlfn.TEXTJOIN(" / ",TRUE,_xlfn.XLOOKUP(B31&"|ATTR-27",'Product Variant Attribute'!$A$2:$A$2000&"|"&'Product Variant Attribute'!$D$2:$D$2000,'Product Variant Attribute'!$F$2:$F$2000,""),_xlfn.XLOOKUP(B31&"|ATTR-24",'Product Variant Attribute'!$A$2:$A$2000&"|"&'Product Variant Attribute'!$D$2:$D$2000,'Product Variant Attribute'!$F$2:$F$2000,""))} | F31: Túi | G31: 3 sợi | H31: =IFERROR(--LEFT(G31,FIND(" ",G31&" ")-1),"") -> 3 | I31: =_xlfn.XLOOKUP(C31,Product!$A:$A,Product!$G:$G,"NOT FOUND") -> sợi | J31: 27000 | K31: Giá (theo biến thể) | L31: 128, 257 | M31: Miếng dán vết thương thay chỉ khâu Seasight tránh giãn sẹo | N31: 362, 363 | O31: ="INSERT INTO public.medical_supply_sellable_unit (code, price, quantity, sale_uom, product_variant_code) VALUES ('"&A31&"', "&IF(J31="","NULL",J31)&", "&IF(H31="","NULL",H31)&", "&IF(F31="","NULL","'"&SUBSTITUTE(F31,"'","''")&"'")&", '"&B31&"');" -> INSERT INTO public.medical_supply_sellable_unit (code, price, quantity, sale_uom, product_variant_code) VALUES ('PRODUCT-00259-001-01', 27000, 3, 'Túi', 'PRODUCT-00259-001');
A32: =B32&"-"&TEXT(COUNTIF(B$2:B32,B32),"00") -> PRODUCT-00020-001-01 | B32: PRODUCT-00020-001 | C32: =_xlfn.XLOOKUP(B32,'Product Variant'!$A:$A,'Product Variant'!$B:$B,"NOT FOUND") -> PRODUCT-00020 | D32: =_xlfn.XLOOKUP(B32,'Product Variant'!$A:$A,'Product Variant'!$C:$C,"NOT FOUND") -> [Tanaphar] Bông tẩm cồn tiệt trùng - Alcohol Swab | E32: {=_xlfn.TEXTJOIN(" / ",TRUE,_xlfn.XLOOKUP(B32&"|ATTR-27",'Product Variant Attribute'!$A$2:$A$2000&"|"&'Product Variant Attribute'!$D$2:$D$2000,'Product Variant Attribute'!$F$2:$F$2000,""),_xlfn.XLOOKUP(B32&"|ATTR-24",'Product Variant Attribute'!$A$2:$A$2000&"|"&'Product Variant Attribute'!$D$2:$D$2000,'Product Variant Attribute'!$F$2:$F$2000,""))} | F32: Hộp | G32: 100 miếng | H32: =IFERROR(--LEFT(G32,FIND(" ",G32&" ")-1),"") -> 100 | I32: =_xlfn.XLOOKUP(C32,Product!$A:$A,Product!$G:$G,"NOT FOUND") -> miếng | J32: 20000 | K32: Giá sản phẩm (chung) – khớp theo tên | L32: 345 | M32: Bông tẩm cồn Tanaphar Alcohol Swab tiệt trùng giảm nhiễm khuẩn huyết | N32: 126 | O32: ="INSERT INTO public.medical_supply_sellable_unit (code, price, quantity, sale_uom, product_variant_code) VALUES ('"&A32&"', "&IF(J32="","NULL",J32)&", "&IF(H32="","NULL",H32)&", "&IF(F32="","NULL","'"&SUBSTITUTE(F32,"'","''")&"'")&", '"&B32&"');" -> INSERT INTO public.medical_supply_sellable_unit (code, price, quantity, sale_uom, product_variant_code) VALUES ('PRODUCT-00020-001-01', 20000, 100, 'Hộp', 'PRODUCT-00020-001');
A33: =B33&"-"&TEXT(COUNTIF(B$2:B33,B33),"00") -> PRODUCT-00021-001-01 | B33: PRODUCT-00021-001 | C33: =_xlfn.XLOOKUP(B33,'Product Variant'!$A:$A,'Product Variant'!$B:$B,"NOT FOUND") -> PRODUCT-00021 | D33: =_xlfn.XLOOKUP(B33,'Product Variant'!$A:$A,'Product Variant'!$C:$C,"NOT FOUND") -> [Terrapharm] Dung dịch kháng khuẩn rửa vết thương - Dizigone (300ml) | E33: {=_xlfn.TEXTJOIN(" / ",TRUE,_xlfn.XLOOKUP(B33&"|ATTR-27",'Product Variant Attribute'!$A$2:$A$2000&"|"&'Product Variant Attribute'!$D$2:$D$2000,'Product Variant Attribute'!$F$2:$F$2000,""),_xlfn.XLOOKUP(B33&"|ATTR-24",'Product Variant Attribute'!$A$2:$A$2000&"|"&'Product Variant Attribute'!$D$2:$D$2000,'Product Variant Attribute'!$F$2:$F$2000,""))} | F33: Hộp | G33: 1 chai | H33: =IFERROR(--LEFT(G33,FIND(" ",G33&" ")-1),"") -> 1 | I33: =_xlfn.XLOOKUP(C33,Product!$A:$A,Product!$G:$G,"NOT FOUND") -> chai | K33: Liên hệ – merinco.com.vn không công bố giá | L33: 244 | M33: Dung dịch kháng khuẩn Dizigone rửa vết thương, làm sạch vi khuẩn, khử mùi 300ml | N33: 224 | O33: ="INSERT INTO public.medical_supply_sellable_unit (code, price, quantity, sale_uom, product_variant_code) VALUES ('"&A33&"', "&IF(J33="","NULL",J33)&", "&IF(H33="","NULL",H33)&", "&IF(F33="","NULL","'"&SUBSTITUTE(F33,"'","''")&"'")&", '"&B33&"');" -> INSERT INTO public.medical_supply_sellable_unit (code, price, quantity, sale_uom, product_variant_code) VALUES ('PRODUCT-00021-001-01', NULL, 1, 'Hộp', 'PRODUCT-00021-001');
A34: =B34&"-"&TEXT(COUNTIF(B$2:B34,B34),"00") -> PRODUCT-00022-001-01 | B34: PRODUCT-00022-001 | C34: =_xlfn.XLOOKUP(B34,'Product Variant'!$A:$A,'Product Variant'!$B:$B,"NOT FOUND") -> PRODUCT-00022 | D34: =_xlfn.XLOOKUP(B34,'Product Variant'!$A:$A,'Product Variant'!$C:$C,"NOT FOUND") -> [Terrapharm] Xịt kháng khuẩn - Dizigone Spray (100ml) | E34: {=_xlfn.TEXTJOIN(" / ",TRUE,_xlfn.XLOOKUP(B34&"|ATTR-27",'Product Variant Attribute'!$A$2:$A$2000&"|"&'Product Variant Attribute'!$D$2:$D$2000,'Product Variant Attribute'!$F$2:$F$2000,""),_xlfn.XLOOKUP(B34&"|ATTR-24",'Product Variant Attribute'!$A$2:$A$2000&"|"&'Product Variant Attribute'!$D$2:$D$2000,'Product Variant Attribute'!$F$2:$F$2000,""))} | F34: Hộp | G34: 1 chai | H34: =IFERROR(--LEFT(G34,FIND(" ",G34&" ")-1),"") -> 1 | I34: =_xlfn.XLOOKUP(C34,Product!$A:$A,Product!$G:$G,"NOT FOUND") -> chai | J34: 65000 | K34: Giá sản phẩm (chung) – khớp theo tên | L34: 245 | M34: Xịt kháng khuẩn Dizigone Spray loại bỏ vi khuẩn, khử mùi, phòng loét 100ml | N34: 552 | O34: ="INSERT INTO public.medical_supply_sellable_unit (code, price, quantity, sale_uom, product_variant_code) VALUES ('"&A34&"', "&IF(J34="","NULL",J34)&", "&IF(H34="","NULL",H34)&", "&IF(F34="","NULL","'"&SUBSTITUTE(F34,"'","''")&"'")&", '"&B34&"');" -> INSERT INTO public.medical_supply_sellable_unit (code, price, quantity, sale_uom, product_variant_code) VALUES ('PRODUCT-00022-001-01', 65000, 1, 'Hộp', 'PRODUCT-00022-001');
A35: =B35&"-"&TEXT(COUNTIF(B$2:B35,B35),"00") -> PRODUCT-00023-001-01 | B35: PRODUCT-00023-001 | C35: =_xlfn.XLOOKUP(B35,'Product Variant'!$A:$A,'Product Variant'!$B:$B,"NOT FOUND") -> PRODUCT-00023 | D35: =_xlfn.XLOOKUP(B35,'Product Variant'!$A:$A,'Product Variant'!$C:$C,"NOT FOUND") -> [Urgo] Gạc lưới chống dính - UrgoTul (10cmx10cm) | E35: {=_xlfn.TEXTJOIN(" / ",TRUE,_xlfn.XLOOKUP(B35&"|ATTR-27",'Product Variant Attribute'!$A$2:$A$2000&"|"&'Product Variant Attribute'!$D$2:$D$2000,'Product Variant Attribute'!$F$2:$F$2000,""),_xlfn.XLOOKUP(B35&"|ATTR-24",'Product Variant Attribute'!$A$2:$A$2000&"|"&'Product Variant Attribute'!$D$2:$D$2000,'Product Variant Attribute'!$F$2:$F$2000,""))} | F35: Túi | G35: 1 miếng | H35: =IFERROR(--LEFT(G35,FIND(" ",G35&" ")-1),"") -> 1 | I35: =_xlfn.XLOOKUP(C35,Product!$A:$A,Product!$G:$G,"NOT FOUND") -> miếng | J35: 60000 | K35: Giá sản phẩm (chung) – khớp theo tên | L35: 385 | M35: Gạc lưới chống dính UrgoTul 10cmx10cm | N35: 227 | O35: ="INSERT INTO public.medical_supply_sellable_unit (code, price, quantity, sale_uom, product_variant_code) VALUES ('"&A35&"', "&IF(J35="","NULL",J35)&", "&IF(H35="","NULL",H35)&", "&IF(F35="","NULL","'"&SUBSTITUTE(F35,"'","''")&"'")&", '"&B35&"');" -> INSERT INTO public.medical_supply_sellable_unit (code, price, quantity, sale_uom, product_variant_code) VALUES ('PRODUCT-00023-001-01', 60000, 1, 'Túi', 'PRODUCT-00023-001');
A36: =B36&"-"&TEXT(COUNTIF(B$2:B36,B36),"00") -> PRODUCT-00260-001-01 | B36: PRODUCT-00260-001 | C36: =_xlfn.XLOOKUP(B36,'Product Variant'!$A:$A,'Product Variant'!$B:$B,"NOT FOUND") -> PRODUCT-00260 | D36: =_xlfn.XLOOKUP(B36,'Product Variant'!$A:$A,'Product Variant'!$C:$C,"NOT FOUND") -> [Urgo] Gạc lưới chống dính - UrgoTul (15cmx20cm) | E36: {=_xlfn.TEXTJOIN(" / ",TRUE,_xlfn.XLOOKUP(B36&"|ATTR-27",'Product Variant Attribute'!$A$2:$A$2000&"|"&'Product Variant Attribute'!$D$2:$D$2000,'Product Variant Attribute'!$F$2:$F$2000,""),_xlfn.XLOOKUP(B36&"|ATTR-24",'Product Variant Attribute'!$A$2:$A$2000&"|"&'Product Variant Attribute'!$D$2:$D$2000,'Product Variant Attribute'!$F$2:$F$2000,""))} | F36: Túi | G36: 1 miếng | H36: =IFERROR(--LEFT(G36,FIND(" ",G36&" ")-1),"") -> 1 | I36: =_xlfn.XLOOKUP(C36,Product!$A:$A,Product!$G:$G,"NOT FOUND") -> miếng | J36: 85000 | K36: Giá sản phẩm (chung) – khớp theo tên | L36: 383 | M36: Gạc lưới vô trùng chống dính UrgoTul 15cmx20cm | N36: 230 | O36: ="INSERT INTO public.medical_supply_sellable_unit (code, price, quantity, sale_uom, product_variant_code) VALUES ('"&A36&"', "&IF(J36="","NULL",J36)&", "&IF(H36="","NULL",H36)&", "&IF(F36="","NULL","'"&SUBSTITUTE(F36,"'","''")&"'")&", '"&B36&"');" -> INSERT INTO public.medical_supply_sellable_unit (code, price, quantity, sale_uom, product_variant_code) VALUES ('PRODUCT-00260-001-01', 85000, 1, 'Túi', 'PRODUCT-00260-001');
A37: =B37&"-"&TEXT(COUNTIF(B$2:B37,B37),"00") -> PRODUCT-00261-001-01 | B37: PRODUCT-00261-001 | C37: =_xlfn.XLOOKUP(B37,'Product Variant'!$A:$A,'Product Variant'!$B:$B,"NOT FOUND") -> PRODUCT-00261 | D37: =_xlfn.XLOOKUP(B37,'Product Variant'!$A:$A,'Product Variant'!$C:$C,"NOT FOUND") -> [Urgo] Gạc lưới chống dính - UrgoTul (5cmx5cm) | E37: {=_xlfn.TEXTJOIN(" / ",TRUE,_xlfn.XLOOKUP(B37&"|ATTR-27",'Product Variant Attribute'!$A$2:$A$2000&"|"&'Product Variant Attribute'!$D$2:$D$2000,'Product Variant Attribute'!$F$2:$F$2000,""),_xlfn.XLOOKUP(B37&"|ATTR-24",'Product Variant Attribute'!$A$2:$A$2000&"|"&'Product Variant Attribute'!$D$2:$D$2000,'Product Variant Attribute'!$F$2:$F$2000,""))} | F37: Túi | G37: 1 miếng | H37: =IFERROR(--LEFT(G37,FIND(" ",G37&" ")-1),"") -> 1 | I37: =_xlfn.XLOOKUP(C37,Product!$A:$A,Product!$G:$G,"NOT FOUND") -> miếng | J37: 23000 | K37: Giá sản phẩm (chung) – khớp theo tên | L37: 384 | M37: Gạc mỡ chống dính UrgoTul 5cmx5cm | N37: 231 | O37: ="INSERT INTO public.medical_supply_sellable_unit (code, price, quantity, sale_uom, product_variant_code) VALUES ('"&A37&"', "&IF(J37="","NULL",J37)&", "&IF(H37="","NULL",H37)&", "&IF(F37="","NULL","'"&SUBSTITUTE(F37,"'","''")&"'")&", '"&B37&"');" -> INSERT INTO public.medical_supply_sellable_unit (code, price, quantity, sale_uom, product_variant_code) VALUES ('PRODUCT-00261-001-01', 23000, 1, 'Túi', 'PRODUCT-00261-001');
A38: =B38&"-"&TEXT(COUNTIF(B$2:B38,B38),"00") -> PRODUCT-00024-001-01 | B38: PRODUCT-00024-001 | C38: =_xlfn.XLOOKUP(B38,'Product Variant'!$A:$A,'Product Variant'!$B:$B,"NOT FOUND") -> PRODUCT-00024 | D38: =_xlfn.XLOOKUP(B38,'Product Variant'!$A:$A,'Product Variant'!$C:$C,"NOT FOUND") -> [Urgo] Gạc lưới tẩm bạc chống dính - UrgoTul Ag/Silver (10cmx12cm) | E38: {=_xlfn.TEXTJOIN(" / ",TRUE,_xlfn.XLOOKUP(B38&"|ATTR-27",'Product Variant Attribute'!$A$2:$A$2000&"|"&'Product Variant Attribute'!$D$2:$D$2000,'Product Variant Attribute'!$F$2:$F$2000,""),_xlfn.XLOOKUP(B38&"|ATTR-24",'Product Variant Attribute'!$A$2:$A$2000&"|"&'Product Variant Attribute'!$D$2:$D$2000,'Product Variant Attribute'!$F$2:$F$2000,""))} | F38: Túi | G38: 1 miếng | H38: =IFERROR(--LEFT(G38,FIND(" ",G38&" ")-1),"") -> 1 | I38: =_xlfn.XLOOKUP(C38,Product!$A:$A,Product!$G:$G,"NOT FOUND") -> miếng | J38: 85000 | K38: Giá sản phẩm (chung) – khớp theo tên | L38: 382 | M38: Gạc lưới chống dính tẩm bạc UrgoTul Ag/Silver 10cmx12cm | N38: 226 | O38: ="INSERT INTO public.medical_supply_sellable_unit (code, price, quantity, sale_uom, product_variant_code) VALUES ('"&A38&"', "&IF(J38="","NULL",J38)&", "&IF(H38="","NULL",H38)&", "&IF(F38="","NULL","'"&SUBSTITUTE(F38,"'","''")&"'")&", '"&B38&"');" -> INSERT INTO public.medical_supply_sellable_unit (code, price, quantity, sale_uom, product_variant_code) VALUES ('PRODUCT-00024-001-01', 85000, 1, 'Túi', 'PRODUCT-00024-001');
A39: =B39&"-"&TEXT(COUNTIF(B$2:B39,B39),"00") -> PRODUCT-00262-001-01 | B39: PRODUCT-00262-001 | C39: =_xlfn.XLOOKUP(B39,'Product Variant'!$A:$A,'Product Variant'!$B:$B,"NOT FOUND") -> PRODUCT-00262 | D39: =_xlfn.XLOOKUP(B39,'Product Variant'!$A:$A,'Product Variant'!$C:$C,"NOT FOUND") -> [Urgo] Gạc lưới tẩm bạc chống dính - UrgoTul Ag/Silver (15cmx20cm) | E39: {=_xlfn.TEXTJOIN(" / ",TRUE,_xlfn.XLOOKUP(B39&"|ATTR-27",'Product Variant Attribute'!$A$2:$A$2000&"|"&'Product Variant Attribute'!$D$2:$D$2000,'Product Variant Attribute'!$F$2:$F$2000,""),_xlfn.XLOOKUP(B39&"|ATTR-24",'Product Variant Attribute'!$A$2:$A$2000&"|"&'Product Variant Attribute'!$D$2:$D$2000,'Product Variant Attribute'!$F$2:$F$2000,""))} | F39: Túi | G39: 1 miếng | H39: =IFERROR(--LEFT(G39,FIND(" ",G39&" ")-1),"") -> 1 | I39: =_xlfn.XLOOKUP(C39,Product!$A:$A,Product!$G:$G,"NOT FOUND") -> miếng | J39: 130000 | K39: Giá sản phẩm (chung) – khớp theo tên | L39: 380 | M39: Gạc lưới tẩm bạc chống dính UrgoTul Ag/Silver 15cmx20cm | N39: 228 | O39: ="INSERT INTO public.medical_supply_sellable_unit (code, price, quantity, sale_uom, product_variant_code) VALUES ('"&A39&"', "&IF(J39="","NULL",J39)&", "&IF(H39="","NULL",H39)&", "&IF(F39="","NULL","'"&SUBSTITUTE(F39,"'","''")&"'")&", '"&B39&"');" -> INSERT INTO public.medical_supply_sellable_unit (code, price, quantity, sale_uom, product_variant_code) VALUES ('PRODUCT-00262-001-01', 130000, 1, 'Túi', 'PRODUCT-00262-001');
A40: =B40&"-"&TEXT(COUNTIF(B$2:B40,B40),"00") -> PRODUCT-00263-001-01 | B40: PRODUCT-00263-001 | C40: =_xlfn.XLOOKUP(B40,'Product Variant'!$A:$A,'Product Variant'!$B:$B,"NOT FOUND") -> PRODUCT-00263 | D40: =_xlfn.XLOOKUP(B40,'Product Variant'!$A:$A,'Product Variant'!$C:$C,"NOT FOUND") -> [Urgo] Gạc lưới tẩm bạc chống dính - UrgoTul Ag/Silver (5cmx5cm) | E40: {=_xlfn.TEXTJOIN(" / ",TRUE,_xlfn.XLOOKUP(B40&"|ATTR-27",'Product Variant Attribute'!$A$2:$A$2000&"|"&'Product Variant Attribute'!$D$2:$D$2000,'Product Variant Attribute'!$F$2:$F$2000,""),_xlfn.XLOOKUP(B40&"|ATTR-24",'Product Variant Attribute'!$A$2:$A$2000&"|"&'Product Variant Attribute'!$D$2:$D$2000,'Product Variant Attribute'!$F$2:$F$2000,""))} | F40: Túi | G40: 1 miếng | H40: =IFERROR(--LEFT(G40,FIND(" ",G40&" ")-1),"") -> 1 | I40: =_xlfn.XLOOKUP(C40,Product!$A:$A,Product!$G:$G,"NOT FOUND") -> miếng | J40: 30000 | K40: Giá sản phẩm (chung) – khớp theo tên | L40: 381 | M40: Gạc lưới tẩm bạc UrgoTul Ag/Silver 5cmx5cm | N40: 229 | O40: ="INSERT INTO public.medical_supply_sellable_unit (code, price, quantity, sale_uom, product_variant_code) VALUES ('"&A40&"', "&IF(J40="","NULL",J40)&", "&IF(H40="","NULL",H40)&", "&IF(F40="","NULL","'"&SUBSTITUTE(F40,"'","''")&"'")&", '"&B40&"');" -> INSERT INTO public.medical_supply_sellable_unit (code, price, quantity, sale_uom, product_variant_code) VALUES ('PRODUCT-00263-001-01', 30000, 1, 'Túi', 'PRODUCT-00263-001');
A41: =B41&"-"&TEXT(COUNTIF(B$2:B41,B41),"00") -> PRODUCT-00025-001-01 | B41: PRODUCT-00025-001 | C41: =_xlfn.XLOOKUP(B41,'Product Variant'!$A:$A,'Product Variant'!$B:$B,"NOT FOUND") -> PRODUCT-00025 | D41: =_xlfn.XLOOKUP(B41,'Product Variant'!$A:$A,'Product Variant'!$C:$C,"NOT FOUND") -> [VH Pharma] Gel trị vết thương hở - Healit (5g) | E41: {=_xlfn.TEXTJOIN(" / ",TRUE,_xlfn.XLOOKUP(B41&"|ATTR-27",'Product Variant Attribute'!$A$2:$A$2000&"|"&'Product Variant Attribute'!$D$2:$D$2000,'Product Variant Attribute'!$F$2:$F$2000,""),_xlfn.XLOOKUP(B41&"|ATTR-24",'Product Variant Attribute'!$A$2:$A$2000&"|"&'Product Variant Attribute'!$D$2:$D$2000,'Product Variant Attribute'!$F$2:$F$2000,""))} | F41: Hộp | G41: 1 tuýp | H41: =IFERROR(--LEFT(G41,FIND(" ",G41&" ")-1),"") -> 1 | I41: =_xlfn.XLOOKUP(C41,Product!$A:$A,Product!$G:$G,"NOT FOUND") -> tuýp | J41: 309000 | K41: Giá sản phẩm (chung) – khớp theo tên | L41: 250 | M41: Gel trị vết thương hở Healit 5g đẩy nhanh quá trình lành vết thương | N41: 265 | O41: ="INSERT INTO public.medical_supply_sellable_unit (code, price, quantity, sale_uom, product_variant_code) VALUES ('"&A41&"', "&IF(J41="","NULL",J41)&", "&IF(H41="","NULL",H41)&", "&IF(F41="","NULL","'"&SUBSTITUTE(F41,"'","''")&"'")&", '"&B41&"');" -> INSERT INTO public.medical_supply_sellable_unit (code, price, quantity, sale_uom, product_variant_code) VALUES ('PRODUCT-00025-001-01', 309000, 1, 'Hộp', 'PRODUCT-00025-001');
A42: =B42&"-"&TEXT(COUNTIF(B$2:B42,B42),"00") -> PRODUCT-00026-001-01 | B42: PRODUCT-00026-001 | C42: =_xlfn.XLOOKUP(B42,'Product Variant'!$A:$A,'Product Variant'!$B:$B,"NOT FOUND") -> PRODUCT-00026 | D42: =_xlfn.XLOOKUP(B42,'Product Variant'!$A:$A,'Product Variant'!$C:$C,"NOT FOUND") -> [Wonbiogen] Băng dán vết thương Hydrocolloid - Renoderm (10cmx10cm) | E42: {=_xlfn.TEXTJOIN(" / ",TRUE,_xlfn.XLOOKUP(B42&"|ATTR-27",'Product Variant Attribute'!$A$2:$A$2000&"|"&'Product Variant Attribute'!$D$2:$D$2000,'Product Variant Attribute'!$F$2:$F$2000,""),_xlfn.XLOOKUP(B42&"|ATTR-24",'Product Variant Attribute'!$A$2:$A$2000&"|"&'Product Variant Attribute'!$D$2:$D$2000,'Product Variant Attribute'!$F$2:$F$2000,""))} | F42: Túi | G42: 1 miếng | H42: =IFERROR(--LEFT(G42,FIND(" ",G42&" ")-1),"") -> 1 | I42: =_xlfn.XLOOKUP(C42,Product!$A:$A,Product!$G:$G,"NOT FOUND") -> miếng | J42: 50000 | K42: Giá sản phẩm (chung) – khớp theo tên | L42: 465 | M42: Băng dán vết thương Hydrocolloid Renoderm 10cmx10cm miếng dán mụn, bỏng bô, miếng dán chống loét | N42: 5 | O42: ="INSERT INTO public.medical_supply_sellable_unit (code, price, quantity, sale_uom, product_variant_code) VALUES ('"&A42&"', "&IF(J42="","NULL",J42)&", "&IF(H42="","NULL",H42)&", "&IF(F42="","NULL","'"&SUBSTITUTE(F42,"'","''")&"'")&", '"&B42&"');" -> INSERT INTO public.medical_supply_sellable_unit (code, price, quantity, sale_uom, product_variant_code) VALUES ('PRODUCT-00026-001-01', 50000, 1, 'Túi', 'PRODUCT-00026-001');
A43: =B43&"-"&TEXT(COUNTIF(B$2:B43,B43),"00") -> PRODUCT-00027-001-01 | B43: PRODUCT-00027-001 | C43: =_xlfn.XLOOKUP(B43,'Product Variant'!$A:$A,'Product Variant'!$B:$B,"NOT FOUND") -> PRODUCT-00027 | D43: =_xlfn.XLOOKUP(B43,'Product Variant'!$A:$A,'Product Variant'!$C:$C,"NOT FOUND") -> [Wonbiogen] Băng gạc xốp không dính vết thương - Therasorb Algi Plus Adhesive (7.5cmx7.5cm) | E43: {=_xlfn.TEXTJOIN(" / ",TRUE,_xlfn.XLOOKUP(B43&"|ATTR-27",'Product Variant Attribute'!$A$2:$A$2000&"|"&'Product Variant Attribute'!$D$2:$D$2000,'Product Variant Attribute'!$F$2:$F$2000,""),_xlfn.XLOOKUP(B43&"|ATTR-24",'Product Variant Attribute'!$A$2:$A$2000&"|"&'Product Variant Attribute'!$D$2:$D$2000,'Product Variant Attribute'!$F$2:$F$2000,""))} | F43: Túi | G43: 1 miếng | H43: =IFERROR(--LEFT(G43,FIND(" ",G43&" ")-1),"") -> 1 | I43: =_xlfn.XLOOKUP(C43,Product!$A:$A,Product!$G:$G,"NOT FOUND") -> miếng | J43: 68000 | K43: Giá sản phẩm (chung) – khớp theo tên | L43: 333 | M43: Băng gạc xốp Therasorb Algi Plus Adhesive không dính vào vết thương 7.5cmx7.5cm | N43: 42 | O43: ="INSERT INTO public.medical_supply_sellable_unit (code, price, quantity, sale_uom, product_variant_code) VALUES ('"&A43&"', "&IF(J43="","NULL",J43)&", "&IF(H43="","NULL",H43)&", "&IF(F43="","NULL","'"&SUBSTITUTE(F43,"'","''")&"'")&", '"&B43&"');" -> INSERT INTO public.medical_supply_sellable_unit (code, price, quantity, sale_uom, product_variant_code) VALUES ('PRODUCT-00027-001-01', 68000, 1, 'Túi', 'PRODUCT-00027-001');
A44: =B44&"-"&TEXT(COUNTIF(B$2:B44,B44),"00") -> PRODUCT-00264-001-01 | B44: PRODUCT-00264-001 | C44: =_xlfn.XLOOKUP(B44,'Product Variant'!$A:$A,'Product Variant'!$B:$B,"NOT FOUND") -> PRODUCT-00264 | D44: =_xlfn.XLOOKUP(B44,'Product Variant'!$A:$A,'Product Variant'!$C:$C,"NOT FOUND") -> [Wonbiogen] Băng gạc xốp không dính vết thương - Therasorb Algi Plus Adhesive (9cmx15cm) | E44: {=_xlfn.TEXTJOIN(" / ",TRUE,_xlfn.XLOOKUP(B44&"|ATTR-27",'Product Variant Attribute'!$A$2:$A$2000&"|"&'Product Variant Attribute'!$D$2:$D$2000,'Product Variant Attribute'!$F$2:$F$2000,""),_xlfn.XLOOKUP(B44&"|ATTR-24",'Product Variant Attribute'!$A$2:$A$2000&"|"&'Product Variant Attribute'!$D$2:$D$2000,'Product Variant Attribute'!$F$2:$F$2000,""))} | F44: Túi | G44: 1 miếng | H44: =IFERROR(--LEFT(G44,FIND(" ",G44&" ")-1),"") -> 1 | I44: =_xlfn.XLOOKUP(C44,Product!$A:$A,Product!$G:$G,"NOT FOUND") -> miếng | J44: 86000 | K44: Giá sản phẩm (chung) – khớp theo tên | L44: 363 | M44: Băng gạc xốp Therasorb Algi Plus Adhesive không dính vào vết thương 9cmx15cm | N44: 43 | O44: ="INSERT INTO public.medical_supply_sellable_unit (code, price, quantity, sale_uom, product_variant_code) VALUES ('"&A44&"', "&IF(J44="","NULL",J44)&", "&IF(H44="","NULL",H44)&", "&IF(F44="","NULL","'"&SUBSTITUTE(F44,"'","''")&"'")&", '"&B44&"');" -> INSERT INTO public.medical_supply_sellable_unit (code, price, quantity, sale_uom, product_variant_code) VALUES ('PRODUCT-00264-001-01', 86000, 1, 'Túi', 'PRODUCT-00264-001');
A45: =B45&"-"&TEXT(COUNTIF(B$2:B45,B45),"00") -> PRODUCT-00265-001-01 | B45: PRODUCT-00265-001 | C45: =_xlfn.XLOOKUP(B45,'Product Variant'!$A:$A,'Product Variant'!$B:$B,"NOT FOUND") -> PRODUCT-00265 | D45: =_xlfn.XLOOKUP(B45,'Product Variant'!$A:$A,'Product Variant'!$C:$C,"NOT FOUND") -> [Wonbiogen] Băng gạc xốp không dính vết thương - Therasorb Algi Plus Adhesive (9cmx20cm) | E45: {=_xlfn.TEXTJOIN(" / ",TRUE,_xlfn.XLOOKUP(B45&"|ATTR-27",'Product Variant Attribute'!$A$2:$A$2000&"|"&'Product Variant Attribute'!$D$2:$D$2000,'Product Variant Attribute'!$F$2:$F$2000,""),_xlfn.XLOOKUP(B45&"|ATTR-24",'Product Variant Attribute'!$A$2:$A$2000&"|"&'Product Variant Attribute'!$D$2:$D$2000,'Product Variant Attribute'!$F$2:$F$2000,""))} | F45: Túi | G45: 1 miếng | H45: =IFERROR(--LEFT(G45,FIND(" ",G45&" ")-1),"") -> 1 | I45: =_xlfn.XLOOKUP(C45,Product!$A:$A,Product!$G:$G,"NOT FOUND") -> miếng | J45: 102000 | K45: Giá sản phẩm (chung) – khớp theo tên | L45: 358 | M45: Băng gạc xốp Therasorb Algi Plus Adhesive không dính vào vết thương 9cmx20cm | N45: 44 | O45: ="INSERT INTO public.medical_supply_sellable_unit (code, price, quantity, sale_uom, product_variant_code) VALUES ('"&A45&"', "&IF(J45="","NULL",J45)&", "&IF(H45="","NULL",H45)&", "&IF(F45="","NULL","'"&SUBSTITUTE(F45,"'","''")&"'")&", '"&B45&"');" -> INSERT INTO public.medical_supply_sellable_unit (code, price, quantity, sale_uom, product_variant_code) VALUES ('PRODUCT-00265-001-01', 102000, 1, 'Túi', 'PRODUCT-00265-001');
... A56: =B56&"-"&TEXT(COUNTIF(B$2:B56,B56),"00") -> PRODUCT-00270-001-01 | B56: PRODUCT-00270-001 | C56: =_xlfn.XLOOKUP(B56,'Product Variant'!$A:$A,'Product Variant'!$B:$B,"NOT FOUND") -> PRODUCT-00270 | D56: =_xlfn.XLOOKUP(B56,'Product Variant'!$A:$A,'Product Variant'!$C:$C,"NOT FOUND") -> [Wonbiogen] Gạc xốp siêu thấm hút dịch tiết vết thương - Therasorb Algi Plus Hydrophilic (20cmx20cm) | E56: {=_xlfn.TEXTJOIN(" / ",TRUE,_xlfn.XLOOKUP(B56&"|ATTR-27",'Product Variant Attribute'!$A$2:$A$2000&"|"&'Product Variant Attribute'!$D$2:$D$2000,'Product Variant Attribute'!$F$2:$F$2000,""),_xlfn.XLOOKUP(B56&"|ATTR-24",'Product Variant Attribute'!$A$2:$A$2000&"|"&'Product Variant Attribute'!$D$2:$D$2000,'Product Variant Attribute'!$F$2:$F$2000,""))} | F56: Túi | G56: 1 miếng | H56: =IFERROR(--LEFT(G56,FIND(" ",G56&" ")-1),"") -> 1 | I56: =_xlfn.XLOOKUP(C56,Product!$A:$A,Product!$G:$G,"NOT FOUND") -> miếng | J56: 390000 | K56: Giá sản phẩm (chung) – khớp theo tên | L56: 433 | M56: Gạc xốp siêu thấm hút dịch tiết vết thương Therasorb Algi Plus Hydrophilic 20cmx20cm | N56: 243 | O56: ="INSERT INTO public.medical_supply_sellable_unit (code, price, quantity, sale_uom, product_variant_code) VALUES ('"&A56&"', "&IF(J56="","NULL",J56)&", "&IF(H56="","NULL",H56)&", "&IF(F56="","NULL","'"&SUBSTITUTE(F56,"'","''")&"'")&", '"&B56&"');" -> INSERT INTO public.medical_supply_sellable_unit (code, price, quantity, sale_uom, product_variant_code) VALUES ('PRODUCT-00270-001-01', 390000, 1, 'Túi', 'PRODUCT-00270-001');
A57: =B57&"-"&TEXT(COUNTIF(B$2:B57,B57),"00") -> PRODUCT-00271-001-01 | B57: PRODUCT-00271-001 | C57: =_xlfn.XLOOKUP(B57,'Product Variant'!$A:$A,'Product Variant'!$B:$B,"NOT FOUND") -> PRODUCT-00271 | D57: =_xlfn.XLOOKUP(B57,'Product Variant'!$A:$A,'Product Variant'!$C:$C,"NOT FOUND") -> [Wonbiogen] Gạc xốp siêu thấm hút dịch tiết vết thương - Therasorb Algi Plus Hydrophilic (35cmx50cm) | E57: {=_xlfn.TEXTJOIN(" / ",TRUE,_xlfn.XLOOKUP(B57&"|ATTR-27",'Product Variant Attribute'!$A$2:$A$2000&"|"&'Product Variant Attribute'!$D$2:$D$2000,'Product Variant Attribute'!$F$2:$F$2000,""),_xlfn.XLOOKUP(B57&"|ATTR-24",'Product Variant Attribute'!$A$2:$A$2000&"|"&'Product Variant Attribute'!$D$2:$D$2000,'Product Variant Attribute'!$F$2:$F$2000,""))} | F57: Túi | G57: 1 miếng | H57: =IFERROR(--LEFT(G57,FIND(" ",G57&" ")-1),"") -> 1 | I57: =_xlfn.XLOOKUP(C57,Product!$A:$A,Product!$G:$G,"NOT FOUND") -> miếng | K57: Liên hệ – merinco.com.vn không công bố giá | L57: 406 | M57: Gạc xốp siêu thấm hút dịch tiết vết thương Therasorb Algi Plus Hydrophilic 35cmx50cm | N57: 244 | O57: ="INSERT INTO public.medical_supply_sellable_unit (code, price, quantity, sale_uom, product_variant_code) VALUES ('"&A57&"', "&IF(J57="","NULL",J57)&", "&IF(H57="","NULL",H57)&", "&IF(F57="","NULL","'"&SUBSTITUTE(F57,"'","''")&"'")&", '"&B57&"');" -> INSERT INTO public.medical_supply_sellable_unit (code, price, quantity, sale_uom, product_variant_code) VALUES ('PRODUCT-00271-001-01', NULL, 1, 'Túi', 'PRODUCT-00271-001');
A58: =B58&"-"&TEXT(COUNTIF(B$2:B58,B58),"00") -> PRODUCT-00029-001-01 | B58: PRODUCT-00029-001 | C58: =_xlfn.XLOOKUP(B58,'Product Variant'!$A:$A,'Product Variant'!$B:$B,"NOT FOUND") -> PRODUCT-00029 | D58: =_xlfn.XLOOKUP(B58,'Product Variant'!$A:$A,'Product Variant'!$C:$C,"NOT FOUND") -> [Wonbiogen] Gạc xốp tẩm bạc kháng khuẩn - Therasorb® Ag Plus (10cmx10cm) | E58: {=_xlfn.TEXTJOIN(" / ",TRUE,_xlfn.XLOOKUP(B58&"|ATTR-27",'Product Variant Attribute'!$A$2:$A$2000&"|"&'Product Variant Attribute'!$D$2:$D$2000,'Product Variant Attribute'!$F$2:$F$2000,""),_xlfn.XLOOKUP(B58&"|ATTR-24",'Product Variant Attribute'!$A$2:$A$2000&"|"&'Product Variant Attribute'!$D$2:$D$2000,'Product Variant Attribute'!$F$2:$F$2000,""))} | F58: Túi | G58: 1 miếng | H58: =IFERROR(--LEFT(G58,FIND(" ",G58&" ")-1),"") -> 1 | I58: =_xlfn.XLOOKUP(C58,Product!$A:$A,Product!$G:$G,"NOT FOUND") -> miếng | J58: 188000 | K58: Giá sản phẩm (chung) – khớp theo tên | L58: 76, 452 | M58: Gạc xốp tẩm bạc kháng khuẩn Therasorb® Ag Plus 10cmx10cm (1 miếng) | N58: 249, 252 | O58: ="INSERT INTO public.medical_supply_sellable_unit (code, price, quantity, sale_uom, product_variant_code) VALUES ('"&A58&"', "&IF(J58="","NULL",J58)&", "&IF(H58="","NULL",H58)&", "&IF(F58="","NULL","'"&SUBSTITUTE(F58,"'","''")&"'")&", '"&B58&"');" -> INSERT INTO public.medical_supply_sellable_unit (code, price, quantity, sale_uom, product_variant_code) VALUES ('PRODUCT-00029-001-01', 188000, 1, 'Túi', 'PRODUCT-00029-001');
A59: =B59&"-"&TEXT(COUNTIF(B$2:B59,B59),"00") -> PRODUCT-00029-001-02 | B59: PRODUCT-00029-001 | C59: =_xlfn.XLOOKUP(B59,'Product Variant'!$A:$A,'Product Variant'!$B:$B,"NOT FOUND") -> PRODUCT-00029 | D59: =_xlfn.XLOOKUP(B59,'Product Variant'!$A:$A,'Product Variant'!$C:$C,"NOT FOUND") -> [Wonbiogen] Gạc xốp tẩm bạc kháng khuẩn - Therasorb® Ag Plus (10cmx10cm) | E59: {=_xlfn.TEXTJOIN(" / ",TRUE,_xlfn.XLOOKUP(B59&"|ATTR-27",'Product Variant Attribute'!$A$2:$A$2000&"|"&'Product Variant Attribute'!$D$2:$D$2000,'Product Variant Attribute'!$F$2:$F$2000,""),_xlfn.XLOOKUP(B59&"|ATTR-24",'Product Variant Attribute'!$A$2:$A$2000&"|"&'Product Variant Attribute'!$D$2:$D$2000,'Product Variant Attribute'!$F$2:$F$2000,""))} | F59: Hộp | G59: 10 miếng | H59: =IFERROR(--LEFT(G59,FIND(" ",G59&" ")-1),"") -> 10 | I59: =_xlfn.XLOOKUP(C59,Product!$A:$A,Product!$G:$G,"NOT FOUND") -> miếng | J59: 1880000 | K59: Giá sản phẩm (chung) – khớp theo tên | L59: 12, 74 | M59: Gạc xốp tẩm bạc kháng khuẩn Therasorb® Ag Plus 10cmx10cm (hộp) | N59: 250, 254 | O59: ="INSERT INTO public.medical_supply_sellable_unit (code, price, quantity, sale_uom, product_variant_code) VALUES ('"&A59&"', "&IF(J59="","NULL",J59)&", "&IF(H59="","NULL",H59)&", "&IF(F59="","NULL","'"&SUBSTITUTE(F59,"'","''")&"'")&", '"&B59&"');" -> INSERT INTO public.medical_supply_sellable_unit (code, price, quantity, sale_uom, product_variant_code) VALUES ('PRODUCT-00029-001-02', 1880000, 10, 'Hộp', 'PRODUCT-00029-001');
A60: =B60&"-"&TEXT(COUNTIF(B$2:B60,B60),"00") -> PRODUCT-00272-001-01 | B60: PRODUCT-00272-001 | C60: =_xlfn.XLOOKUP(B60,'Product Variant'!$A:$A,'Product Variant'!$B:$B,"NOT FOUND") -> PRODUCT-00272 | D60: =_xlfn.XLOOKUP(B60,'Product Variant'!$A:$A,'Product Variant'!$C:$C,"NOT FOUND") -> [Wonbiogen] Gạc xốp tẩm bạc kháng khuẩn - Therasorb® Ag Plus (20cmx20cm) | E60: {=_xlfn.TEXTJOIN(" / ",TRUE,_xlfn.XLOOKUP(B60&"|ATTR-27",'Product Variant Attribute'!$A$2:$A$2000&"|"&'Product Variant Attribute'!$D$2:$D$2000,'Product Variant Attribute'!$F$2:$F$2000,""),_xlfn.XLOOKUP(B60&"|ATTR-24",'Product Variant Attribute'!$A$2:$A$2000&"|"&'Product Variant Attribute'!$D$2:$D$2000,'Product Variant Attribute'!$F$2:$F$2000,""))} | F60: Túi | G60: 1 miếng | H60: =IFERROR(--LEFT(G60,FIND(" ",G60&" ")-1),"") -> 1 | I60: =_xlfn.XLOOKUP(C60,Product!$A:$A,Product!$G:$G,"NOT FOUND") -> miếng | J60: 750000 | K60: Giá sản phẩm (chung) – khớp theo tên | L60: 407, 453 | M60: Gạc xốp tẩm bạc kháng khuẩn Therasorb® Ag Plus siêu thấm hút dịch tiết vết thương 20cmx20cm | N60: 251, 253 | O60: ="INSERT INTO public.medical_supply_sellable_unit (code, price, quantity, sale_uom, product_variant_code) VALUES ('"&A60&"', "&IF(J60="","NULL",J60)&", "&IF(H60="","NULL",H60)&", "&IF(F60="","NULL","'"&SUBSTITUTE(F60,"'","''")&"'")&", '"&B60&"');" -> INSERT INTO public.medical_supply_sellable_unit (code, price, quantity, sale_uom, product_variant_code) VALUES ('PRODUCT-00272-001-01', 750000, 1, 'Túi', 'PRODUCT-00272-001');
A61: =B61&"-"&TEXT(COUNTIF(B$2:B61,B61),"00") -> PRODUCT-00272-001-02 | B61: PRODUCT-00272-001 | C61: =_xlfn.XLOOKUP(B61,'Product Variant'!$A:$A,'Product Variant'!$B:$B,"NOT FOUND") -> PRODUCT-00272 | D61: =_xlfn.XLOOKUP(B61,'Product Variant'!$A:$A,'Product Variant'!$C:$C,"NOT FOUND") -> [Wonbiogen] Gạc xốp tẩm bạc kháng khuẩn - Therasorb® Ag Plus (20cmx20cm) | E61: {=_xlfn.TEXTJOIN(" / ",TRUE,_xlfn.XLOOKUP(B61&"|ATTR-27",'Product Variant Attribute'!$A$2:$A$2000&"|"&'Product Variant Attribute'!$D$2:$D$2000,'Product Variant Attribute'!$F$2:$F$2000,""),_xlfn.XLOOKUP(B61&"|ATTR-24",'Product Variant Attribute'!$A$2:$A$2000&"|"&'Product Variant Attribute'!$D$2:$D$2000,'Product Variant Attribute'!$F$2:$F$2000,""))} | F61: Hộp | G61: 10 miếng | H61: =IFERROR(--LEFT(G61,FIND(" ",G61&" ")-1),"") -> 10 | I61: =_xlfn.XLOOKUP(C61,Product!$A:$A,Product!$G:$G,"NOT FOUND") -> miếng | J61: 1880000 | K61: Giá sản phẩm (chung) | L61: 75 | M61: Gạc xốp tẩm bạc kháng khuẩn Therasorb® Ag Plus, hút dịch tiết vết thương (hộp) | N61: 255 | O61: ="INSERT INTO public.medical_supply_sellable_unit (code, price, quantity, sale_uom, product_variant_code) VALUES ('"&A61&"', "&IF(J61="","NULL",J61)&", "&IF(H61="","NULL",H61)&", "&IF(F61="","NULL","'"&SUBSTITUTE(F61,"'","''")&"'")&", '"&B61&"');" -> INSERT INTO public.medical_supply_sellable_unit (code, price, quantity, sale_uom, product_variant_code) VALUES ('PRODUCT-00272-001-02', 1880000, 10, 'Hộp', 'PRODUCT-00272-001');
A62: =B62&"-"&TEXT(COUNTIF(B$2:B62,B62),"00") -> PRODUCT-00030-001-01 | B62: PRODUCT-00030-001 | C62: =_xlfn.XLOOKUP(B62,'Product Variant'!$A:$A,'Product Variant'!$B:$B,"NOT FOUND") -> PRODUCT-00030 | D62: =_xlfn.XLOOKUP(B62,'Product Variant'!$A:$A,'Product Variant'!$C:$C,"NOT FOUND") -> [Wonbiogen] Gel kháng khuẩn vết thương - SurgiGel | E62: {=_xlfn.TEXTJOIN(" / ",TRUE,_xlfn.XLOOKUP(B62&"|ATTR-27",'Product Variant Attribute'!$A$2:$A$2000&"|"&'Product Variant Attribute'!$D$2:$D$2000,'Product Variant Attribute'!$F$2:$F$2000,""),_xlfn.XLOOKUP(B62&"|ATTR-24",'Product Variant Attribute'!$A$2:$A$2000&"|"&'Product Variant Attribute'!$D$2:$D$2000,'Product Variant Attribute'!$F$2:$F$2000,""))} | F62: Hộp | G62: 1 tuýp | H62: =IFERROR(--LEFT(G62,FIND(" ",G62&" ")-1),"") -> 1 | I62: =_xlfn.XLOOKUP(C62,Product!$A:$A,Product!$G:$G,"NOT FOUND") -> tuýp | J62: 380000 | K62: Giá sản phẩm (chung) – khớp theo tên | L62: 165 | M62: Gel kháng khuẩn vết thương SurgiGel hỗ trợ làm lành vết thương | N62: 264 | O62: ="INSERT INTO public.medical_supply_sellable_unit (code, price, quantity, sale_uom, product_variant_code) VALUES ('"&A62&"', "&IF(J62="","NULL",J62)&", "&IF(H62="","NULL",H62)&", "&IF(F62="","NULL","'"&SUBSTITUTE(F62,"'","''")&"'")&", '"&B62&"');" -> INSERT INTO public.medical_supply_sellable_unit (code, price, quantity, sale_uom, product_variant_code) VALUES ('PRODUCT-00030-001-01', 380000, 1, 'Hộp', 'PRODUCT-00030-001');
A63: =B63&"-"&TEXT(COUNTIF(B$2:B63,B63),"00") -> PRODUCT-00031-001-01 | B63: PRODUCT-00031-001 | C63: =_xlfn.XLOOKUP(B63,'Product Variant'!$A:$A,'Product Variant'!$B:$B,"NOT FOUND") -> PRODUCT-00031 | D63: =_xlfn.XLOOKUP(B63,'Product Variant'!$A:$A,'Product Variant'!$C:$C,"NOT FOUND") -> [Wonbiogen] Kem gel silicone trị sẹo - RemScar® Gel (15g) | E63: {=_xlfn.TEXTJOIN(" / ",TRUE,_xlfn.XLOOKUP(B63&"|ATTR-27",'Product Variant Attribute'!$A$2:$A$2000&"|"&'Product Variant Attribute'!$D$2:$D$2000,'Product Variant Attribute'!$F$2:$F$2000,""),_xlfn.XLOOKUP(B63&"|ATTR-24",'Product Variant Attribute'!$A$2:$A$2000&"|"&'Product Variant Attribute'!$D$2:$D$2000,'Product Variant Attribute'!$F$2:$F$2000,""))} | F63: Hộp | G63: 1 tuýp | H63: =IFERROR(--LEFT(G63,FIND(" ",G63&" ")-1),"") -> 1 | I63: =_xlfn.XLOOKUP(C63,Product!$A:$A,Product!$G:$G,"NOT FOUND") -> tuýp | J63: 320000 | K63: Giá sản phẩm (chung) – khớp theo tên | L63: 150, 460 | M63: Kem gel silicone trị sẹo RemScar® Gel 15g hỗ trợ ngăn ngừa và điều trị sẹo | N63: 271, 273 | O63: ="INSERT INTO public.medical_supply_sellable_unit (code, price, quantity, sale_uom, product_variant_code) VALUES ('"&A63&"', "&IF(J63="","NULL",J63)&", "&IF(H63="","NULL",H63)&", "&IF(F63="","NULL","'"&SUBSTITUTE(F63,"'","''")&"'")&", '"&B63&"');" -> INSERT INTO public.medical_supply_sellable_unit (code, price, quantity, sale_uom, product_variant_code) VALUES ('PRODUCT-00031-001-01', 320000, 1, 'Hộp', 'PRODUCT-00031-001');
A64: =B64&"-"&TEXT(COUNTIF(B$2:B64,B64),"00") -> PRODUCT-00273-001-01 | B64: PRODUCT-00273-001 | C64: =_xlfn.XLOOKUP(B64,'Product Variant'!$A:$A,'Product Variant'!$B:$B,"NOT FOUND") -> PRODUCT-00273 | D64: =_xlfn.XLOOKUP(B64,'Product Variant'!$A:$A,'Product Variant'!$C:$C,"NOT FOUND") -> [Wonbiogen] Kem gel silicone trị sẹo - RemScar® Gel (30g) | E64: {=_xlfn.TEXTJOIN(" / ",TRUE,_xlfn.XLOOKUP(B64&"|ATTR-27",'Product Variant Attribute'!$A$2:$A$2000&"|"&'Product Variant Attribute'!$D$2:$D$2000,'Product Variant Attribute'!$F$2:$F$2000,""),_xlfn.XLOOKUP(B64&"|ATTR-24",'Product Variant Attribute'!$A$2:$A$2000&"|"&'Product Variant Attribute'!$D$2:$D$2000,'Product Variant Attribute'!$F$2:$F$2000,""))} | F64: Hộp | G64: 1 tuýp 30g | H64: =IFERROR(--LEFT(G64,FIND(" ",G64&" ")-1),"") -> 1 | I64: =_xlfn.XLOOKUP(C64,Product!$A:$A,Product!$G:$G,"NOT FOUND") -> tuýp | J64: 480000 | K64: Giá sản phẩm (chung) – khớp theo tên | L64: 404 | M64: Kem gel silicone trị sẹo RemScar® Gel 30g hỗ trợ ngăn ngừa và làm mờ sẹo | N64: 272 | O64: ="INSERT INTO public.medical_supply_sellable_unit (code, price, quantity, sale_uom, product_variant_code) VALUES ('"&A64&"', "&IF(J64="","NULL",J64)&", "&IF(H64="","NULL",H64)&", "&IF(F64="","NULL","'"&SUBSTITUTE(F64,"'","''")&"'")&", '"&B64&"');" -> INSERT INTO public.medical_supply_sellable_unit (code, price, quantity, sale_uom, product_variant_code) VALUES ('PRODUCT-00273-001-01', 480000, 1, 'Hộp', 'PRODUCT-00273-001');
A65: =B65&"-"&TEXT(COUNTIF(B$2:B65,B65),"00") -> PRODUCT-00273-001-02 | B65: PRODUCT-00273-001 | C65: =_xlfn.XLOOKUP(B65,'Product Variant'!$A:$A,'Product Variant'!$B:$B,"NOT FOUND") -> PRODUCT-00273 | D65: =_xlfn.XLOOKUP(B65,'Product Variant'!$A:$A,'Product Variant'!$C:$C,"NOT FOUND") -> [Wonbiogen] Kem gel silicone trị sẹo - RemScar® Gel (30g) | E65: {=_xlfn.TEXTJOIN(" / ",TRUE,_xlfn.XLOOKUP(B65&"|ATTR-27",'Product Variant Attribute'!$A$2:$A$2000&"|"&'Product Variant Attribute'!$D$2:$D$2000,'Product Variant Attribute'!$F$2:$F$2000,""),_xlfn.XLOOKUP(B65&"|ATTR-24",'Product Variant Attribute'!$A$2:$A$2000&"|"&'Product Variant Attribute'!$D$2:$D$2000,'Product Variant Attribute'!$F$2:$F$2000,""))} | F65: Hộp | G65: 1 tuýp | H65: =IFERROR(--LEFT(G65,FIND(" ",G65&" ")-1),"") -> 1 | I65: =_xlfn.XLOOKUP(C65,Product!$A:$A,Product!$G:$G,"NOT FOUND") -> tuýp | J65: 480000 | K65: Giá (theo biến thể) | L65: 461 | M65: Kem gel silicone trị sẹo RemScar® Gel mờ sẹo | N65: 274 | O65: ="INSERT INTO public.medical_supply_sellable_unit (code, price, quantity, sale_uom, product_variant_code) VALUES ('"&A65&"', "&IF(J65="","NULL",J65)&", "&IF(H65="","NULL",H65)&", "&IF(F65="","NULL","'"&SUBSTITUTE(F65,"'","''")&"'")&", '"&B65&"');" -> INSERT INTO public.medical_supply_sellable_unit (code, price, quantity, sale_uom, product_variant_code) VALUES ('PRODUCT-00273-001-02', 480000, 1, 'Hộp', 'PRODUCT-00273-001');
A66: =B66&"-"&TEXT(COUNTIF(B$2:B66,B66),"00") -> PRODUCT-00032-001-01 | B66: PRODUCT-00032-001 | C66: =_xlfn.XLOOKUP(B66,'Product Variant'!$A:$A,'Product Variant'!$B:$B,"NOT FOUND") -> PRODUCT-00032 | D66: =_xlfn.XLOOKUP(B66,'Product Variant'!$A:$A,'Product Variant'!$C:$C,"NOT FOUND") -> [Wonbiogen] Miếng dán silicone trị sẹo lồi, sẹo thâm - RemScar® TR (12cmx15cm) | E66: {=_xlfn.TEXTJOIN(" / ",TRUE,_xlfn.XLOOKUP(B66&"|ATTR-27",'Product Variant Attribute'!$A$2:$A$2000&"|"&'Product Variant Attribute'!$D$2:$D$2000,'Product Variant Attribute'!$F$2:$F$2000,""),_xlfn.XLOOKUP(B66&"|ATTR-24",'Product Variant Attribute'!$A$2:$A$2000&"|"&'Product Variant Attribute'!$D$2:$D$2000,'Product Variant Attribute'!$F$2:$F$2000,""))} | F66: Hộp | G66: 1 miếng | H66: =IFERROR(--LEFT(G66,FIND(" ",G66&" ")-1),"") -> 1 | I66: =_xlfn.XLOOKUP(C66,Product!$A:$A,Product!$G:$G,"NOT FOUND") -> miếng | J66: 940000 | K66: Giá sản phẩm (chung) – khớp theo tên | L66: 405, 464 | M66: Miếng dán silicone trị sẹo lồi, sẹo thâm RemScar® TR 12cmx15cm | N66: 350, 355 | O66: ="INSERT INTO public.medical_supply_sellable_unit (code, price, quantity, sale_uom, product_variant_code) VALUES ('"&A66&"', "&IF(J66="","NULL",J66)&", "&IF(H66="","NULL",H66)&", "&IF(F66="","NULL","'"&SUBSTITUTE(F66,"'","''")&"'")&", '"&B66&"');" -> INSERT INTO public.medical_supply_sellable_unit (code, price, quantity, sale_uom, product_variant_code) VALUES ('PRODUCT-00032-001-01', 940000, 1, 'Hộp', 'PRODUCT-00032-001');
A67: =B67&"-"&TEXT(COUNTIF(B$2:B67,B67),"00") -> PRODUCT-00274-001-01 | B67: PRODUCT-00274-001 | C67: =_xlfn.XLOOKUP(B67,'Product Variant'!$A:$A,'Product Variant'!$B:$B,"NOT FOUND") -> PRODUCT-00274 | D67: =_xlfn.XLOOKUP(B67,'Product Variant'!$A:$A,'Product Variant'!$C:$C,"NOT FOUND") -> [Wonbiogen] Miếng dán silicone trị sẹo lồi, sẹo thâm - RemScar® TR (3.5cmx15cm) | E67: {=_xlfn.TEXTJOIN(" / ",TRUE,_xlfn.XLOOKUP(B67&"|ATTR-27",'Product Variant Attribute'!$A$2:$A$2000&"|"&'Product Variant Attribute'!$D$2:$D$2000,'Product Variant Attribute'!$F$2:$F$2000,""),_xlfn.XLOOKUP(B67&"|ATTR-24",'Product Variant Attribute'!$A$2:$A$2000&"|"&'Product Variant Attribute'!$D$2:$D$2000,'Product Variant Attribute'!$F$2:$F$2000,""))} | F67: Hộp | G67: 1 miếng | H67: =IFERROR(--LEFT(G67,FIND(" ",G67&" ")-1),"") -> 1 | I67: =_xlfn.XLOOKUP(C67,Product!$A:$A,Product!$G:$G,"NOT FOUND") -> miếng | J67: 450000 | K67: Giá sản phẩm (chung) – khớp theo tên | L67: 359, 463 | M67: Miếng dán silicone trị sẹo lồi, sẹo thâm RemScar® TR 3.5cmx15cm | N67: 351, 354 | O67: ="INSERT INTO public.medical_supply_sellable_unit (code, price, quantity, sale_uom, product_variant_code) VALUES ('"&A67&"', "&IF(J67="","NULL",J67)&", "&IF(H67="","NULL",H67)&", "&IF(F67="","NULL","'"&SUBSTITUTE(F67,"'","''")&"'")&", '"&B67&"');" -> INSERT INTO public.medical_supply_sellable_unit (code, price, quantity, sale_uom, product_variant_code) VALUES ('PRODUCT-00274-001-01', 450000, 1, 'Hộp', 'PRODUCT-00274-001');
A68: =B68&"-"&TEXT(COUNTIF(B$2:B68,B68),"00") -> PRODUCT-00275-001-01 | B68: PRODUCT-00275-001 | C68: =_xlfn.XLOOKUP(B68,'Product Variant'!$A:$A,'Product Variant'!$B:$B,"NOT FOUND") -> PRODUCT-00275 | D68: =_xlfn.XLOOKUP(B68,'Product Variant'!$A:$A,'Product Variant'!$C:$C,"NOT FOUND") -> [Wonbiogen] Miếng dán silicone trị sẹo lồi, sẹo thâm - RemScar® TR (5cmx6cm) | E68: {=_xlfn.TEXTJOIN(" / ",TRUE,_xlfn.XLOOKUP(B68&"|ATTR-27",'Product Variant Attribute'!$A$2:$A$2000&"|"&'Product Variant Attribute'!$D$2:$D$2000,'Product Variant Attribute'!$F$2:$F$2000,""),_xlfn.XLOOKUP(B68&"|ATTR-24",'Product Variant Attribute'!$A$2:$A$2000&"|"&'Product Variant Attribute'!$D$2:$D$2000,'Product Variant Attribute'!$F$2:$F$2000,""))} | F68: Hộp | G68: 2 miếng | H68: =IFERROR(--LEFT(G68,FIND(" ",G68&" ")-1),"") -> 2 | I68: =_xlfn.XLOOKUP(C68,Product!$A:$A,Product!$G:$G,"NOT FOUND") -> miếng | J68: 430000 | K68: Giá sản phẩm (chung) – khớp theo tên | L68: 306, 462 | M68: Miếng dán silicone trị sẹo lồi, sẹo thâm RemScar® TR 5cmx6cm | N68: 352, 353 | O68: ="INSERT INTO public.medical_supply_sellable_unit (code, price, quantity, sale_uom, product_variant_code) VALUES ('"&A68&"', "&IF(J68="","NULL",J68)&", "&IF(H68="","NULL",H68)&", "&IF(F68="","NULL","'"&SUBSTITUTE(F68,"'","''")&"'")&", '"&B68&"');" -> INSERT INTO public.medical_supply_sellable_unit (code, price, quantity, sale_uom, product_variant_code) VALUES ('PRODUCT-00275-001-01', 430000, 2, 'Hộp', 'PRODUCT-00275-001');
A69: =B69&"-"&TEXT(COUNTIF(B$2:B69,B69),"00") -> PRODUCT-00033-001-01 | B69: PRODUCT-00033-001 | C69: =_xlfn.XLOOKUP(B69,'Product Variant'!$A:$A,'Product Variant'!$B:$B,"NOT FOUND") -> PRODUCT-00033 | D69: =_xlfn.XLOOKUP(B69,'Product Variant'!$A:$A,'Product Variant'!$C:$C,"NOT FOUND") -> [Yafho] Gạc xốp hút dịch chống loét có viền dính silicone (18cmx18cm) | E69: {=_xlfn.TEXTJOIN(" / ",TRUE,_xlfn.XLOOKUP(B69&"|ATTR-27",'Product Variant Attribute'!$A$2:$A$2000&"|"&'Product Variant Attribute'!$D$2:$D$2000,'Product Variant Attribute'!$F$2:$F$2000,""),_xlfn.XLOOKUP(B69&"|ATTR-24",'Product Variant Attribute'!$A$2:$A$2000&"|"&'Product Variant Attribute'!$D$2:$D$2000,'Product Variant Attribute'!$F$2:$F$2000,""))} | F69: Túi | G69: 1 miếng | H69: =IFERROR(--LEFT(G69,FIND(" ",G69&" ")-1),"") -> 1 | I69: =_xlfn.XLOOKUP(C69,Product!$A:$A,Product!$G:$G,"NOT FOUND") -> miếng | J69: 150000 | K69: Giá sản phẩm (chung) – khớp theo tên | L69: 259 | M69: Gạc xốp hút dịch chống loét cùng cụt, loét mông có viền dính silicone Yafho | N69: 234 | O69: ="INSERT INTO public.medical_supply_sellable_unit (code, price, quantity, sale_uom, product_variant_code) VALUES ('"&A69&"', "&IF(J69="","NULL",J69)&", "&IF(H69="","NULL",H69)&", "&IF(F69="","NULL","'"&SUBSTITUTE(F69,"'","''")&"'")&", '"&B69&"');" -> INSERT INTO public.medical_supply_sellable_unit (code, price, quantity, sale_uom, product_variant_code) VALUES ('PRODUCT-00033-001-01', 150000, 1, 'Túi', 'PRODUCT-00033-001');
A70: =B70&"-"&TEXT(COUNTIF(B$2:B70,B70),"00") -> PRODUCT-00034-001-01 | B70: PRODUCT-00034-001 | C70: =_xlfn.XLOOKUP(B70,'Product Variant'!$A:$A,'Product Variant'!$B:$B,"NOT FOUND") -> PRODUCT-00034 | D70: =_xlfn.XLOOKUP(B70,'Product Variant'!$A:$A,'Product Variant'!$C:$C,"NOT FOUND") -> [Young Chemical Vina] Băng gạc vô trùng - Young Wound Dressing (6cmx7cm) | E70: {=_xlfn.TEXTJOIN(" / ",TRUE,_xlfn.XLOOKUP(B70&"|ATTR-27",'Product Variant Attribute'!$A$2:$A$2000&"|"&'Product Variant Attribute'!$D$2:$D$2000,'Product Variant Attribute'!$F$2:$F$2000,""),_xlfn.XLOOKUP(B70&"|ATTR-24",'Product Variant Attribute'!$A$2:$A$2000&"|"&'Product Variant Attribute'!$D$2:$D$2000,'Product Variant Attribute'!$F$2:$F$2000,""))} | F70: Túi | G70: 1 miếng | H70: =IFERROR(--LEFT(G70,FIND(" ",G70&" ")-1),"") -> 1 | I70: =_xlfn.XLOOKUP(C70,Product!$A:$A,Product!$G:$G,"NOT FOUND") -> miếng | J70: 3600 | K70: Giá (theo biến thể) – nguồn có nhiều giá: 3600 / 160000 – khớp theo tên | L70: 473, 109, 98 | M70: Băng gạc vô trùng Young Wound Dressing (1 miếng) | N70: 14, 30, 31 | O70: ="INSERT INTO public.medical_supply_sellable_unit (code, price, quantity, sale_uom, product_variant_code) VALUES ('"&A70&"', "&IF(J70="","NULL",J70)&", "&IF(H70="","NULL",H70)&", "&IF(F70="","NULL","'"&SUBSTITUTE(F70,"'","''")&"'")&", '"&B70&"');" -> INSERT INTO public.medical_supply_sellable_unit (code, price, quantity, sale_uom, product_variant_code) VALUES ('PRODUCT-00034-001-01', 3600, 1, 'Túi', 'PRODUCT-00034-001');
A71: =B71&"-"&TEXT(COUNTIF(B$2:B71,B71),"00") -> PRODUCT-00034-001-02 | B71: PRODUCT-00034-001 | C71: =_xlfn.XLOOKUP(B71,'Product Variant'!$A:$A,'Product Variant'!$B:$B,"NOT FOUND") -> PRODUCT-00034 | D71: =_xlfn.XLOOKUP(B71,'Product Variant'!$A:$A,'Product Variant'!$C:$C,"NOT FOUND") -> [Young Chemical Vina] Băng gạc vô trùng - Young Wound Dressing (6cmx7cm) | E71: {=_xlfn.TEXTJOIN(" / ",TRUE,_xlfn.XLOOKUP(B71&"|ATTR-27",'Product Variant Attribute'!$A$2:$A$2000&"|"&'Product Variant Attribute'!$D$2:$D$2000,'Product Variant Attribute'!$F$2:$F$2000,""),_xlfn.XLOOKUP(B71&"|ATTR-24",'Product Variant Attribute'!$A$2:$A$2000&"|"&'Product Variant Attribute'!$D$2:$D$2000,'Product Variant Attribute'!$F$2:$F$2000,""))} | F71: Hộp | G71: 50 miếng | H71: =IFERROR(--LEFT(G71,FIND(" ",G71&" ")-1),"") -> 50 | I71: =_xlfn.XLOOKUP(C71,Product!$A:$A,Product!$G:$G,"NOT FOUND") -> miếng | J71: 160000 | K71: Giá (theo biến thể) | L71: 101 | M71: Băng gạc vô trùng Young Wound Dressing (hộp) | N71: 21 | O71: ="INSERT INTO public.medical_supply_sellable_unit (code, price, quantity, sale_uom, product_variant_code) VALUES ('"&A71&"', "&IF(J71="","NULL",J71)&", "&IF(H71="","NULL",H71)&", "&IF(F71="","NULL","'"&SUBSTITUTE(F71,"'","''")&"'")&", '"&B71&"');" -> INSERT INTO public.medical_supply_sellable_unit (code, price, quantity, sale_uom, product_variant_code) VALUES ('PRODUCT-00034-001-02', 160000, 50, 'Hộp', 'PRODUCT-00034-001');
A72: =B72&"-"&TEXT(COUNTIF(B$2:B72,B72),"00") -> PRODUCT-00276-001-01 | B72: PRODUCT-00276-001 | C72: =_xlfn.XLOOKUP(B72,'Product Variant'!$A:$A,'Product Variant'!$B:$B,"NOT FOUND") -> PRODUCT-00276 | D72: =_xlfn.XLOOKUP(B72,'Product Variant'!$A:$A,'Product Variant'!$C:$C,"NOT FOUND") -> [Young Chemical Vina] Băng gạc vô trùng - Young Wound Dressing (6cmx10cm) | E72: {=_xlfn.TEXTJOIN(" / ",TRUE,_xlfn.XLOOKUP(B72&"|ATTR-27",'Product Variant Attribute'!$A$2:$A$2000&"|"&'Product Variant Attribute'!$D$2:$D$2000,'Product Variant Attribute'!$F$2:$F$2000,""),_xlfn.XLOOKUP(B72&"|ATTR-24",'Product Variant Attribute'!$A$2:$A$2000&"|"&'Product Variant Attribute'!$D$2:$D$2000,'Product Variant Attribute'!$F$2:$F$2000,""))} | F72: Túi | G72: 1 miếng | H72: =IFERROR(--LEFT(G72,FIND(" ",G72&" ")-1),"") -> 1 | I72: =_xlfn.XLOOKUP(C72,Product!$A:$A,Product!$G:$G,"NOT FOUND") -> miếng | J72: 5200 | K72: Giá (theo biến thể) – khớp theo tên | L72: 474, 415 | M72: Băng gạc vô trùng Young Wound Dressing (1 miếng) | N72: 15, 28 | O72: ="INSERT INTO public.medical_supply_sellable_unit (code, price, quantity, sale_uom, product_variant_code) VALUES ('"&A72&"', "&IF(J72="","NULL",J72)&", "&IF(H72="","NULL",H72)&", "&IF(F72="","NULL","'"&SUBSTITUTE(F72,"'","''")&"'")&", '"&B72&"');" -> INSERT INTO public.medical_supply_sellable_unit (code, price, quantity, sale_uom, product_variant_code) VALUES ('PRODUCT-00276-001-01', 5200, 1, 'Túi', 'PRODUCT-00276-001');
A73: =B73&"-"&TEXT(COUNTIF(B$2:B73,B73),"00") -> PRODUCT-00276-001-02 | B73: PRODUCT-00276-001 | C73: =_xlfn.XLOOKUP(B73,'Product Variant'!$A:$A,'Product Variant'!$B:$B,"NOT FOUND") -> PRODUCT-00276 | D73: =_xlfn.XLOOKUP(B73,'Product Variant'!$A:$A,'Product Variant'!$C:$C,"NOT FOUND") -> [Young Chemical Vina] Băng gạc vô trùng - Young Wound Dressing (6cmx10cm) | E73: {=_xlfn.TEXTJOIN(" / ",TRUE,_xlfn.XLOOKUP(B73&"|ATTR-27",'Product Variant Attribute'!$A$2:$A$2000&"|"&'Product Variant Attribute'!$D$2:$D$2000,'Product Variant Attribute'!$F$2:$F$2000,""),_xlfn.XLOOKUP(B73&"|ATTR-24",'Product Variant Attribute'!$A$2:$A$2000&"|"&'Product Variant Attribute'!$D$2:$D$2000,'Product Variant Attribute'!$F$2:$F$2000,""))} | F73: Hộp | G73: 50 miếng | H73: =IFERROR(--LEFT(G73,FIND(" ",G73&" ")-1),"") -> 50 | I73: =_xlfn.XLOOKUP(C73,Product!$A:$A,Product!$G:$G,"NOT FOUND") -> miếng | J73: 240000 | K73: Giá (theo biến thể) – nguồn có nhiều giá: 240000 / 260000 – khớp theo tên | L73: 102, 108 | M73: Băng gạc vô trùng Young Wound Dressing (hộp) | N73: 22, 29 | O73: ="INSERT INTO public.medical_supply_sellable_unit (code, price, quantity, sale_uom, product_variant_code) VALUES ('"&A73&"', "&IF(J73="","NULL",J73)&", "&IF(H73="","NULL",H73)&", "&IF(F73="","NULL","'"&SUBSTITUTE(F73,"'","''")&"'")&", '"&B73&"');" -> INSERT INTO public.medical_supply_sellable_unit (code, price, quantity, sale_uom, product_variant_code) VALUES ('PRODUCT-00276-001-02', 240000, 50, 'Hộp', 'PRODUCT-00276-001');
A74: =B74&"-"&TEXT(COUNTIF(B$2:B74,B74),"00") -> PRODUCT-00277-001-01 | B74: PRODUCT-00277-001 | C74: =_xlfn.XLOOKUP(B74,'Product Variant'!$A:$A,'Product Variant'!$B:$B,"NOT FOUND") -> PRODUCT-00277 | D74: =_xlfn.XLOOKUP(B74,'Product Variant'!$A:$A,'Product Variant'!$C:$C,"NOT FOUND") -> [Young Chemical Vina] Băng gạc vô trùng - Young Wound Dressing (9cmx10cm) | E74: {=_xlfn.TEXTJOIN(" / ",TRUE,_xlfn.XLOOKUP(B74&"|ATTR-27",'Product Variant Attribute'!$A$2:$A$2000&"|"&'Product Variant Attribute'!$D$2:$D$2000,'Product Variant Attribute'!$F$2:$F$2000,""),_xlfn.XLOOKUP(B74&"|ATTR-24",'Product Variant Attribute'!$A$2:$A$2000&"|"&'Product Variant Attribute'!$D$2:$D$2000,'Product Variant Attribute'!$F$2:$F$2000,""))} | F74: Túi | G74: 1 miếng | H74: =IFERROR(--LEFT(G74,FIND(" ",G74&" ")-1),"") -> 1 | I74: =_xlfn.XLOOKUP(C74,Product!$A:$A,Product!$G:$G,"NOT FOUND") -> miếng | J74: 6500 | K74: Giá (theo biến thể) – khớp theo tên | L74: 475, 416 | M74: Băng gạc vô trùng Young Wound Dressing (1 miếng) | N74: 16, 32 | O74: ="INSERT INTO public.medical_supply_sellable_unit (code, price, quantity, sale_uom, product_variant_code) VALUES ('"&A74&"', "&IF(J74="","NULL",J74)&", "&IF(H74="","NULL",H74)&", "&IF(F74="","NULL","'"&SUBSTITUTE(F74,"'","''")&"'")&", '"&B74&"');" -> INSERT INTO public.medical_supply_sellable_unit (code, price, quantity, sale_uom, product_variant_code) VALUES ('PRODUCT-00277-001-01', 6500, 1, 'Túi', 'PRODUCT-00277-001');
A75: =B75&"-"&TEXT(COUNTIF(B$2:B75,B75),"00") -> PRODUCT-00277-001-02 | B75: PRODUCT-00277-001 | C75: =_xlfn.XLOOKUP(B75,'Product Variant'!$A:$A,'Product Variant'!$B:$B,"NOT FOUND") -> PRODUCT-00277 | D75: =_xlfn.XLOOKUP(B75,'Product Variant'!$A:$A,'Product Variant'!$C:$C,"NOT FOUND") -> [Young Chemical Vina] Băng gạc vô trùng - Young Wound Dressing (9cmx10cm) | E75: {=_xlfn.TEXTJOIN(" / ",TRUE,_xlfn.XLOOKUP(B75&"|ATTR-27",'Product Variant Attribute'!$A$2:$A$2000&"|"&'Product Variant Attribute'!$D$2:$D$2000,'Product Variant Attribute'!$F$2:$F$2000,""),_xlfn.XLOOKUP(B75&"|ATTR-24",'Product Variant Attribute'!$A$2:$A$2000&"|"&'Product Variant Attribute'!$D$2:$D$2000,'Product Variant Attribute'!$F$2:$F$2000,""))} | F75: Hộp | G75: 50 miếng | H75: =IFERROR(--LEFT(G75,FIND(" ",G75&" ")-1),"") -> 50 | I75: =_xlfn.XLOOKUP(C75,Product!$A:$A,Product!$G:$G,"NOT FOUND") -> miếng | J75: 305000 | K75: Giá (theo biến thể) – khớp theo tên | L75: 103, 100 | M75: Băng gạc vô trùng Young Wound Dressing (hộp) | N75: 23, 33 | O75: ="INSERT INTO public.medical_supply_sellable_unit (code, price, quantity, sale_uom, product_variant_code) VALUES ('"&A75&"', "&IF(J75="","NULL",J75)&", "&IF(H75="","NULL",H75)&", "&IF(F75="","NULL","'"&SUBSTITUTE(F75,"'","''")&"'")&", '"&B75&"');" -> INSERT INTO public.medical_supply_sellable_unit (code, price, quantity, sale_uom, product_variant_code) VALUES ('PRODUCT-00277-001-02', 305000, 50, 'Hộp', 'PRODUCT-00277-001');
